Workbook

Sheet Vision
B2: Vision Dental Clinic
B3: Financial Report for the year Jan 2025
B4: Profit & Loss Statement
B5: Casflow Statement
D7: Profit & Loss Statement | E7: Amount | H7: %age | I7: Collection | J7: Coll % | P7: Cashflow Statement | Q7: Ref. | R7: Amount | U7: %age | X7: Differences (P&L - CF)
B8: Sales / Income: | N8: Current Period Collection:
C9: =+Sales!A7 -> Dr. Hussien Tahoun | O9: Cash & Cheque Collection of Jan 2025 | R9: =+Collection!T16 -> 9710.17 | U9: =R9/$R$25 -> 0.039780193
D10: Cash & Credit Card of Jan 2025 - (a) | E10: =+Sales!D9 -> 21054.26 | H10: =E10/$E$47 -> 0.05284223 | I10: =+Sales!H86 -> 37920.09 | J10: =+I10/E10 -> 1.801065 | O10: Credit Card Jan 2025 | R10: =+'Bank Recon'!E231 -> 194833.18 | U10: =R10/$R$25 -> 0.79818391
D11: Insurance Sales of Jan 2025 - (b) | E11: =+Sales!D17 -> 44043.4 | H11: =E11/$E$47 -> 0.11054064 | O11: Tabby, Bank Trf & Others | R11: =+Collection!M21 -> 815 | U11: =R11/$R$25 -> 0.0033388558
E12: =SUM(E10:E11) -> 65097.66 | H12: =SUM(H10:H11) -> 0.16338287 | I12: =SUM(I10:I11) -> 37920.09
O13: Total Current period Self Pay Sales Collection | Q13: (a) | R13: =R9+R10+R11 -> 205358.35 | U13: =SUM(U9:U12) -> 0.84130296
C14: =+Sales!A21 -> Dr. Salim Alhamadani | O14: Cash Collection but not deposited in bank | R14: 0
D15: Cash & Credit Card of Jan 2025 - (c) | E15: =+Sales!D23 -> 27524.4 | H15: =E15/$E$47 -> 0.069081064 | I15: =+Sales!H101 -> 18228.77 | J15: =+I15/E15 -> 0.66227674 | O15: Insurance Collection for the Year | R15: =+'Claim Sheet'!J16 -> 38737.25 | U15: =R15/$R$25 -> 0.15869704
D16: Insurance Sales of Jan 2025 - (d) | E16: =+Sales!D32 -> 53387.66 | H16: =E16/$E$47 -> 0.13399298
E17: =SUM(E15:E16) -> 80912.06 | H17: =SUM(H15:H16) -> 0.20307404 | I17: =SUM(I15:I16) -> 18228.77 | O17: Total Previous month Sales Collection | Q17: (b) | R17: =SUM(R14:R15) -> 38737.25 | U17: =SUM(U13:U15) -> 1
C19: =+Sales!A36 -> Dr. Asma Butt
D20: Cash & Credit Card of Jan 2025 - (e) | E20: =+Sales!D38 -> 30110.9 | H20: =E20/$E$47 -> 0.075572692 | I20: =+Sales!H78 -> 29434.62 | J20: =+I20/E20 -> 0.97754036
D21: Insurance Sales of Jan 2025 - (f) | E21: =+Sales!D47 -> 51530.26 | H21: =E21/$E$47 -> 0.12933125 | O21: Grand Total of Sales Collection | Q21: (c = a+b) | R21: =R17+R13 -> 244095.6 | U21: =R21/$R$25 -> 1
E22: =SUM(E20:E21) -> 81641.16 | H22: =SUM(H20:H21) -> 0.20490395 | I22: =SUM(I20:I21) -> 29434.62 | O22: Collection from Vending Machine | Q22: (d) | R22: 0 | U22: =R22/$R$25 -> 0
O23: Other Refunds | Q23: (e) | R23: 0 | U23: =R23/$R$25 -> 0
C24: =+Sales!A51 -> Dr. Amr Labib | O24: Loan Fund | Q24: (f) | R24: 0 | U24: =R24/$R$25 -> 0
D25: Cash & Credit Card of Jan 2025 - (e) | E25: =+Sales!D52 -> 1723.98 | H25: =E25/$E$47 -> 0.0043268653 | I25: =+Sales!H72 -> 13772.98 | J25: =+I25/E25 -> 7.9890602 | O25: Total Collection Received | Q25: (g= c+d+e+f) | R25: =R21+R22+R23+R24 -> 244095.6 | U25: =U21+U22+U23+U24 -> 1
D26: Insurance Sales of Jan 2025 - (f) | E26: =+Sales!D62 -> 2756 | H26: =E26/$E$47 -> 0.0069170413
E27: =SUM(E25:E26) -> 4479.98 | H27: =SUM(H25:H26) -> 0.011243907 | I27: =SUM(I25:I26) -> 13772.98
C29: =+Sales!A67 -> Dr. Ammar
D30: Cash & Credit Card of Jan 2025 - (e) | E30: =+Sales!D69 -> 20773.99 | H30: =E30/$E$47 -> 0.052138805 | I30: =+Sales!H64 -> 12470.83 | J30: =+I30/E30 -> 0.60030981
D31: Insurance Sales of Jan 2025 - (f) | E31: =+Sales!D78 -> 107379.65 | H31: =E31/$E$47 -> 0.26950271
E32: =SUM(E30:E31) -> 128153.64 | H32: =SUM(H30:H31) -> 0.32164152 | I32: =SUM(I30:I31) -> 12470.83
C34: =+Sales!A85 -> Dr. Ibrahim
D35: Cash & Credit Card of Jan 2025 - (e) | E35: =+Sales!D87 -> 18013.22 | H35: =E35/$E$47 -> 0.045209792 | I35: =+Sales!H94 -> 12406.26 | J35: =+I35/E35 -> 0.68873083
D36: Insurance Sales of Jan 2025 - (f) | E36: =+Sales!D96 -> 20138.53 | H36: =E36/$E$47 -> 0.05054392
E37: =SUM(E35:E36) -> 38151.75 | H37: =SUM(H35:H36) -> 0.095753712 | I37: =SUM(I35:I36) -> 12406.26
C40: Other Income
D41: External LAB | E41: 0
C43: Total
D44: Cash & Credit Card of Jan 2025 - (i = a+c+e+g) | E44: =E10+E15+E20+E30+E25+E35 -> 119200.75 | H44: =E44/$E$47 -> 0.29917145 | I44: =I12+I17+I22+I32+I27+I37 -> 124233.55 | J44: =+I44/E44 -> 1.0422212
D45: Insurance Sales of Jan 2025 - (j = b+d+f+h) | E45: =E11+E16+E21+E31+E26+E36 -> 279235.5 | H45: =E45/$E$47 -> 0.70082855 | I45: 0
D46: Other Income | E46: 0 | H46: =E46/$E$47 -> 0
E47: =SUM(E44:E46) -> 398436.25 | H47: =SUM(H44:H46) -> 1 | I47: =SUM(I44:I46) -> 124233.55 | J47: =+I47/E44 -> 1.0422212
X48: =-E47+R25 -> -154340.65
D49: -
B50: Less: | N50: Less:
B51: Direct Expenses: | E51: - | N51: Direct Expenses Payment:
C52: Consumables / LAB | O52: Inventory Purchased
D53: Consumables -( Dr. H.T /-, Dr. S /- ,Dr. Asma /- , Dr. Ammar /- , Dr. Amr , VIP1 /- , VIP2/-) | E53: =+GETPIVOTDATA(" Transaction Value ",'Pivot Movement'!$A$2,"Transaction Type","02- Usage","Supplier/Customer Name","13- VIP 1")+GETPIVOTDATA(" Transaction Value ",'Pivot Movement'!$A$2,"Transaction Type","02- Usage","Supplier/Customer Name","14- VIP 2")+GETPIVOTDATA(" Transaction Value ",'Pivot Movement'!$A$2,"Transaction Type","02- Usage","Supplier/Customer Name","04- Clinic 1")+GETPIVOTDATA(" Transaction Value ",'Pivot Movement'!$A$2,"Transaction Type","02- Usage","Supplier/Customer Name","05- Clinic 2")+GETPIVOTDATA(" Transaction Value ",'Pivot Movement'!$A$2,"Transaction Type","02- Usage","Supplier/Customer Name","06- Clinic 3")+GETPIVOTDATA(" Transaction Value ",'Pivot Movement'!$A$2,"Transaction Type","02- Usage","Supplier/Customer Name","07- Clinic 4")+GETPIVOTDATA(" Transaction Value ",'Pivot Movement'!$A$2,"Transaction Type","03- Internal Return","Supplier/Customer Name","13- VIP 1")+GETPIVOTDATA(" Transaction Value ",'Pivot Movement'!$A$2,"Transaction Type","03- Internal Return","Supplier/Customer Name","14- VIP 2") -> -80969.674 | H53: =-(E53/$E$47) -> 0.20321864 | P53: Payment against Purchases of Jan 2025 | R53: =-GETPIVOTDATA("Amount",'Pivot cash in hand'!$A$1,"Category","01- Equipment and Supply","Sub-Category","01- Consumables / New Invoice Payment") -> -4948.97 | U53: =-(R53/$R$25) -> 0.02027472
D54: Consumables - ( CSSD /- , Vital - /-, PAN - /- , ADRC /- , CVM-) | E54: =+GETPIVOTDATA(" Transaction Value ",'Pivot Movement'!$A$2,"Transaction Type","02- Usage","Supplier/Customer Name","01- Reception Area")+GETPIVOTDATA(" Transaction Value ",'Pivot Movement'!$A$2,"Transaction Type","02- Usage","Supplier/Customer Name","02- Triage/OPG Room")+GETPIVOTDATA(" Transaction Value ",'Pivot Movement'!$A$2,"Transaction Type","02- Usage","Supplier/Customer Name","03- CSSD / Washrooms")+GETPIVOTDATA(" Transaction Value ",'Pivot Movement'!$A$2,"Transaction Type","02- Usage","Supplier/Customer Name","12- Coffee Vending Machine") -> -4963.3099 | H54: =-(E54/$E$47) -> 0.012456974 | P54: Payment against Purchase of previous months | R54: =-GETPIVOTDATA("Amount",'Pivot cash in hand'!$A$1,"Category","01- Equipment and Supply","Sub-Category","02- Consumables / Old Invoice Payment") -> -57892.7 | U54: =-(R54/$R$25) -> 0.23717224
D55: Internal LAB (/-) | E55: =+GETPIVOTDATA(" Transaction Value ",'Pivot Movement'!$A$2,"Transaction Type","02- Usage","Supplier/Customer Name","10- Internal Laboratory") -> -14324.503 | H55: =-(E55/$E$47) -> 0.035951807 | P55: External LAB | R55: =-GETPIVOTDATA("Amount",'Pivot cash in hand'!$A$1,"Category","01- Equipment and Supply","Sub-Category","05- External Lab / New Invoice Payment")-GETPIVOTDATA("Amount",'Pivot cash in hand'!$A$1,"Category","01- Equipment and Supply","Sub-Category","06- External Lab / Old Invoice Payment") -> -1870 | U55: =-(R55/$R$25) -> 0.0076609328
D56: External LAB | E56: =-GETPIVOTDATA("Amount",'Pivot cash in hand'!$A$1,"Category","01- Equipment and Supply","Sub-Category","05- External Lab / New Invoice Payment")-GETPIVOTDATA("Amount",'Pivot cash in hand'!$A$1,"Category","01- Equipment and Supply","Sub-Category","06- External Lab / Old Invoice Payment") -> -1870 | H56: =-(E56/$E$47) -> 0.0046933481 | R56: =SUM(R53:R55) -> -64711.67 | U56: =SUM(U53:U55) -> 0.26510789
D57: Disposal/Expired | E57: 0 | H57: =-(E57/$E$47) -> 0
E58: =SUM(E53:E57) -> -102127.49 | H58: =SUM(H53:H57) -> 0.25632077 | X58: =(-E58+R56) -> 37415.817
C59: Salaries | O59: Salaries
D60: Doctor' Salary for Jan 2025 | E60: =-GETPIVOTDATA("Net Salary",Salary!$E$2,"Head","Doctor") -> -174061.73 | H60: =-(E60/$E$47) -> 0.43686219 | P60: Doctor' Salary | R60: =-GETPIVOTDATA("Net Salary",Salary!$S$50,"Head","Doctors Salary") -> -157808 | U60: =-(R60/$R$25) -> 0.6465008
D61: Nurses' Salary for Jan 2025 | E61: =-GETPIVOTDATA("Net Salary",Salary!$E$2,"Head","nurse") -> -34140.323 | H61: =-(E61/$E$47) -> 0.085685784 | P61: Nurses' Salary | R61: =-GETPIVOTDATA("Net Salary",Salary!$S$50,"Head","Nurse Direct")-GETPIVOTDATA("Net Salary",Salary!$S$58,"Head","Nurse Direct") -> -39150 | U61: =-(R61/$R$25) -> 0.16038798
D62: Indirect Staff Salaries for Jan 2025 | E62: =-GETPIVOTDATA("Net Salary",Salary!$E$2,"Head","indirect")-GETPIVOTDATA("Net Salary",Salary!$E$2,"Head","external") -> -125272.56 | H62: =-(E62/$E$47) -> 0.31441055 | P62: Indirect Staff Salaries | R62: =-GETPIVOTDATA("Net Salary",Salary!$S$50,"Head","External")-GETPIVOTDATA("Net Salary",Salary!$S$50,"Head","indirect")-GETPIVOTDATA("Net Salary",Salary!$S$58,"Head","indirect") -> -121563 | U62: =-(R62/$R$25) -> 0.49801389
D63: Final Settelement | E63: 0 | H63: =-(E63/$E$47) -> 0 | P63: Final Settelement | R63: 0 | U63: =-(R63/$R$25) -> 0
E64: =SUM(E60:E63) -> -333474.62 | H64: =SUM(H60:H63) -> 0.83695853 | R64: =SUM(R60:R63) -> -318521 | U64: =SUM(U60:U63) -> 1.3049027 | X64: =(-E64+R64) -> 14953.616
B65: In-Direct Expenses: | N65: In-Direct Expenses Payment:
C66: Third Party Consultancy | E66: =-GETPIVOTDATA("Amount",'Pivot cash in hand'!$A$1,"Category","04- Legal and Professionalism","Sub-Category","07- 3rd Party Consultancy") -> -8732.85 | H66: =-(E66/$E$47) -> 0.02191781 | O66: Third Party Consultancy | R66: =-GETPIVOTDATA("Amount",'Pivot cash in hand'!$A$1,"Category","04- Legal and Professionalism","Sub-Category","07- 3rd Party Consultancy") -> -8732.85 | U66: =-(R66/$R$25) -> 0.035776352
C67: General Running and Maintenance | E67: =-GETPIVOTDATA("Amount",'Pivot cash in hand'!$A$1,"Category","02- General Running and Maintenance") -> -18988.8 | H67: =-(E67/$E$47) -> 0.047658314 | O67: General Running and Maintenance | R67: =-GETPIVOTDATA("Amount",'Pivot cash in hand'!$A$1,"Category","02- General Running and Maintenance") -> -18988.8 | U67: =-(R67/$R$25) -> 0.077792471
C68: Legal and Professionalism | E68: =-GETPIVOTDATA("Amount",'Pivot cash in hand'!$A$1,"Category","04- Legal and Professionalism")+GETPIVOTDATA("Amount",'Pivot cash in hand'!$A$1,"Category","04- Legal and Professionalism","Sub-Category","07- 3rd Party Consultancy") -> -61791.9 | H68: =-(E68/$E$47) -> 0.15508604 | O68: Legal and Professionalism | R68: =-GETPIVOTDATA("Amount",'Pivot cash in hand'!$A$1,"Category","04- Legal and Professionalism")+GETPIVOTDATA("Amount",'Pivot cash in hand'!$A$1,"Category","04- Legal and Professionalism","Sub-Category","07- 3rd Party Consultancy") -> -61791.9 | U68: =-(R68/$R$25) -> 0.25314631
C69: Staff Qualification And Education | E69: =-GETPIVOTDATA("Amount",'Pivot cash in hand'!$A$1,"Category","03- Staff Qualification And Education (HR)","Sub-Category","04- Staff Benefits and Bonus")-GETPIVOTDATA("Amount",'Pivot cash in hand'!$A$1,"Category","03- Staff Qualification And Education (HR)","Sub-Category","05- Training") -> -6309.99 | H69: =-(E69/$E$47) -> 0.015836887 | O69: Staff Qualification And Education | R69: =-GETPIVOTDATA("Amount",'Pivot cash in hand'!$A$1,"Category","03- Staff Qualification And Education (HR)","Sub-Category","04- Staff Benefits and Bonus")-GETPIVOTDATA("Amount",'Pivot cash in hand'!$A$1,"Category","03- Staff Qualification And Education (HR)","Sub-Category","05- Training") -> -6309.99 | U69: =-(R69/$R$25) -> 0.025850486
C70: Office Rent forJan 2025 | E70: -13916.67 | H70: =-(E70/$E$47) -> 0.034928223 | O70: Office Rent | R70: 0 | U70: =-(R70/$R$25) -> 0
C71: Equipments Maintenance | E71: =-GETPIVOTDATA("Amount",'Pivot cash in hand'!$A$1,"Category","01- Equipment and Supply","Sub-Category","04- Equipments Maintenance") -> -1000 | H71: =-(E71/$E$47) -> 0.0025098118 | O71: Fixed Assets Purchased | R71: =-GETPIVOTDATA("Amount",'Pivot cash in hand'!$A$1,"Category","01- Equipment and Supply","Sub-Category","03- Fixed Asset Purchase") -> -13619 | U71: =-(R71/$R$25) -> 0.055793714
O72: Equipments Maintenance | R72: =-GETPIVOTDATA("Amount",'Pivot cash in hand'!$A$1,"Category","01- Equipment and Supply","Sub-Category","04- Equipments Maintenance") -> -1000 | U72: =-(R72/$R$25) -> 0.0040967555
C74: Total Indirect Expenses | E74: =SUM(E66:E72) -> -110740.21 | H74: =SUM(H66:H72) -> 0.27793709 | O74: Total Indirect Payment | R74: =SUM(R66:R73) -> -110442.54 | U74: =SUM(U66:U73) -> 0.45245609 | X74: =(-SUM(E66:E71)+SUM(R66:R73)) -> 297.67
O76: Fund Return & Invested | R76: =+Collection!M29-Collection!M35 -> 45500 | U76: =-(R76/$R$25) -> -0.18640238 | X76: =+R76 -> 45500
O77: Loan Repayment | R77: =-Collection!M45 -> -29166.67 | U77: =-(R77/$R$25) -> 0.11948872 | X77: =+R77 -> -29166.67
C80: Total Expense | E80: =E74+E64+E58 -> -546342.31 | H80: =-(E80/$E$47) -> 1.3712164 | O80: Total Payments | R80: =R76+R74+R64+R56+R77+R78 -> -477341.88 | U80: =-(R80/$R$25) -> 1.955553
X81: =+R81 -> 0
B83: Profit & (Loss) for the month of Jan 2025 | E83: =E47+E80 -> -147906.06 | H83: =(E83/$E$47) -> -0.37121638 | N83: CashFlow Movement for the month of Jan 2025 | R83: =R25+R80+R81 -> -233246.28 | U83: =(R83/$R$25) -> -0.95555299 | X83: =SUM(X9:X81) -> -85340.216
B87: Mysmile
B88: Financial Report for the month of Jan 2025
B89: Profit & Loss Statement
B90: Casflow Statement
D92: Profit & Loss Statement | E92: Amount
C94: Sales / Income: | E94: 0
C96: Other Income
E97: 0
C99: Total
D100: Other Income | E100: 0
E101: =SUM(E100:E100) -> 0
D103: -
B104: Less:
B105: Direct Expenses: | E105: -
C106: Consumables / LAB
D107: Consumables -( Dr. H.T /-, Dr. S /- ,Dr. Asma /- , Dr. Ammar /- , Dr. Amr , VIP1 /- , VIP2/-)
D108: Consumables - ( CSSD /- , Vital - /-, PAN - /- , ADRC /- , CVM-)
D109: Internal LAB (/-)
D110: External LAB
D111: Disposal/Expired | E111: 0
E112: =SUM(E107:E111) -> 0
B114: Direct Expenses:
B115: Consumables / LAB
C116: Consumables -( Dr. H.T /-, Dr. S /- ,Dr. Asma /- , Dr. Ammar /- , Dr. Amr , VIP1 /- , VIP2/-) | E116: =+'Pivot Movement'!C102+'Pivot Movement'!C95+'Pivot Movement'!C96+'Pivot Movement'!C97+'Pivot Movement'!C100+'Pivot Movement'!C101+'Pivot Movement'!C104+'Pivot Movement'!C105 -> 0 | G116: =-(E116/$E$47) -> 0
C117: Consumables - ( CSSD /- , Vital - /-, PAN - /- , ADRC /- , CVM-) | E117: =+'Pivot Movement'!C92+'Pivot Movement'!C93+'Pivot Movement'!C94+'Pivot Movement'!C99 -> 0 | G117: =-(E117/$E$47) -> 0
C118: Internal LAB (/-) | E118: =+'Pivot Movement'!C210 -> 0 | G118: =-(E118/$E$47) -> 0
C119: External LAB | E119: =-'Pivot cash in hand'!C67 -> 0 | G119: =-(E119/$E$47) -> 0
C120: Disposal/Expired | E120: 0 | G120: =-(E120/$E$47) -> 0
E121: =SUM(E116:E120) -> 0 | G121: =SUM(G116:G120) -> 0
C122: Salaries
...

Sheet Pivot cash in hand
A1: Row Labels | B1: Sum of Amount
A2: 01- Equipment and Supply | B2: 79330.67
A3: 01- Consumables / New Invoice Payment | B3: 4948.97
A4: 02- Consumables / Old Invoice Payment | B4: 57892.7
A5: 03- Fixed Asset Purchase | B5: 13619
A6: 05- External Lab / New Invoice Payment | B6: 1470
A7: 04- Equipments Maintenance | B7: 1000
A8: 06- External Lab / Old Invoice Payment | B8: 400
A9: 02- General Running and Maintenance | B9: 18988.8
A10: 02- Office Supplies and Stationery | B10: 810.06
A11: 05- Pantry | B11: 1602.63
A12: 07- Miscellaneous | B12: 2138.76
A13: 04- Transportation and Vehicle | B13: 1435.77
... A35: Grand Total | B35: 1025870.1

Sheet Cash_in_hand_Jan 2025
A1: Serial Num | B1: Date | C1: Transaction Type | D1: Treasury Type | E1: Category | F1: Sub-Category | G1: Agency | H1: Person In Charge | I1: Vision Desc | J1: Descriptions | K1: Internal document No. | L1: External document No. | M1: Amount | N1: Vat Amount | O1: Vat Eligibility | P1: Remarks
A2: 12600 | B2: 45658 | C2: 01- Paid to: | D2: 02- Electronic Treasury | E2: 02- General Running and Maintenance | F2: 07- Miscellaneous | G2: Shamsin | H2: Mohamed Abdel Moniem | I2: Complementary for Patient | J2: Payment as a Complementray for PT Obaid Family #39290 | K2: 6002 | L2: N/A | M2: 36 | N2: 0
A3: 12398 | B3: 45658 | C3: 01- Paid to: | D3: 01- Main Treasury | E3: 03- Staff Qualification And Education (HR) | F3: 01- Direct Staff Salaries | G3: Lari Exchange | H3: Mohamed Abdel Moniem | I3: Salary FMO Dec2024 | J3: Salary FMO Dec2024 to Dr.Tahoun and Ms.Heba | K3: 6004 | L3: 5.4501013e+15 | M3: 140000
A4: 12399 | B4: 45658 | C4: 01- Paid to: | D4: 01- Main Treasury | E4: 03- Staff Qualification And Education (HR) | F4: 01- Direct Staff Salaries | G4: Lari Exchange | H4: Mohamed Abdel Moniem | I4: Salary FMO Dec2024 | J4: Salary FMO Dec2024 to Razel, Jorylin , Kimberly and Mariam | K4: 6005 | L4: 5.4501013e+15 | M4: 20900
A5: 12400 | B5: 45658 | C5: 01- Paid to: | D5: 01- Main Treasury | E5: 03- Staff Qualification And Education (HR) | F5: 03- External Staff Salaries | G5: Lari Exchange | H5: Mohamed Abdel Moniem | I5: Salary FMO Dec2024 | J5: Salary FMO Dec2024 to External Staff Saber, Saed , Alamghir, Arjun and Algien | K5: 6006 | L5: 5.4501013e+15 | M5: 9000
A6: 12402 | B6: 45658 | C6: 01- Paid to: | D6: 01- Main Treasury | E6: 05- Treasuries Transactions | F6: 01- Treasury Transfer | G6: Adib | H6: Mohamed Abdel Moniem | I6: Bank Transfer | J6: Bank transfer to Electronic Treasury | K6: 6008 | L6: 5.4501013e+15 | M6: 2000
A7: 12349 | B7: 45659 | C7: 01- Paid to: | D7: 02- Electronic Treasury | E7: 01- Equipment and Supply | F7: 01- Consumables / New Invoice Payment | G7: Amazon.ae | H7: Zenneth - Staff | I7: Batteries | J7: Purchase of Batteries | K7: 6131 | L7: 407-4498548-5528300 | M7: 27.1 | N7: 1.29 | O7: Not Eligible
A8: 12602 | B8: 45659 | C8: 01- Paid to: | D8: 01- Main Treasury | E8: 04- Legal and Professionalism | F8: 11- Bank Charges | G8: Lari Exchange | H8: Mohamed Abdel Moniem | I8: Lari Transfer Fee | J8: Payment for Lari Transfer Fees for Dec2024 Salary First Batch | K8: 6007 | L8: 180125796 | M8: 32.55 | N8: 1.55 | O8: Eligible
A9: 12360 | B9: 45659 | C9: 01- Paid to: | D9: 02- Electronic Treasury | E9: 04- Legal and Professionalism | F9: 02- Immigration and Labor | G9: Icp Smart Services | H9: Aasiya Siddiqa | I9: Request Fees, Issue Fees, E-service Fees, Icp Fees, Electronic Payment Fees, | J9: New Visa Issuance - Mysmyle - Moby | K9: 6129 | L9: 7258-1-977694670 | M9: 356.2 | N9: 0
A10: 12361 | B10: 45659 | C10: 01- Paid to: | D10: 02- Electronic Treasury | E10: 04- Legal and Professionalism | F10: 02- Immigration and Labor | G10: Icp Smart Services | H10: Marife Samson | I10: Card Issuance, Electronic Payment Fees, Smart Services Fee, Request Fees, Issue Fees, E-service Fees, Icp Fees, Electronic Payment Fees, | J10: Residency and EID for Genet - Mysmyle (Attached both payments and document files in 1 LPO) | K10: 6130 | L10: 7152-1-903563028 | M10: 761.66 | N10: 0
A11: 12363 | B11: 45659 | C11: 01- Paid to: | D11: 02- Electronic Treasury | E11: 04- Legal and Professionalism | F11: 02- Immigration and Labor | G11: Icp Smart Services | H11: Marife Samson | I11: Request Fees, Issue Fees, E-service Fees, Icp Fees, Electronic Payment Fees, Card Issuance, Electronic Payment Fees, Smart Services Fee, | J11: Residency and EID for Jennifer - Mysmyle ( Both payments and files are attached in 1 LOP only ) | K11: 6132 | L11: 7154-1-908811057 | M11: 761.66 | N11: 0
A12: 12364 | B12: 45659 | C12: 01- Paid to: | D12: 02- Electronic Treasury | E12: 04- Legal and Professionalism | F12: 02- Immigration and Labor | G12: Icp Smart Services | H12: Marife Samson | I12: Request Fees, Issue Fees, E-service Fees, Icp Fees, Electronic Payment Fees, Card Issuance, Electronic Payment Fees, Smart Services Fee, | J12: Residency and EID payment for Aasiya - Mysmyle (Both payments and files are attached in 1 LPO only) | K12: 6133 | L12: 7153-1-785140435 | M12: 761.66 | N12: 0
A13: 12365 | B13: 45659 | C13: 01- Paid to: | D13: 02- Electronic Treasury | E13: 04- Legal and Professionalism | F13: 02- Immigration and Labor | G13: Icp Smart Services | H13: Aasiya Siddiqa | I13: Request Fees, E-service Fees, Icp Fees, Electronic Payment Fees, | J13: Change Status - Mysmyle - Moby | K13: 6134 | L13: 7257-1-698483155 | M13: 660.29 | N13: 0
A14: 12350 | B14: 45660 | C14: 01- Paid to: | D14: 02- Electronic Treasury | E14: 01- Equipment and Supply | F14: 01- Consumables / New Invoice Payment | G14: Amazon.ae | H14: Mohamed Abdel Moniem | I14: Clinic Supplies Purchase | J14: Purchase of Torniquet | K14: 6137 | L14: 407-1150671-9345968 | M14: 16.46
A15: 12351 | B15: 45660 | C15: 01- Paid to: | D15: 02- Electronic Treasury | E15: 01- Equipment and Supply | F15: 01- Consumables / New Invoice Payment | G15: Amazon.ae | H15: Mohamed Abdel Moniem | I15: Lab Tools and Accessories | J15: Purchase of veneers box | K15: 6138 | L15: 407-9908123-5919517 | M15: 70
A16: 12601 | B16: 45660 | C16: 01- Paid to: | D16: 02- Electronic Treasury | E16: 04- Legal and Professionalism | F16: 09- Marketing and Advertisement (PEC) | G16: Facebook | H16: Mohamed Abdel Moniem | I16: Facebook Ads | J16: Payment for facebook ads | K16: 6003 | L16: Qt4qzh4mc2 | M16: 94.37 | N16: 0
A17: 12366 | B17: 45660 | C17: 01- Paid to: | D17: 02- Electronic Treasury | E17: 04- Legal and Professionalism | F17: 02- Immigration and Labor | G17: Icp Smart Services | H17: Marife Samson | I17: Request Fees, E-service Fees, Icp Fees, Electronic Payment Fees, | J17: Residence Visa cancellation under Vision Dental Clinic- Manju Devadasan | K17: 6135 | L17: 7162-1-780862608 | M17: 204.15 | N17: 0
A18: 12616 | B18: 45660 | C18: 01- Paid to: | D18: 01- Main Treasury | E18: 04- Legal and Professionalism | F18: 02- Immigration and Labor | G18: Abu Dhabi Pension Fund | H18: Mohamed Abdel Moniem | I18: Staff Benefits | J18: Payment for Muna Mohamed Retirement Pensions | K18: 6327 | L18: MC2025X322758E | M18: 1300 | N18: 0
A19: 12418 | B19: 45660 | C19: 01- Paid to: | D19: 02- Electronic Treasury | E19: 04- Legal and Professionalism | F19: 04- Departement of health (DOH)-HAAD | G19: Tamm Doh | H19: Aasiya Siddiqa | I19: Doh- License Issuance Fee, Processing Charges, | J19: DOH Facility License Renewal - Vision Dental Clinic (Receipt include DOH application fees. Please Ignore the Application fees 100 AED receipt). Note: Check page 2 of PDF for attachment. | K19: 6136 | L19: 7255-1-209242459 | M19: 23006 | N19: 0
A20: 12352 | B20: 45661 | C20: 01- Paid to: | D20: 02- Electronic Treasury | E20: 01- Equipment and Supply | F20: 01- Consumables / New Invoice Payment | G20: New Al Daman Pharmacy Llc | H20: Mohamed Abdel Moniem | I20: Medicine for Triage | J20: Purchase of RBS Strips | K20: 6141 | L20: 820041 | M20: 80
A21: 12353 | B21: 45661 | C21: 01- Paid to: | D21: 02- Electronic Treasury | E21: 01- Equipment and Supply | F21: 01- Consumables / New Invoice Payment | G21: New Al Daman Pharmacy Llc | H21: Mohamed Abdel Moniem | I21: Medicine for Triage | J21: Purchase of RBS Lancet | K21: 6142 | L21: 820042 | M21: 40
A22: 12354 | B22: 45661 | C22: 01- Paid to: | D22: 02- Electronic Treasury | E22: 02- General Running and Maintenance | F22: 02- Office Supplies and Stationery | G22: Delight Stationery | H22: Mohamed Abdel Moniem | I22: Office Supplies and Stationery | J22: Purchase of Office Supplies | K22: 6143 | L22: CB-25-00154 | M22: 63 | N22: 3 | O22: Eligible
A23: 12355 | B23: 45661 | C23: 01- Paid to: | D23: 02- Electronic Treasury | E23: 01- Equipment and Supply | F23: 01- Consumables / New Invoice Payment | G23: Aster Pharmacy | H23: Mohamed Abdel Moniem | I23: Crash Cart Medicine | J23: Purchase of Crash Cart medicine | K23: 6145 | L23: 1245-124504-1736000537248 | M23: 35.1
A24: 12612 | B24: 45661 | C24: 01- Paid to: | D24: 02- Electronic Treasury | E24: 02- General Running and Maintenance | F24: 05- Pantry | G24: Home Centre | H24: Mohamed Abdel Moniem | I24: Pantry Supplies | J24: Payment for Door Mat | K24: 6144 | L24: 4.0006206e+19 | M24: 99 | N24: 4.71 | O24: Not Eligible
A25: 12367 | B25: 45661 | C25: 01- Paid to: | D25: 02- Electronic Treasury | E25: 04- Legal and Professionalism | F25: 09- Marketing and Advertisement (PEC) | G25: Google | H25: Mohamed Mohamed Elsamanodey | I25: Social Media Ads, | J25: Payment for Social Media ADS | K25: 6139 | L25: 7230-1-697661646 | M25: 1134.09 | N25: 0
A26: 12368 | B26: 45661 | C26: 01- Paid to: | D26: 02- Electronic Treasury | E26: 04- Legal and Professionalism | F26: 09- Marketing and Advertisement (PEC) | G26: Facebook | H26: Mohamed Mohamed Elsamanodey | I26: Facebook Ads, | J26: Payment for Facebook Ads | K26: 6140 | L26: 7229-1-558010850 | M26: 369 | N26: 0
A27: 12322 | B27: 45662 | C27: 01- Paid to: | D27: 05- Reception Treasury | E27: 02- General Running and Maintenance | F27: 07- Miscellaneous | G27: Tea Trend Cafeteria | H27: Zenneth - Staff | I27: Food for Patient | J27: juice for dr tayseer wife | K27: 6101 | L27: 24071 | M27: 10.5 | N27: 0.5 | O27: Not Eligible
A28: 12323 | B28: 45662 | C28: 01- Paid to: | D28: 05- Reception Treasury | E28: 03- Staff Qualification And Education (HR) | F28: 03- External Staff Salaries | G28: Sajed Tahoun | H28: Zenneth - Staff | I28: Salary Advance | J28: Salary advanced of Sajed Tahoun FMO December 2024 | K28: 6102 | L28: NA | M28: 100
A29: 12324 | B29: 45662 | C29: 01- Paid to: | D29: 05- Reception Treasury | E29: 02- General Running and Maintenance | F29: 04- Transportation and Vehicle | G29: Sohag Car Wash Services | H29: Zenneth - Staff | I29: Car Washing | J29: Car Wash payment for company vehicle | K29: 6103 | L29: NA | M29: 30
A30: 12325 | B30: 45662 | C30: 01- Paid to: | D30: 05- Reception Treasury | E30: 02- General Running and Maintenance | F30: 02- Office Supplies and Stationery | G30: Global Digital | H30: Zenneth - Staff | I30: Office Supplies and Stationery | J30: Purchase of Matt Paper Printing | K30: 6104 | L30: 39258 | M30: 21 | N30: 1 | O30: Eligible
A31: 12327 | B31: 45662 | C31: 01- Paid to: | D31: 05- Reception Treasury | E31: 03- Staff Qualification And Education (HR) | F31: 04- Staff Benefits and Bonus | G31: Abu Dhabi Coop | H31: Zenneth - Staff | I31: Staff Benefits | J31: Purchase of Food Supplies for Staff | K31: 6106 | L31: 193011004391 | M31: 1000 | N31: 47.62 | O31: Not Eligible
A32: 12328 | B32: 45662 | C32: 01- Paid to: | D32: 05- Reception Treasury | E32: 02- General Running and Maintenance | F32: 07- Miscellaneous | G32: Abu Dhabi Coop | H32: Zenneth - Staff | I32: Food for Patient | J32: Purchase of Food for Patient 34586 | K32: 6107 | L32: 19201100438222-19201100437382 | M32: 32.5 | N32: 1.55 | O32: Not Eligible
A33: 12329 | B33: 45662 | C33: 01- Paid to: | D33: 05- Reception Treasury | E33: 01- Equipment and Supply | F33: 01- Consumables / New Invoice Payment | G33: ABDU Market LLC | H33: Zenneth - Staff | I33: Cleaning Materials (Gloves & Mop) | J33: Purchase of Gloves | K33: 6108 | L33: 001-186147 | M33: 14 | N33: 0.67 | O33: Not Eligible
A34: 12330 | B34: 45662 | C34: 01- Paid to: | D34: 05- Reception Treasury | E34: 02- General Running and Maintenance | F34: 04- Transportation and Vehicle | G34: National Taxi | H34: Zenneth - Staff | I34: Taxi Fare | J34: Taxi Fare for Chart Collection | K34: 6109 | L34: 8681 | M34: 24
A35: 12331 | B35: 45662 | C35: 01- Paid to: | D35: 05- Reception Treasury | E35: 02- General Running and Maintenance | F35: 01- General Maintenance | G35: Rowad Al Ebtekar | H35: Zenneth - Staff | I35: General Maintenance and fixtures | J35: Payment for Furniture fixing for clinic 3 | K35: 6110 | L35: 408 | M35: 220
A36: 12332 | B36: 45662 | C36: 01- Paid to: | D36: 05- Reception Treasury | E36: 02- General Running and Maintenance | F36: 01- General Maintenance | G36: Continental Electrical Trading Est. | H36: Zenneth - Staff | I36: General Maintenance- Saber | J36: Purchase of Light Bulb | K36: 6111 | L36: 119853 | M36: 31.5 | N36: 1.5 | O36: Not Eligible
A37: 12333 | B37: 45662 | C37: 01- Paid to: | D37: 05- Reception Treasury | E37: 03- Staff Qualification And Education (HR) | F37: 04- Staff Benefits and Bonus | G37: Perfect Zone Automatic Laundry | H37: Zenneth - Staff | I37: Coat Laundry | J37: Payment for Laundry of Dr Coat | K37: 6112 | L37: 9743 | M37: 33.6 | N37: 1.6 | O37: Not Eligible
A38: 12334 | B38: 45662 | C38: 01- Paid to: | D38: 05- Reception Treasury | E38: 02- General Running and Maintenance | F38: 01- General Maintenance | G38: Continental Electrical Trading Est. | H38: Zenneth - Staff | I38: General Maintenance- Saber | J38: Purchase of Light Bulb | K38: 6113 | L38: 119864 | M38: 5.25 | N38: 0.25 | O38: Not Eligible
A39: 12345 | B39: 45662 | C39: 01- Paid to: | D39: 02- Electronic Treasury | E39: 03- Staff Qualification And Education (HR) | F39: 04- Staff Benefits and Bonus | G39: Baqala Golden Tulip | H39: Zenneth - Staff | I39: Top Up for Facility Mobiles | J39: Top up for Ortho Mobile | K39: 6124 | L39: 30951160071 | M39: 52
A40: 12406 | B40: 45662 | C40: 01- Paid to: | D40: 01- Main Treasury | E40: 01- Equipment and Supply | F40: 02- Consumables / Old Invoice Payment | G40: Three Dimensions Me General Trading Llc | H40: Helen Dacayo | I40: 3d Ink Shade Bl, Delivery Charge, | J40: 3D INK Shade | K40: 6020 | L40: 7148-1-137367430-02928-24 | M40: 2126.25 | N40: 101.25 | O40: Eligible
A41: 12521 | B41: 45663 | C41: 02- Received from: | D41: 05- Reception Treasury | E41: 05- Treasuries Transactions | F41: 01- Treasury Transfer | G41: Adib | H41: Mohamed Abdel Moniem | I41: Cash withdrawal | J41: Cash withdrawal from Electronic Treasury | K41: 1342 | L41: SEQ 2121 | M41: 100
A42: 12529 | B42: 45663 | C42: 02- Received from: | D42: 01- Main Treasury | E42: 05- Treasuries Transactions | F42: 01- Treasury Transfer | G42: Patient | H42: Mohamed Abdel Moniem | I42: Income received | J42: Income Received from Patient Anna Spynka #36269 as Bank transfer | K42: 1350 | L42: INV/38646 | M42: 500
A43: 12356 | B43: 45663 | C43: 01- Paid to: | D43: 02- Electronic Treasury | E43: 02- General Running and Maintenance | F43: 05- Pantry | G43: City Max | H43: Mohamed Abdel Moniem | I43: Pantry Supplies | J43: Purchase of Pantry Supplies . tea and coffee | K43: 6146 | L43: 109 | M43: 48.22 | N43: 2.3 | O43: Not Eligible
A44: 12357 | B44: 45663 | C44: 01- Paid to: | D44: 02- Electronic Treasury | E44: 05- Treasuries Transactions | F44: 01- Treasury Transfer | G44: Adib | H44: Mohamed Abdel Moniem | I44: Cash withdrawal | J44: Cash Withdrawal for Reception Treasury. | K44: 6147 | L44: SEQ 2121 | M44: 100
A45: 12618 | B45: 45663 | C45: 01- Paid to: | D45: 01- Main Treasury | E45: 05- Treasuries Transactions | F45: 01- Treasury Transfer | G45: Adib | H45: Mohamed Abdel Moniem | I45: Bank Transfer | J45: Bank transfer to Electronic Treasury | K45: 6328 | L45: 5.4506013e+15 | M45: 3000
A46: 12619 | B46: 45663 | C46: 01- Paid to: | D46: 01- Main Treasury | E46: 01- Equipment and Supply | F46: 05- External Lab / New Invoice Payment | G46: Staff | H46: Mohamed Abdel Moniem | I46: External Lab | J46: Barcode Payment for LAB Mchine (10 Paper *75 =750AED | K46: 6329 | L46: 5.4506013e+15 | M46: 750 | N46: 0
A47: 12484 | B47: 45663 | C47: 02- Received from: | D47: 02- Electronic Treasury | E47: 05- Treasuries Transactions | F47: 01- Treasury Transfer | G47: Adib | H47: Mohamed Abdel Moniem | I47: Bank Transfer | J47: Bank transfer from Main Treasury | K47: 1340 | L47: 5.4506013e+15 | M47: 3000
A48: 12358 | B48: 45664 | C48: 01- Paid to: | D48: 02- Electronic Treasury | E48: 02- General Running and Maintenance | F48: 02- Office Supplies and Stationery | G48: Coral Mobile Phones | H48: Mohamed Abdel Moniem | I48: Office Supplies and Stationery | J48: Purchase of HDMI Cable | K48: 6148 | L48: 60715 | M48: 25 | N48: 1.19 | O48: Not Eligible
A49: 12370 | B49: 45664 | C49: 01- Paid to: | D49: 02- Electronic Treasury | E49: 01- Equipment and Supply | F49: 01- Consumables / New Invoice Payment | G49: Hachem Dental Care Llc | H49: Helen Dacayo | I49: Ceramic Polisher, | J49: Dental Use requested by Dr.Ammar | K49: 6149 | L49: 7172-1-263972997 | M49: 135 | N49: 0
A50: 12520 | B50: 45665 | C50: 01- Paid to: | D50: 07- Main Treasury- Mysmile | E50: 03- Staff Qualification And Education (HR) | F50: 02- Indirect Staff Salaries | G50: Lari Exchange | H50: Mohamed Abdel Moniem | I50: Salary FMO Dec2024 | J50: Salary FMO Dec2024 to Myrna and Genet | K50: 1 | L50: 5.4508013e+15 | M50: 3850
A51: 12522 | B51: 45665 | C51: 02- Received from: | D51: 05- Reception Treasury | E51: 05- Treasuries Transactions | F51: 01- Treasury Transfer | G51: Adib | H51: Mohamed Abdel Moniem | I51: Cash withdrawal | J51: Cash withdrawal from Electronic Treasury | K51: 1343 | L51: SEQ 4334 | M51: 200
A52: 12523 | B52: 45665 | C52: 02- Received from: | D52: 05- Reception Treasury | E52: 05- Treasuries Transactions | F52: 01- Treasury Transfer | G52: Adib | H52: Mohamed Abdel Moniem | I52: Cash withdrawal | J52: Cash withdrawal from Electronic Treasury | K52: 1344 | L52: SEQ 4335 | M52: 100
A53: 12621 | B53: 45665 | C53: 01- Paid to: | D53: 01- Main Treasury | E53: 01- Equipment and Supply | F53: 04- Equipments Maintenance | G53: Three Q Dental And Medical Supplies Llc | H53: Zenneth | J53: LAB Machine Calibration | K53: 6331 | L53: 6733-1-412713833-TQDMS-00192 | M53: 1000 | N53: 0
A54: 12622 | B54: 45665 | C54: 01- Paid to: | D54: 01- Main Treasury | E54: 01- Equipment and Supply | F54: 02- Consumables / Old Invoice Payment | G54: Fala Trading | H54: Zenneth | J54: 3D INK Shade A3 , Bl12 , A13 and Zirconia Beads | K54: 6330 | L54: 6726-1-215026638-1024 | M54: 2205 | N54: 105 | O54: Eligible
A55: 12623 | B55: 45665 | C55: 01- Paid to: | D55: 01- Main Treasury | E55: 01- Equipment and Supply | F55: 03- Fixed Asset Purchase | G55: Ahmed Saboura | H55: Zenneth | I55: Lab Sofware, | J55: Payment For Exocad Training (Software Support) | K55: 6332 | L55: 7365-1-604322726 | M55: 2500 | N55: 0
A56: 12624 | B56: 45665 | C56: 01- Paid to: | D56: 01- Main Treasury | E56: 02- General Running and Maintenance | F56: 03- Utilities and Communications | G56: Etisalat | H56: Mohamed Abdel Moniem | I56: Etisalat Bill | J56: Etisalat Bill FMO Dec2024 to Ms.Heba Hamdy | K56: 6333 | L56: INV/1945826979 | M56: 838.1 | N56: 39.91 | O56: Not Eligible
A57: 12375 | B57: 45665 | C57: 01- Paid to: | D57: 02- Electronic Treasury | E57: 03- Staff Qualification And Education (HR) | F57: 04- Staff Benefits and Bonus | G57: LIFE PHARMACY LLC | H57: Mohamed Abdel Moniem | I57: Medicine for Staff | J57: Purchase of Medicine for Staff | K57: 6151 | L57: 1.399021e+16 | M57: 75.6 | N57: 3.6 | O57: Not Eligible
A58: 12376 | B58: 45665 | C58: 01- Paid to: | D58: 02- Electronic Treasury | E58: 05- Treasuries Transactions | F58: 01- Treasury Transfer | G58: Adib | H58: Mohamed Abdel Moniem | I58: Cash withdrawal | J58: Cash Withdrawal for Reception treasury | K58: 6152 | L58: 4334 | M58: 200
A59: 12377 | B59: 45665 | C59: 01- Paid to: | D59: 02- Electronic Treasury | E59: 05- Treasuries Transactions | F59: 01- Treasury Transfer | G59: Adib | H59: Mohamed Abdel Moniem | I59: Cash withdrawal | J59: Cash Withdrawal for Reception Treasury | K59: 6153 | L59: 4335 | M59: 100
A60: 12410 | B60: 45665 | C60: 01- Paid to: | D60: 01- Main Treasury | E60: 02- General Running and Maintenance | F60: 03- Utilities and Communications | G60: Addc- Abu Dhabi Distribution Company | H60: Aasiya Siddiqa | I60: Utility Bills, | J60: TAQA bill - Electricity & water - Mysmyle - Dec 2024 | K60: 6192 | L60: 7241-1-162608280 | M60: 879.94 | N60: 0
A61: 12411 | B61: 45665 | C61: 01- Paid to: | D61: 01- Main Treasury | E61: 02- General Running and Maintenance | F61: 03- Utilities and Communications | G61: Etisalat | H61: Aasiya Siddiqa | I61: Etisalat Landline, | J61: Etisalat bill payment - Dec 2024 (02-6224700) | K61: 6193 | L61: 7242-1-962336822 | M61: 115.5 | N61: 0
A62: 12412 | B62: 45665 | C62: 01- Paid to: | D62: 01- Main Treasury | E62: 02- General Running and Maintenance | F62: 03- Utilities and Communications | G62: Etisalat | H62: Aasiya Siddiqa | I62: Etisalat Landline, | J62: Etisalat bill payment - Vision dental clinic - Dec 2024 (02-6313110) | K62: 6194 | L62: 7243-1-112374598 | M62: 99.75 | N62: 0
A63: 12413 | B63: 45665 | C63: 01- Paid to: | D63: 01- Main Treasury | E63: 02- General Running and Maintenance | F63: 03- Utilities and Communications | G63: Etisalat | H63: Aasiya Siddiqa | I63: Etisalat Landline, | J63: Etisalat bill payment - Vision dental clinic - Dec 2024 (1222276837) | K63: 6195 | L63: 7244-1-263216310 | M63: 367.5 | N63: 0
A64: 12414 | B64: 45665 | C64: 01- Paid to: | D64: 01- Main Treasury | E64: 02- General Running and Maintenance | F64: 03- Utilities and Communications | G64: Etisalat | H64: Aasiya Siddiqa | I64: Etisalat Landline, | J64: Etisalat bill payment - Vision dental clinic - Dec 2024 ( 02-5529567 ) | K64: 6196 | L64: 7245-1-877824654 | M64: 1548.75 | N64: 0
A65: 12415 | B65: 45665 | C65: 01- Paid to: | D65: 01- Main Treasury | E65: 02- General Running and Maintenance | F65: 03- Utilities and Communications | G65: Etisalat | H65: Aasiya Siddiqa | I65: Etisalat Landline, | J65: Etisalat bill payment - Vision - Dec 2024 (02-3122777) | K65: 6197 | L65: 7246-1-329230803 | M65: 1500.26 | N65: 0
A66: 12416 | B66: 45665 | C66: 01- Paid to: | D66: 01- Main Treasury | E66: 02- General Running and Maintenance | F66: 03- Utilities and Communications | G66: Etisalat | H66: Aasiya Siddiqa | I66: Etisalat Landline, | J66: Etisalat bill payment - Vision - Dec 24 (02-5571885) | K66: 6198 | L66: 7247-1-959605606 | M66: 1569.75 | N66: 0
A67: 12417 | B67: 45665 | C67: 01- Paid to: | D67: 01- Main Treasury | E67: 02- General Running and Maintenance | F67: 03- Utilities and Communications | G67: Addc- Abu Dhabi Distribution Company | H67: Aasiya Siddiqa | I67: Utility Bills, | J67: TAQA bill payment - Mysmyle - Dec 2024 | K67: 6199 | L67: 7248-1-136291507 | M67: 1148.49 | N67: 0
A68: 12419 | B68: 45665 | C68: 01- Paid to: | D68: 01- Main Treasury | E68: 02- General Running and Maintenance | F68: 03- Utilities and Communications | G68: Etisalat | H68: Aasiya Siddiqa | I68: Etisalat Landline, | J68: Dr. Hussien Tahoun - Etisalat bill payment FMO Dec 2024 (0529992283) | K68: 6201 | L68: 7263-1-175352041 | M68: 181.53 | N68: 0
A69: 12420 | B69: 45665 | C69: 01- Paid to: | D69: 01- Main Treasury | E69: 02- General Running and Maintenance | F69: 03- Utilities and Communications | G69: Etisalat | H69: Aasiya Siddiqa | I69: Etisalat Landline, | J69: Dr. Hussien Tahoun - Etisalat payment FMO Dec 2024 (0551366843) | K69: 6202 | L69: 7264-1-423366257 | M69: 780.76 | N69: 0
A70: 12524 | B70: 45666 | C70: 02- Received from: | D70: 05- Reception Treasury | E70: 05- Treasuries Transactions | F70: 01- Treasury Transfer | G70: Adib | H70: Mohamed Abdel Moniem | I70: Cash withdrawal | J70: Cash withdrawal from Electronic Treasury | K70: 1345 | L70: SEQ 8602 | M70: 1000
A71: 12525 | B71: 45666 | C71: 02- Received from: | D71: 05- Reception Treasury | E71: 05- Treasuries Transactions | F71: 01- Treasury Transfer | G71: Adib | H71: Mohamed Abdel Moniem | I71: Cash withdrawal | J71: Cash Withdrawal from Electronic Treasury | K71: 1346 | L71: SEQ 4086 | M71: 5000
A72: 12526 | B72: 45666 | C72: 02- Received from: | D72: 05- Reception Treasury | E72: 05- Treasuries Transactions | F72: 01- Treasury Transfer | G72: Adib | H72: Mohamed Abdel Moniem | I72: Cash withdrawal | J72: Cash Withdrawal from Electronic Treasury | K72: 1347 | L72: SEQ 4087 | M72: 5000
A73: 12527 | B73: 45666 | C73: 02- Received from: | D73: 05- Reception Treasury | E73: 05- Treasuries Transactions | F73: 01- Treasury Transfer | G73: Adib | H73: Mohamed Abdel Moniem | I73: Cash withdrawal | J73: Cash Withdrawal from Electronic Treasury | K73: 1348 | L73: SEQ 4089 | M73: 5000
A74: 12528 | B74: 45666 | C74: 02- Received from: | D74: 05- Reception Treasury | E74: 05- Treasuries Transactions | F74: 01- Treasury Transfer | G74: Adib | H74: Mohamed Abdel Moniem | I74: Cash withdrawal | J74: Cash withdrawal from Electronic treasury | K74: 1349 | L74: SEQ 4088 | M74: 5000
A75: 12530 | B75: 45666 | C75: 02- Received from: | D75: 01- Main Treasury | E75: 05- Treasuries Transactions | F75: 02- Fund Invested | G75: Dr. Hussien Tahoun - Management | H75: Mohamed Abdel Moniem | I75: Fund Invested | J75: Received as Fund Invested from Dr.Tahoun | K75: 1330 | L75: 8208 | M75: 30000
A76: 12359 | B76: 45666 | C76: 01- Paid to: | D76: 02- Electronic Treasury | E76: 02- General Running and Maintenance | F76: 05- Pantry | G76: City Max | H76: Mohamed Abdel Moniem | I76: Pantry Supplies | J76: Payment for Pantry Supplies , Sugar , toilet roll | K76: 6150 | L76: 33-110 | M76: 163.94 | N76: 7.81 | O76: Not Eligible
A77: 12378 | B77: 45666 | C77: 01- Paid to: | D77: 02- Electronic Treasury | E77: 05- Treasuries Transactions | F77: 01- Treasury Transfer | G77: Adib | H77: Mohamed Abdel Moniem | I77: Cash withdrawal | J77: Cash Withdrawal for Reception Treasury | K77: 6154 | L77: 8602 | M77: 1000
A78: 12379 | B78: 45666 | C78: 01- Paid to: | D78: 02- Electronic Treasury | E78: 03- Staff Qualification And Education (HR) | F78: 04- Staff Benefits and Bonus | G78: Abu Dhabi Coop | H78: Mohamed Abdel Moniem | I78: Staff Benefits | J78: Purchase of Food Supplies for Staff | K78: 6155 | L78: 19201100439106 | M78: 257.9 | N78: 12.28 | O78: Not Eligible
A79: 12380 | B79: 45666 | C79: 01- Paid to: | D79: 02- Electronic Treasury | E79: 05- Treasuries Transactions | F79: 01- Treasury Transfer | G79: Adib | H79: Mohamed Abdel Moniem | I79: Cash withdrawal | J79: Cash Withdrawal for Reception Treasury | K79: 6156 | L79: 4086 | M79: 5000
A80: 12381 | B80: 45666 | C80: 01- Paid to: | D80: 02- Electronic Treasury | E80: 05- Treasuries Transactions | F80: 01- Treasury Transfer | G80: Adib | H80: Mohamed Abdel Moniem | I80: Cash withdrawal | J80: Cash Withdrawal for Reception Treasury | K80: 6157 | L80: 4087 | M80: 5000
A81: 12382 | B81: 45666 | C81: 01- Paid to: | D81: 02- Electronic Treasury | E81: 05- Treasuries Transactions | F81: 01- Treasury Transfer | G81: Adib | H81: Mohamed Abdel Moniem | I81: Cash withdrawal | J81: Cash withdrawal for Reception Treasury | K81: 6158 | L81: 4089 | M81: 5000
A82: 12383 | B82: 45666 | C82: 01- Paid to: | D82: 02- Electronic Treasury | E82: 05- Treasuries Transactions | F82: 01- Treasury Transfer | G82: Adib | H82: Mohamed Abdel Moniem | I82: Cash withdrawal | J82: Cash withdrawal for Reception Treasury | K82: 6159 | L82: 4088 | M82: 5000
A83: 12404 | B83: 45666 | C83: 01- Paid to: | D83: 01- Main Treasury | E83: 05- Treasuries Transactions | F83: 01- Treasury Transfer | G83: Adib | H83: Mohamed Abdel Moniem | I83: Bank Transfer | J83: Bank Transfer to Electronic Treasury | K83: 6040 | L83: 5.4509013e+15 | M83: 20000
A84: 12405 | B84: 45666 | C84: 01- Paid to: | D84: 05- Reception Treasury | E84: 05- Treasuries Transactions | F84: 03- Fund Return | G84: Dr. Hussien Tahoun - Management | H84: Mohamed Abdel Moniem | I84: Fund Return | J84: Payment as Fund Return to Dr.Tahoun RV 11425 | K84: 6041 | L84: N/A | M84: 20000
A85: 12481 | B85: 45666 | C85: 01- Paid to: | D85: 01- Main Treasury | E85: 03- Staff Qualification And Education (HR) | F85: 01- Direct Staff Salaries | G85: Lari Exchange | H85: Mohamed Abdel Moniem | I85: Salary FMO Dec2024 | J85: Salary FMO DEC2024 to Dr.Asmaa and Ibrahim Abdelkarim | K85: 6182 | L85: 5.4509013e+15 | M85: 23000
A86: 12482 | B86: 45666 | C86: 01- Paid to: | D86: 01- Main Treasury | E86: 03- Staff Qualification And Education (HR) | F86: 02- Indirect Staff Salaries | G86: Lari Exchange | H86: Mohamed Abdel Moniem | I86: Salary FMO Dec2024 | J86: Salary FMO Dec2024 to Kae, Joel , Zen , Moniem and Marife | K86: 6183 | L86: 5.4509013e+15 | M86: 18156
A87: 12485 | B87: 45666 | C87: 02- Received from: | D87: 02- Electronic Treasury | E87: 05- Treasuries Transactions | F87: 01- Treasury Transfer | G87: Adib | H87: Mohamed Abdel Moniem | I87: Bank Transfer | J87: Bank transfer from Main Treasury | K87: 1341 | L87: 5.4509013e+15 | M87: 20000
A88: 12514 | B88: 45667 | C88: 01- Paid to: | D88: 07- Main Treasury- Mysmile | E88: 03- Staff Qualification And Education (HR) | F88: 02- Indirect Staff Salaries | G88: Lari Exchange | H88: Mohamed Abdel Moniem | I88: Salary FMO Dec2024 | J88: Salary FMO Dec2024 to Hassan Labib, Aubrey , Shabna , Jennifer , Helen , Jessie ,Aasiya , Moby and Dieryl | K88: 2 | L88: 5.4509013e+15 | M88: 37400
A89: 12515 | B89: 45667 | C89: 01- Paid to: | D89: 07- Main Treasury- Mysmile | E89: 03- Staff Qualification And Education (HR) | F89: 02- Indirect Staff Salaries | G89: Lari Exchange | H89: Mohamed Abdel Moniem | I89: Salary FMO Dec2024 | J89: Salary FMO Dec2024 to Omar Alzarkan LAB | K89: 3 | L89: 5.4509013e+15 | M89: 8000
A90: 12533 | B90: 45667 | C90: 02- Received from: | D90: 01- Main Treasury | E90: 05- Treasuries Transactions | F90: 01- Treasury Transfer | G90: Daman Insurancce | H90: Mohamed Abdel Moniem | I90: Income received | J90: income received from Daman Insurance Jan01 to 10/2025 | K90: 1353 | L90: 404G2501097D23F1 404G2501077A4191 | M90: 5748.5
A91: 12534 | B91: 45667 | C91: 02- Received from: | D91: 01- Main Treasury | E91: 05- Treasuries Transactions | F91: 01- Treasury Transfer | G91: Adnic Insurance Claims | H91: Mohamed Abdel Moniem | I91: Income received | J91: Income received from Adnic INS from Jan01 to 10/2025 | K91: 1354 | L91: 404C2501077A8A3A | M91: 336
A92: 12535 | B92: 45667 | C92: 02- Received from: | D92: 01- Main Treasury | E92: 05- Treasuries Transactions | F92: 01- Treasury Transfer | G92: Nextcare Claims Mgt | H92: Mohamed Abdel Moniem | I92: Income received | J92: Income Received from NextCare INS Jan01 to 10/2025 | K92: 1355 | L92: 404C2501087AD8F2:2 | M92: 1737.6
A93: 12537 | B93: 45667 | C93: 02- Received from: | D93: 01- Main Treasury | E93: 05- Treasuries Transactions | F93: 01- Treasury Transfer | G93: Adib | H93: Mohamed Abdel Moniem | I93: Income received | J93: Income Received from POS Machine Jan01 to 10/2025 | K93: 1356 | L93: 162501100643186 162501090628230 162501080612395 162501070597287 162501060584621 162501050571057 162501030546672 162501020533282 162501010517650 | M93: 68502.78
A94: 12342 | B94: 45667 | C94: 01- Paid to: | D94: 05- Reception Treasury | E94: 02- General Running and Maintenance | F94: 05- Pantry | G94: Riviere Mineral Water | H94: Zenneth - Staff | I94: water refill | J94: Purchase of Water refill | K94: 6121 | L94: 566565 | M94: 31.5 | N94: 1.5 | O94: Not Eligible
A95: 12343 | B95: 45667 | C95: 01- Paid to: | D95: 05- Reception Treasury | E95: 03- Staff Qualification And Education (HR) | F95: 04- Staff Benefits and Bonus | G95: Kent Tailoring | H95: Zenneth - Staff | I95: Staff uniform | J95: Unifrom alteration | K95: 6122 | L95: 4864 | M95: 80
A96: 12538 | B96: 45668 | C96: 02- Received from: | D96: 02- Electronic Treasury | E96: 05- Treasuries Transactions | F96: 01- Treasury Transfer | G96: Adib | H96: Mohamed Abdel Moniem | I96: Bank Transfer | J96: Bank transfer from Main Treasury | K96: 1357 | L96: 5.4511013e+15 | M96: 3000
A97: 12620 | B97: 45668 | C97: 01- Paid to: | D97: 01- Main Treasury | E97: 05- Treasuries Transactions | F97: 01- Treasury Transfer | G97: Adib | H97: Mohamed Abdel Moniem | I97: Bank Transfer | J97: Bank Transfer to Electronic Treasury | K97: 6335 | L97: 5.4511013e+15 | M97: 3000
A98: 12384 | B98: 45668 | C98: 01- Paid to: | D98: 02- Electronic Treasury | E98: 02- General Running and Maintenance | F98: 05- Pantry | G98: Day to Day Hypermarket LLC | H98: Mohamed Abdel Moniem | I98: water refill | J98: Purchase of Water refill | K98: 6160 | L98: 91 | M98: 97.5 | N98: 4.64 | O98: Not Eligible
A99: 12386 | B99: 45668 | C99: 01- Paid to: | D99: 02- Electronic Treasury | E99: 01- Equipment and Supply | F99: 01- Consumables / New Invoice Payment | G99: Aster Pharmacy | H99: Mohamed Abdel Moniem | I99: Crash Cart Medicine | J99: Payment for PT Medicine IV Medication | K99: 6162 | L99: 12450110005221 | M99: 11.7
A100: 12387 | B100: 45668 | C100: 01- Paid to: | D100: 02- Electronic Treasury | E100: 02- General Running and Maintenance | F100: 02- Office Supplies and Stationery | G100: Delight Stationery | H100: Mohamed Abdel Moniem | I100: Office Supplies and Stationery | J100: Purchase of A4 Paper and clear tape | K100: 6163 | L100: CB-25-00368 | M100: 58.28 | N100: 2.78 | O100: Eligible
...

Sheet Pivot Movement
A1: In Value | D1: In Units
A2: Row Labels | B2: Sum of Transaction Value | D2: Row Labels | E2: Sum of Quanity
A3: 01- Purchase | B3: 62203.527 | D3: 01- Purchase | E3: 1473
A4: Al Hayat Pharmaceuticals | B4: 3545 | D4: 01- Medical & LAB Devices. Instruments- (DEV) | E4: 71
A5: City Pharmacy Co. WLL | B5: 5087.5 | D5: 06- Hand Instruments (Restorative, Perio, Endo, Implants,Ortho…) | E5: 68
A6: Panacea Synthetic Gas Trading LLC | B6: 690 | D6: 04- Hand Pieces, Scaler Devices & Accessories | E6: 2
A7: Sirona Dental Systems Trading LLC | B7: 1611 | D7: 08- Cssd, Triage, PCI Devices | E7: 1
A8: Saber Mohammed/Elwan Technical Supplies | B8: 850 | D8: 02- Drugs, Needles & Triage- (DRG) | E8: 78
A9: Jackson Trading Co. LLC | B9: 914 | D9: 03- Vital Signs/ Emergency Supplies | E9: 18
A10: Alphamed General Trading LLC | B10: 2060 | D10: 04- Needles & Syringes | E10: 60
A11: Itqan Dental Supply LLC | B11: 591 | D11: 03- Prevention & Control of Infection- (PCI) | E11: 639
A12: Sapling Drug Store | B12: 10500 | D12: 01- Personal Protective Equipment | E12: 320
A13: Bio Link Medical Surgical Equipment & Intruments Trading LLC | B13: 925 | D13: 02- Disinfectants & Lubricants | E13: 13
A14: Everest Medical & Safety Trading | B14: 7402.5304 | D14: 03- General & Waste Management | E14: 214
... A55: Grand Total | B55: -38053.96 | D55: 04- Dental Materials & Supplies- (DMS) | E55: -288.32667
D56: 01- Burs & Stones Tools | E56: -28.3
D57: 02- Nitrous & Oxygen Sedation | E57: -11
D58: 03- Scaling / Gingiva Materials & Supplies | E58: -7.365
D59: 04- Restorative Fillings, Adhesives & Supplies | E59: -34.95
D60: 05- Endodontic Materials & Posts Supplies | E60: -93.666667
D61: 06- Surgical Materials & Supplies | E61: -80.545
D62: 07- Impression Materials & Supplies | E62: -9.5
D63: 08- Bleaching Material & Supplies | E63: -5
D64: 10- Patient Education Printouts & Giveaways | E64: -18
D65: 05- Implants- (IMPL) | E65: -130
D66: 01- Implant Fixtures | E66: -48
D67: 03- Abutments | E67: -20
... D95: Grand Total | E95: 343.57667

Sheet Movement Jan 2025
A1: Movement Date | B1: Transaction Type | C1: Category | D1: Sub-Category | E1: Type | F1: Variant 1 | G1: Variant 2 (If Applicable) | H1: Vision Description (Description understood by VDC users) | I1: Quanity | J1: Unit Of Measure | K1: Vision ID | L1: Item Price (Without Vat) | M1: Item Vat ( If Applicable) | N1: Warranty Certificate | O1: Medication Alerts (For Medcines Only) | P1: Color Classification (For Electronic Devices) | Q1: Expiration / Depreciation Date | R1: Department Ownership | S1: Internal User /Agent Name | T1: Internal User ID | U1: Undertaking Staff ID / Form | V1: Location | W1: Location ID | X1: Location Index | Y1: Incident Report Attached | Z1: PPM Date (For electronic Devices) | AA1: Disposal Forms | AB1: Stock Description (the exact description as per the supplier Invoice) | AC1: Brand / Model | AD1: Supplier Details | AE1: Supplier/Customer Name | AF1: Supplier / Agency represertative | AG1: Supplier / Agency Contact Number | AH1: Financial Grading | AI1: Door Number | AJ1: Buffer Stock (1 clinic usage/ month) | AK1: LPO/IPO Number | AL1: Transaction Value | AM1: Payment Voucher Number | AN1: External Doc Num. | AO1: Invoice Amount | AP1: VAT | AQ1: Total amount | AR1: Amount Paid
A2: 45661 | B2: 01- Purchase | C2: 04- Dental Materials & Supplies- (DMS) | D2: 01- Burs & Stones Tools | E2: Burs | F2: Straight Black Cylinder Round Tip | G2: NA | H2: Straight Black Cylinder Round Tip | I2: 4 | J2: Pkt | K2: D881 SG 1.2 | L2: 60 | M2: NA | N2: NA | O2: NA | P2: NA | Q2: NA | R2: 08- FIN/INV | S2: NA | T2: NA | U2: NA | V2: 32- Main Inventory 1 | W2: NA | X2: 7.4 | Y2: NA | Z2: NA | AA2: NA | AB2: Bur - Diamond Bur #52 - Stoddard | AC2: Stoddard | AD2: Al Hana Medical Equipments | AE2: Al Hana Medical Equipments | AF2: Mahamud | AG2: +971 50 219 8081 | AH2: 02- Reusable | AI2: 7 | AJ2: 1 | AK2: LPO-7168 | AL2: 240 | AM2: - | AN2: 41750 | AO2: 240 | AP2: 12 | AQ2: 252 | AR2: -
A3: 45663 | B3: 01- Purchase | C3: 08- Facility Management & (FMS) | D3: 07- Pantry Supplies | E3: Pantry Supplies | F3: Coffee Powder | G3: NA | H3: Coffee Powder | I3: 1 | J3: Pack | K3: IGDE044 | L3: 90 | M3: NA | N3: NA | O3: NA | P3: NA | Q3: 45901 | R3: 08- FIN/INV | S3: NA | T3: NA | U3: NA | V3: 30- Main Inventory 2 | W3: NA | X3: 8.2 | Y3: NA | Z3: NA | AA3: NA | AB3: Espresso Barista C&B - 1Kg | AC3: DALLMAYR | AD3: Jackson Trading Co. LLC | AE3: Jackson Trading Co. LLC | AF3: Sales | AG3: +971 56 975 6706 | AH3: 01- Consumables | AI3: 8 | AJ3: 1 | AK3: LPO-7166 | AL3: 90 | AM3: - | AN3: AUH-32123 | AO3: 90 | AP3: 4.5 | AQ3: 94.5 | AR3: -
A4: 45663 | B4: 01- Purchase | C4: 04- Dental Materials & Supplies- (DMS) | D4: 04- Restorative Fillings, Adhesives & Supplies | E4: Restorative Fillings | F4: Ceramic Polisher | G4: NA | H4: Ceramic Polisher | I4: 1 | J4: Pcs | K4: K0200-06 | L4: 135 | M4: NA | N4: NA | O4: NA | P4: NA | Q4: NA | R4: 08- FIN/INV | S4: NA | T4: NA | U4: NA | V4: 32- Main Inventory 1 | W4: NA | X4: 8.3 | Y4: NA | Z4: NA | AA4: NA | AB4: Kenda 0200 All Ceramic 2-steps Set 6Pcs F Polish Com | AC4: KENDA | AD4: Hachem Dental Care LLC | AE4: Hachem Dental Care LLC | AF4: Hadi | AG4: +971 52 824 3223 | AH4: 02- Reusable | AI4: 8 | AJ4: 1 | AK4: LPO-7172 | AL4: 135 | AM4: - | AN4: 1000026 | AO4: 135 | AP4: 0 | AQ4: 135 | AR4: 135
A5: 45663 | B5: 01- Purchase | C5: 08- Facility Management & (FMS) | D5: 07- Pantry Supplies | E5: Pantry Supplies | F5: Milk Powder | G5: NA | H5: Milk Powder | I5: 2 | J5: Kilogram | K5: IGDT002 | L5: 60 | M5: NA | N5: NA | O5: NA | P5: NA | Q5: 45901 | R5: 08- FIN/INV | S5: NA | T5: NA | U5: NA | V5: 30- Main Inventory 2 | W5: NA | X5: 8.2 | Y5: NA | Z5: NA | AA5: NA | AB5: Dallmayr Topping | AC5: DALLMAYR | AD5: Jackson Trading Co. LLC | AE5: Jackson Trading Co. LLC | AF5: Sales | AG5: +971 56 975 6706 | AH5: 01- Consumables | AI5: 8 | AJ5: 1 | AK5: LPO-7166 | AL5: 120 | AM5: - | AN5: AUH-32123 | AO5: 120 | AP5: 6 | AQ5: 126 | AR5: -
A6: 45663 | B6: 01- Purchase | C6: 08- Facility Management & (FMS) | D6: 07- Pantry Supplies | E6: Pantry Supplies | F6: Chocolate Powder | G6: NA | H6: Chocolate Powder | I6: 3 | J6: Kilogram | K6: IGDC001 | L6: 50 | M6: NA | N6: NA | O6: NA | P6: NA | Q6: 45901 | R6: 08- FIN/INV | S6: NA | T6: NA | U6: NA | V6: 30- Main Inventory 2 | W6: NA | X6: 8.2 | Y6: NA | Z6: NA | AA6: NA | AB6: Dallmayr Premium Chocolate | AC6: DALLMAYR | AD6: Jackson Trading Co. LLC | AE6: Jackson Trading Co. LLC | AF6: Sales | AG6: +971 56 975 6706 | AH6: 01- Consumables | AI6: 8 | AJ6: 1 | AK6: LPO-7166 | AL6: 150 | AM6: - | AN6: AUH-32123 | AO6: 150 | AP6: 7.5 | AQ6: 157.5 | AR6: -
A7: 45663 | B7: 01- Purchase | C7: 08- Facility Management & (FMS) | D7: 07- Pantry Supplies | E7: Pantry Supplies | F7: Stirrer | G7: NA | H7: Stirrer | I7: 4 | J7: Bundle | K7: IGDT001 | L7: 8 | M7: NA | N7: NA | O7: NA | P7: NA | Q7: NA | R7: 08- FIN/INV | S7: NA | T7: NA | U7: NA | V7: 30- Main Inventory 2 | W7: NA | X7: 8.3 | Y7: NA | Z7: NA | AA7: NA | AB7: Automatic Stirrer 105mm | AC7: DALLMAYR | AD7: Jackson Trading Co. LLC | AE7: Jackson Trading Co. LLC | AF7: Sales | AG7: +971 56 975 6706 | AH7: 01- Consumables | AI7: 8 | AJ7: 1 | AK7: LPO-7166 | AL7: 32 | AM7: - | AN7: AUH-32123 | AO7: 32 | AP7: 1.6 | AQ7: 33.6 | AR7: -
A8: 45664 | B8: 01- Purchase | C8: 04- Dental Materials & Supplies- (DMS) | D8: 05- Endodontic Materials & Posts Supplies | E8: Endodontic Materials | F8: Endo XP Finisher | G8: NA | H8: Endo XP Finisher | I8: 3 | J8: Pack of 3pcs | K8: S1.XB0. 00.0AA .FKG | L8: 240 | M8: NA | N8: NA | O8: NA | P8: NA | Q8: NA | R8: 08- FIN/INV | S8: NA | T8: NA | U8: NA | V8: 32- Main Inventory 1 | W8: NA | X8: 8.4 | Y8: NA | Z8: NA | AA8: NA | AB8: XP Endo Finisher 25mm - S1.XB0.00.0AA.FK G | AC8: FKG | AD8: Dubai Medical Equipment LLC | AE8: Dubai Medical Equipment LLC | AF8: Mr.Islam | AG8: +971 55 167 3454 | AH8: 02- Reusable | AI8: 8 | AJ8: 1 | AK8: LPO-7169 | AL8: 720 | AM8: - | AN8: INV/2025/00092 | AO8: 720 | AP8: 0 | AQ8: 720 | AR8: -
A9: 45664 | B9: 01- Purchase | C9: 06- Laboratory- (LAB) | D9: 07- Lab Drilling / Milling Tools & Accessories | E9: Milling Tools | F9: Lab Diamond Cutting Disc | G9: NA | H9: Diamond Cutting Disc | I9: 6 | J9: Pcs | K9: Disc | L9: 25 | M9: NA | N9: NA | O9: NA | P9: NA | Q9: NA | R9: 08- FIN/INV | S9: NA | T9: NA | U9: NA | V9: 32- Main Inventory 1 | W9: NA | X9: 4.5 | Y9: NA | Z9: NA | AA9: NA | AB9: Diamond Cutting Disc | AC9: NA | AD9: Fala Medical Trading | AE9: Fala Medical Trading | AF9: Peter | AG9: +971 56 9360381 | AH9: 02- Reusable | AI9: 4 | AJ9: 1 | AK9: LPO-7193 | AL9: 150 | AM9: - | AN9: 1499 | AO9: 150 | AP9: 7.5 | AQ9: 157.5 | AR9: -
A10: 45664 | B10: 01- Purchase | C10: 06- Laboratory- (LAB) | D10: 07- Lab Drilling / Milling Tools & Accessories | E10: Milling Tools | F10: Rubber Tornado | G10: NA | H10: Rubber Tornado | I10: 6 | J10: Pcs | K10: TDR0601 | L10: 20.8333 | M10: NA | N10: NA | O10: NA | P10: NA | Q10: NA | R10: 08- FIN/INV | S10: NA | T10: NA | U10: NA | V10: 32- Main Inventory 1 | W10: NA | X10: 4.5 | Y10: NA | Z10: NA | AA10: NA | AB10: Rubber Tornado | AC10: NA | AD10: Fala Medical Trading | AE10: Fala Medical Trading | AF10: Peter | AG10: +971 56 9360381 | AH10: 02- Reusable | AI10: 4 | AJ10: 1 | AK10: LPO-7193 | AL10: 124.9998 | AM10: - | AN10: 1499 | AO10: 124.9998 | AP10: 6.24999 | AQ10: 131.24979 | AR10: -
A11: 45664 | B11: 01- Purchase | C11: 03- Prevention & Control of Infection- (PCI) | D11: 03- General & Waste Management | E11: General Materials | F11: Z Fold Tissue | G11: NA | H11: Z Fold Tissue | I11: 60 | J11: Bundle | K11: DIS142 | L11: 1.6 | M11: NA | N11: NA | O11: NA | P11: NA | Q11: NA | R11: 08- FIN/INV | S11: NA | T11: NA | U11: NA | V11: 30- Main Inventory 2 | W11: NA | X11: 5.2 | Y11: NA | Z11: NA | AA11: NA | AB11: Hand Towel - Z Fold Tissues - 2 Ply (150*16 Pkt) | AC11: NA | AD11: Breath General Trading | AE11: Breath General Trading | AF11: Mustaq | AG11: +971 54 745 6475 | AH11: 01- Consumables | AI11: 5 | AJ11: 1 | AK11: LPO-7171 | AL11: 96 | AM11: - | AN11: VDCL-01 | AO11: 96 | AP11: - | AQ11: 96 | AR11: -
A12: 45665 | B12: 01- Purchase | C12: 06- Laboratory- (LAB) | D12: 03- Dental Blanks | E12: Dental Blanks | F12: Blank - Cercon HT Disk 98mm A3 18 | G12: NA | H12: Blank - Cercon HT Disk 98mm A3 18 | I12: 1 | J12: Disc | K12: 5366091218 | L12: 475 | M12: NA | N12: NA | O12: NA | P12: NA | Q12: 46174 | R12: 08- FIN/INV | S12: NA | T12: NA | U12: NA | V12: 32- Main Inventory 1 | W12: NA | X12: 3.4 | Y12: NA | Z12: NA | AA12: NA | AB12: Blank - Cercon HT Disk 98mm A3 18 | AC12: Dentsply Sirona | AD12: Sirona Dental Systems Trading LLC | AE12: Sirona Dental Systems Trading LLC | AF12: Dr.Marwan | AG12: +971 56 415 6254 | AH12: 01- Consumables | AI12: 3 | AJ12: 1 | AK12: LPO-7126 | AL12: 475 | AM12: - | AN12: INV-00641 | AO12: 475 | AP12: 0 | AQ12: 475 | AR12: -
A13: 45665 | B13: 01- Purchase | C13: 05- Implants- (IMPL) | D13: 04- Implant Impression Tools & Supplies | E13: Implant Impression Tools | F13: Ostell Smartpeg Type 53 | G13: NA | H13: Ostell Smartpeg Type 53 | I13: 5 | J13: Pcs | K13: NA | L13: 80 | M13: NA | N13: NA | O13: NA | P13: NA | Q13: NA | R13: 08- FIN/INV | S13: NA | T13: NA | U13: NA | V13: 32- Main Inventory 1 | W13: NA | X13: 1.3 | Y13: NA | Z13: NA | AA13: NA | AB13: Ostell Smartpeg Type 53 | AC13: Ostell | AD13: Prime Medical Supplies Est. | AE13: Prime Medical Supplies Est. | AF13: Martin | AG13: +971 56 449 6039 | AH13: 02- Reusable | AI13: 1 | AJ13: 1 | AK13: LPO-7184 | AL13: 400 | AM13: - | AN13: 33786 | AO13: 400 | AP13: 0 | AQ13: 400 | AR13: -
A14: 45666 | B14: 01- Purchase | C14: 06- Laboratory- (LAB) | D14: 06- Dental Stone, Stains & Wax | E14: Stains | F14: Gum Composite GHB2 | G14: NA | H14: Gum Composite GHB2 | I14: 1 | J14: Pack | K14: EEP901088 | L14: 165 | M14: NA | N14: NA | O14: NA | P14: NA | Q14: 46357 | R14: 08- FIN/INV | S14: NA | T14: NA | U14: NA | V14: 32- Main Inventory 1 | W14: NA | X14: 3.6 | Y14: NA | Z14: NA | AA14: NA | AB14: Gum Composite - Gradia Plus, Gum Paste , GHB-2 | AC14: NA | AD14: Dubai Medical Equipment LLC | AE14: Dubai Medical Equipment LLC | AF14: Mr.Islam | AG14: +971 55 167 3454 | AH14: 01- Consumables | AI14: 3 | AJ14: 1 | AK14: LPO-7194 | AL14: 165 | AM14: - | AN14: INV/2025/00167 | AO14: 165 | AP14: 0 | AQ14: 165 | AR14: -
A15: 45666 | B15: 01- Purchase | C15: 01- Medical & LAB Devices. Instruments- (DEV) | D15: 08- Cssd, Triage, PCI Devices | E15: PCI Devices | F15: Biological Incubator | G15: NA | H15: Biological Incubator | I15: 1 | J15: Unit | K15: SR-13-EMD-BI-02 | L15: 1500 | M15: 75 | N15: NA | O15: NA | P15: NA | Q15: NA | R15: 08- FIN/INV | S15: NA | T15: NA | U15: NA | V15: 32- Main Inventory 1 | W15: NA | X15: 5.2 | Y15: NA | Z15: NA | AA15: NA | AB15: Biological Incubator | AC15: Medley | AD15: City Pharmacy Co. WLL | AE15: City Pharmacy Co. WLL | AF15: Mr.Anas | AG15: +971 55 244 0493 | AH15: 03- Fixed Assets | AI15: 5 | AJ15: 1 | AK15: LPO-7190 | AL15: 1500 | AM15: - | AN15: 1AINDCP-336343 | AO15: 1500 | AP15: 75 | AQ15: 1575 | AR15: -
A16: 45666 | B16: 01- Purchase | C16: 04- Dental Materials & Supplies- (DMS) | D16: 03- Scaling / Gingiva Materials & Supplies | E16: Gingiva Materials | F16: Retraction Paste | G16: NA | H16: Retraction Paste | I16: 2 | J16: Box of 25 Pcs | K16: 56944 | L16: 350 | M16: NA | N16: NA | O16: NA | P16: NA | Q16: 45925 | R16: 08- FIN/INV | S16: NA | T16: NA | U16: NA | V16: 32- Main Inventory 1 | W16: NA | X16: 7.2 | Y16: NA | Z16: NA | AA16: NA | AB16: Retraction Paste - 3M ESPE Astringent | AC16: 3M ESPE | AD16: Bright Gate Healthcare LLC | AE16: Bright Gate Healthcare LLC | AF16: Sales | AG16: +971 50 622 5639 | AH16: 01- Consumables | AI16: 7 | AJ16: 1 | AK16: LPO-7188 | AL16: 700 | AM16: - | AN16: 18257 | AO16: 700 | AP16: - | AQ16: 700 | AR16: -
A17: 45668 | B17: 01- Purchase | C17: 06- Laboratory- (LAB) | D17: 06- Dental Stone, Stains & Wax | E17: Stains | F17: Gum Composite GHB3 | G17: NA | H17: Gum Composite GHB3 | I17: 1 | J17: Pack | K17: NA | L17: 165 | M17: NA | N17: NA | O17: NA | P17: NA | Q17: 46357 | R17: 08- FIN/INV | S17: NA | T17: NA | U17: NA | V17: 32- Main Inventory 1 | W17: NA | X17: 3.6 | Y17: NA | Z17: NA | AA17: NA | AB17: Gum Composite - Gradia Plus, Gum Paste , GHB-3 | AC17: NA | AD17: Dubai Medical Equipment LLC | AE17: Dubai Medical Equipment LLC | AF17: Mr.Islam | AG17: +971 55 167 3454 | AH17: 01- Consumables | AI17: 3 | AJ17: 1 | AK17: LPO-7194 | AL17: 165 | AM17: - | AN17: INV/2025/00167 | AO17: 165 | AP17: 0 | AQ17: 165 | AR17: -
A18: 45668 | B18: 01- Purchase | C18: 04- Dental Materials & Supplies- (DMS) | D18: 02- Nitrous & Oxygen Sedation | E18: Nitrous Sedation | F18: Nitrous Oxide Refill | G18: NA | H18: Nitrous Oxide Refill | I18: 1 | J18: Cylinder | K18: MI-DMS-NR-01 | L18: 150 | M18: NA | N18: NA | O18: NA | P18: NA | Q18: NA | R18: 08- FIN/INV | S18: NA | T18: NA | U18: NA | V18: 32- Main Inventory 1 | W18: NA | X18: 2.5 | Y18: NA | Z18: NA | AA18: NA | AB18: Nitrous Oxide Refill | AC18: NA | AD18: Panacea Synthetic Gas Trading LLC | AE18: Panacea Synthetic Gas Trading LLC | AF18: Suresh | AG18: +971 52 850 2873 | AH18: 01- Consumables | AI18: 2 | AJ18: 1 | AK18: LPO-7195 | AL18: 150 | AM18: - | AN18: PSGT-0322025 | AO18: 150 | AP18: 7.5 | AQ18: 157.5 | AR18: -
A19: 45668 | B19: 01- Purchase | C19: 04- Dental Materials & Supplies- (DMS) | D19: 02- Nitrous & Oxygen Sedation | E19: Oxygen Sedation | F19: Oxygen Refill | G19: NA | H19: Oxygen Refill | I19: 2 | J19: Cylinder | K19: MI-DMS-OR-01 | L19: 30 | M19: NA | N19: NA | O19: NA | P19: NA | Q19: NA | R19: 08- FIN/INV | S19: NA | T19: NA | U19: NA | V19: 32- Main Inventory 1 | W19: NA | X19: 2.5 | Y19: NA | Z19: NA | AA19: NA | AB19: Oxygen Refill | AC19: NA | AD19: Panacea Synthetic Gas Trading LLC | AE19: Panacea Synthetic Gas Trading LLC | AF19: Suresh | AG19: +971 52 850 2873 | AH19: 01- Consumables | AI19: 2 | AJ19: 1 | AK19: LPO-7195 | AL19: 60 | AM19: - | AN19: PSGT-0322025 | AO19: 60 | AP19: 3 | AQ19: 63 | AR19: -
A20: 45668 | B20: 01- Purchase | C20: 04- Dental Materials & Supplies- (DMS) | D20: 05- Endodontic Materials & Posts Supplies | E20: Endodontic Materials | F20: Rotary Files - Assorted 25mm | G20: NA | H20: Rotary Files - Assorted 25mm | I20: 10 | J20: Pack of 4Pcs | K20: RFA-00025 | L20: 125 | M20: NA | N20: NA | O20: NA | P20: NA | Q20: NA | R20: 08- FIN/INV | S20: NA | T20: NA | U20: NA | V20: 32- Main Inventory 1 | W20: NA | X20: 8.4 | Y20: NA | Z20: NA | AA20: NA | AB20: Rotary Files Assorted 25mm - Smart Carver Kit | AC20: Smart Files | AD20: Ora Tech Medical and Surgical Articles & Requisites Trading LLC | AE20: Ora Tech Medical and Surgical Articles & Requisites Trading LLC | AF20: Amer | AG20: +971 58 567 3445 | AH20: 02- Reusable | AI20: 8 | AJ20: 1 | AK20: LPO-6989 | AL20: 1250 | AM20: - | AN20: CS0S125000008 | AO20: 1250 | AP20: 0 | AQ20: 1250 | AR20: -
A21: 45668 | B21: 01- Purchase | C21: 04- Dental Materials & Supplies- (DMS) | D21: 05- Endodontic Materials & Posts Supplies | E21: Endodontic Materials | F21: Rotary Files - Assorted 31mm | G21: NA | H21: Rotary Files - Assorted 31mm | I21: 10 | J21: Pack of 4Pcs | K21: RFA-00031 | L21: 125 | M21: NA | N21: NA | O21: NA | P21: NA | Q21: NA | R21: 08- FIN/INV | S21: NA | T21: NA | U21: NA | V21: 32- Main Inventory 1 | W21: NA | X21: 8.4 | Y21: NA | Z21: NA | AA21: NA | AB21: Rotary Files Assorted 31mm - Smart Carver Kit | AC21: Smart Files | AD21: Ora Tech Medical and Surgical Articles & Requisites Trading LLC | AE21: Ora Tech Medical and Surgical Articles & Requisites Trading LLC | AF21: Amer | AG21: +971 58 567 3445 | AH21: 02- Reusable | AI21: 8 | AJ21: 1 | AK21: LPO-7189 | AL21: 1250 | AM21: - | AN21: CS0S125000008 | AO21: 1250 | AP21: 0 | AQ21: 1250 | AR21: -
A22: 45670 | B22: 01- Purchase | C22: 02- Drugs, Needles & Triage- (DRG) | D22: 04- Needles & Syringes | E22: Needles | F22: STA Long | G22: NA | H22: STA Long | I22: 1 | J22: Box of 50 Pcs | K22: MILESTA-5050-301 | L22: 549 | M22: NA | N22: NA | O22: NA | P22: NA | Q22: 46350 | R22: 08- FIN/INV | S22: NA | T22: NA | U22: NA | V22: 32- Main Inventory 1 | W22: NA | X22: 5.6 | Y22: NA | Z22: NA | AA22: NA | AB22: Wand STA Handpieces with Needle 30 gauge x 1" | AC22: WAND STA | AD22: Al Hayat Pharmaceuticals | AE22: Al Hayat Pharmaceuticals | AF22: Dr.Noha | AG22: +971 56 367 4713 | AH22: 01- Consumables | AI22: 5 | AJ22: 1 | AK22: LPO-7185 | AL22: 549 | AM22: - | AN22: TCS-202501802 | AO22: 549 | AP22: 27.45 | AQ22: 576.45 | AR22: -
A23: 45670 | B23: 01- Purchase | C23: 02- Drugs, Needles & Triage- (DRG) | D23: 04- Needles & Syringes | E23: Needles | F23: STA Short | G23: NA | H23: STA Short | I23: 1 | J23: Box of 50 Pcs | K23: MILESTA-5050-305 | L23: 549 | M23: NA | N23: NA | O23: NA | P23: NA | Q23: 46715 | R23: 08- FIN/INV | S23: NA | T23: NA | U23: NA | V23: 32- Main Inventory 1 | W23: NA | X23: 5.6 | Y23: NA | Z23: NA | AA23: NA | AB23: Wand STA Handpieces with Needle 30 gauge x 1/2" | AC23: WAND STA | AD23: Al Hayat Pharmaceuticals | AE23: Al Hayat Pharmaceuticals | AF23: Dr.Noha | AG23: +971 56 367 4713 | AH23: 01- Consumables | AI23: 5 | AJ23: 1 | AK23: LPO-7185 | AL23: 549 | AM23: - | AN23: TCS-202501802 | AO23: 549 | AP23: 27.45 | AQ23: 576.45 | AR23: -
A24: 45670 | B24: 01- Purchase | C24: 05- Implants- (IMPL) | D24: 03- Abutments | E24: Abutments | F24: Titanium Abutments | G24: NA | H24: Titanium Abutment Unibase TBC-SV-RP | I24: 2 | J24: Pcs | K24: NA | L24: 176 | M24: NA | N24: NA | O24: NA | P24: NA | Q24: NA | R24: 08- FIN/INV | S24: NA | T24: NA | U24: NA | V24: 30- Main Inventory 2 | W24: NA | X24: 2.4 | Y24: NA | Z24: NA | AA24: NA | AB24: Titanium Abutment Unibase TBC-SV-RP | AC24: NA | AD24: Edison Medical | AE24: Edison Medical | AF24: Dr. Hala Al Atieh | AG24: +971 56 587 8515 | AH24: 01- Consumables | AI24: 2 | AJ24: 4 | AK24: LPO-7224 | AL24: 352 | AM24: - | AN24: AE-25004013399 | AO24: 352 | AP24: - | AQ24: 352 | AR24: -
A25: 45670 | B25: 01- Purchase | C25: 04- Dental Materials & Supplies- (DMS) | D25: 04- Restorative Fillings, Adhesives & Supplies | E25: Adhesives | F25: Adhesive L-Pop 100 | G25: NA | H25: Adhesive L-Pop 100 | I25: 2 | J25: Box of 100 Pcs | K25: 41279 | L25: 1030 | M25: NA | N25: NA | O25: NA | P25: NA | Q25: 45927 | R25: 08- FIN/INV | S25: NA | T25: NA | U25: NA | V25: 32- Main Inventory 1 | W25: NA | X25: 7.3 | Y25: NA | Z25: NA | AA25: NA | AB25: Adhesive - L-Pop - Single Bond 100's - 3M ESPE | AC25: 3M ESPE | AD25: Alphamed General Trading LLC | AE25: Alphamed General Trading LLC | AF25: Dr.Lujian | AG25: +971 56 697 4909 | AH25: 01- Consumables | AI25: 7 | AJ25: 1 | AK25: LPO-7186 | AL25: 2060 | AM25: - | AN25: LB-DXB-6309591 | AO25: 2060 | AP25: - | AQ25: 2060 | AR25: 2060
A26: 45671 | B26: 01- Purchase | C26: 02- Drugs, Needles & Triage- (DRG) | D26: 04- Needles & Syringes | E26: Syringes | F26: Insuline Syringe | G26: NA | H26: Insuline Syringe | I26: 1 | J26: Box of 10packs | K26: INS01 | L26: 22 | M26: NA | N26: NA | O26: NA | P26: NA | Q26: 46837 | R26: 08- FIN/INV | S26: NA | T26: NA | U26: NA | V26: 32- Main Inventory 1 | W26: NA | X26: 6.5 | Y26: NA | Z26: NA | AA26: NA | AB26: Insuline Syringe | AC26: NA | AD26: Everest Medical & Safety Trading | AE26: Everest Medical & Safety Trading | AF26: Mujeeb | AG26: +971 56 683 3107 | AH26: 01- Consumables | AI26: 6 | AJ26: 1 | AK26: LPO-7191 | AL26: 22 | AM26: - | AN26: MS-INV-28421 | AO26: 22 | AP26: 0 | AQ26: 22 | AR26: -
A27: 45671 | B27: 01- Purchase | C27: 04- Dental Materials & Supplies- (DMS) | D27: 03- Scaling / Gingiva Materials & Supplies | E27: Scaling | F27: Prophy Cup | G27: NA | H27: Prophy Cup | I27: 1 | J27: Pack | K27: PROPHYCUP-00001 | L27: 25 | M27: NA | N27: NA | O27: NA | P27: NA | Q27: NA | R27: 08- FIN/INV | S27: NA | T27: NA | U27: NA | V27: 32- Main Inventory 1 | W27: NA | X27: 8.2 | Y27: NA | Z27: NA | AA27: NA | AB27: Prophylaxis Cup - Standard | AC27: ORO | AD27: Everest Medical & Safety Trading | AE27: Everest Medical & Safety Trading | AF27: Mujeeb | AG27: +971 56 683 3107 | AH27: 01- Consumables | AI27: 8 | AJ27: 1 | AK27: LPO-7191 | AL27: 25 | AM27: - | AN27: MS-INV-28421 | AO27: 25 | AP27: 0 | AQ27: 25 | AR27: -
A28: 45671 | B28: 01- Purchase | C28: 03- Prevention & Control of Infection- (PCI) | D28: 04- Wrapping & Protective Materials | E28: Wrapping | F28: Sterilization Pouch 300 | G28: NA | H28: Sterilization Pouch 300 | I28: 1 | J28: Roll | K28: STR-000300 | L28: 130 | M28: NA | N28: NA | O28: NA | P28: NA | Q28: NA | R28: 08- FIN/INV | S28: NA | T28: NA | U28: NA | V28: 30- Main Inventory 2 | W28: NA | X28: 1.4 | Y28: NA | Z28: NA | AA28: NA | AB28: Sterilization Reel - 300x200mt Plain | AC28: MMC | AD28: Everest Medical & Safety Trading | AE28: Everest Medical & Safety Trading | AF28: Mujeeb | AG28: +971 56 683 3107 | AH28: 01- Consumables | AI28: 1 | AJ28: 1 | AK28: LPO-7191 | AL28: 130 | AM28: - | AN28: MS-INV-28421 | AO28: 130 | AP28: 0 | AQ28: 130 | AR28: -
A29: 45671 | B29: 01- Purchase | C29: 04- Dental Materials & Supplies- (DMS) | D29: 04- Restorative Fillings, Adhesives & Supplies | E29: Restorative Fillings | F29: Composite Universal A2 | G29: NA | H29: Composite Universal A2 | I29: 1 | J29: Syringe | K29: 1370A2 | L29: 128 | M29: NA | N29: NA | O29: NA | P29: NA | Q29: 45992 | R29: 08- FIN/INV | S29: NA | T29: NA | U29: NA | V29: 32- Main Inventory 1 | W29: NA | X29: 8.3 | Y29: NA | Z29: NA | AA29: NA | AB29: Universal Restorative - Filtek Z250 Universal Restorative A2 Shade - 3M ESPE | AC29: 3M ESPE | AD29: Everest Medical & Safety Trading | AE29: Everest Medical & Safety Trading | AF29: Mujeeb | AG29: +971 56 683 3107 | AH29: 01- Consumables | AI29: 8 | AJ29: 1 | AK29: LPO-7191 | AL29: 128 | AM29: - | AN29: MS-INV-28421 | AO29: 128 | AP29: 0 | AQ29: 128 | AR29: -
A30: 45671 | B30: 01- Purchase | C30: 03- Prevention & Control of Infection- (PCI) | D30: 04- Wrapping & Protective Materials | E30: Wrapping | F30: Sterilization Pouch 55 | G30: NA | H30: Sterilization Pouch 55 | I30: 1 | J30: Roll | K30: STR-00055 | L30: 28 | M30: NA | N30: NA | O30: NA | P30: NA | Q30: NA | R30: 08- FIN/INV | S30: NA | T30: NA | U30: NA | V30: 30- Main Inventory 2 | W30: NA | X30: 1.4 | Y30: NA | Z30: NA | AA30: NA | AB30: Sterilization Reel - 55x200mt Plain | AC30: MMC | AD30: Everest Medical & Safety Trading | AE30: Everest Medical & Safety Trading | AF30: Mujeeb | AG30: +971 56 683 3107 | AH30: 01- Consumables | AI30: 1 | AJ30: 1 | AK30: LPO-7191 | AL30: 28 | AM30: - | AN30: MS-INV-28421 | AO30: 28 | AP30: 0 | AQ30: 28 | AR30: -
A31: 45671 | B31: 01- Purchase | C31: 04- Dental Materials & Supplies- (DMS) | D31: 05- Endodontic Materials & Posts Supplies | E31: Endodontic Materials | F31: Rubber Dam Sheet | G31: NA | H31: Rubber Dam Sheet | I31: 1 | J31: Pack of 36 Sheets | K31: DL622B-EBSH0 | L31: 32 | M31: NA | N31: NA | O31: NA | P31: NA | Q31: 46572 | R31: 08- FIN/INV | S31: NA | T31: NA | U31: NA | V31: 32- Main Inventory 1 | W31: NA | X31: 8.4 | Y31: NA | Z31: NA | AA31: NA | AB31: Rubber Dam Sheet | AC31: Sanctuary | AD31: Everest Medical & Safety Trading | AE31: Everest Medical & Safety Trading | AF31: Mujeeb | AG31: +971 56 683 3107 | AH31: 01- Consumables | AI31: 8 | AJ31: 1 | AK31: LPO-7191 | AL31: 32 | AM31: - | AN31: MS-INV-28421 | AO31: 32 | AP31: 0 | AQ31: 32 | AR31: -
A32: 45671 | B32: 01- Purchase | C32: 04- Dental Materials & Supplies- (DMS) | D32: 04- Restorative Fillings, Adhesives & Supplies | E32: Restorative Supplies | F32: Supercap 6.3mm | G32: NA | H32: Supercap 6.3mm | I32: 1 | J32: Pack of 50 Pcs | K32: 2181 | L32: 160 | M32: NA | N32: NA | O32: NA | P32: NA | Q32: NA | R32: 08- FIN/INV | S32: NA | T32: NA | U32: NA | V32: 32- Main Inventory 1 | W32: NA | X32: 7.3 | Y32: NA | Z32: NA | AA32: NA | AB32: Matrix Supercap 6.3mm | AC32: KERR | AD32: Everest Medical & Safety Trading | AE32: Everest Medical & Safety Trading | AF32: Mujeeb | AG32: +971 56 683 3107 | AH32: 01- Consumables | AI32: 7 | AJ32: 1 | AK32: LPO-7191 | AL32: 160 | AM32: - | AN32: MS-INV-28421 | AO32: 160 | AP32: 0 | AQ32: 160 | AR32: -
A33: 45671 | B33: 01- Purchase | C33: 04- Dental Materials & Supplies- (DMS) | D33: 07- Impression Materials & Supplies | E33: Impression Materials | F33: Mixing Tip - Light Green | G33: NA | H33: Mixing Tip - Light Green | I33: 1 | J33: Pack | K33: MXTG-00001 | L33: 25 | M33: NA | N33: NA | O33: NA | P33: NA | Q33: NA | R33: 08- FIN/INV | S33: NA | T33: NA | U33: NA | V33: 32- Main Inventory 1 | W33: NA | X33: 8.5 | Y33: NA | Z33: NA | AA33: NA | AB33: Mixing Tip - Light Green | AC33: NEOPRO | AD33: Everest Medical & Safety Trading | AE33: Everest Medical & Safety Trading | AF33: Mujeeb | AG33: +971 56 683 3107 | AH33: 01- Consumables | AI33: 8 | AJ33: 1 | AK33: LPO-7191 | AL33: 25 | AM33: - | AN33: MS-INV-28421 | AO33: 25 | AP33: 0 | AQ33: 25 | AR33: -
A34: 45671 | B34: 01- Purchase | C34: 04- Dental Materials & Supplies- (DMS) | D34: 05- Endodontic Materials & Posts Supplies | E34: Endodontic Materials | F34: K Files | G34: NA | H34: K Files 31-15 | I34: 1 | J34: Pkt | K34: KF-003115 | L34: 6 | M34: NA | N34: NA | O34: NA | P34: NA | Q34: NA | R34: 08- FIN/INV | S34: NA | T34: NA | U34: NA | V34: 32- Main Inventory 1 | W34: NA | X34: 8.4 | Y34: NA | Z34: NA | AA34: NA | AB34: K Files - 31mm #15 | AC34: Mani | AD34: Everest Medical & Safety Trading | AE34: Everest Medical & Safety Trading | AF34: Mujeeb | AG34: +971 56 683 3107 | AH34: 02- Reusable | AI34: 8 | AJ34: 1 | AK34: LPO-7191 | AL34: 6 | AM34: - | AN34: MS-INV-28421 | AO34: 6 | AP34: - | AQ34: 6 | AR34: -
A35: 45671 | B35: 01- Purchase | C35: 04- Dental Materials & Supplies- (DMS) | D35: 08- Bleaching Material & Supplies | E35: Bleaching Material | F35: Zoom Whitening in Office | G35: NA | H35: Chairside Dental Teeth Whitening | I35: 1 | J35: Pack for 2 Patients | K35: DIC/ZME2665 | L35: 800 | M35: NA | N35: NA | O35: NA | P35: NA | Q35: 46387 | R35: 08- FIN/INV | S35: NA | T35: NA | U35: NA | V35: 32- Main Inventory 1 | W35: NA | X35: 7.1 | Y35: NA | Z35: NA | AA35: NA | AB35: Chairside Dental Teeth Whitening - 2 Complete Patient Kits - Philips Zoom | AC35: Philips Zoom | AD35: Al Hayat Pharmaceuticals | AE35: Al Hayat Pharmaceuticals | AF35: Dr.Noha | AG35: +971 56 367 4713 | AH35: 01- Consumables | AI35: 7 | AJ35: 1 | AK35: LPO-7200 | AL35: 800 | AM35: - | AN35: TCS-20252200 | AO35: 800 | AP35: 40 | AQ35: 840 | AR35: -
A36: 45671 | B36: 01- Purchase | C36: 01- Medical & LAB Devices. Instruments- (DEV) | D36: 06- Hand Instruments (Restorative, Perio, Endo, Implants,Ortho…) | E36: Restorative | F36: Mouth Mirror Head | G36: NA | H36: Mouth Mirror Head | I36: 2 | J36: Pack of 12 Pcs | K36: 5462 | L36: 28 | M36: NA | N36: NA | O36: NA | P36: NA | Q36: NA | R36: 08- FIN/INV | S36: NA | T36: NA | U36: NA | V36: 32- Main Inventory 1 | W36: NA | X36: 5.3 | Y36: NA | Z36: NA | AA36: NA | AB36: Mouth Mirror Head | AC36: NA | AD36: Everest Medical & Safety Trading | AE36: Everest Medical & Safety Trading | AF36: Mujeeb | AG36: +971 56 683 3107 | AH36: 02- Reusable | AI36: 5 | AJ36: 1 | AK36: LPO-7191 | AL36: 56 | AM36: - | AN36: MS-INV-28421 | AO36: 56 | AP36: 0 | AQ36: 56 | AR36: -
A37: 45671 | B37: 01- Purchase | C37: 02- Drugs, Needles & Triage- (DRG) | D37: 04- Needles & Syringes | E37: Syringes | F37: Disposable Syringe 20cc | G37: NA | H37: Disposable Syringe 20cc | I37: 2 | J37: Box of 25pcs | K37: DS20CC | L37: 15 | M37: NA | N37: NA | O37: NA | P37: NA | Q37: 46103 | R37: 08- FIN/INV | S37: NA | T37: NA | U37: NA | V37: 32- Main Inventory 1 | W37: NA | X37: 6.5 | Y37: NA | Z37: NA | AA37: NA | AB37: Syringe 20cc | AC37: MEDISOFT | AD37: Everest Medical & Safety Trading | AE37: Everest Medical & Safety Trading | AF37: Mujeeb | AG37: +971 56 683 3107 | AH37: 01- Consumables | AI37: 6 | AJ37: 1 | AK37: LPO-7191 | AL37: 30 | AM37: - | AN37: MS-INV-28421 | AO37: 30 | AP37: 0 | AQ37: 30 | AR37: -
A38: 45671 | B38: 01- Purchase | C38: 04- Dental Materials & Supplies- (DMS) | D38: 04- Restorative Fillings, Adhesives & Supplies | E38: Restorative | F38: Articulating Paper | G38: NA | H38: Articulating Paper | I38: 2 | J38: Pack of 12 Books | K38: AP-00001 | L38: 14 | M38: NA | N38: NA | O38: NA | P38: NA | Q38: NA | R38: 08- FIN/INV | S38: NA | T38: NA | U38: NA | V38: 32- Main Inventory 1 | W38: NA | X38: 7.3 | Y38: NA | Z38: NA | AA38: NA | AB38: Articulating Paper - Ehros - 12 Books - 12 Sheets/Book | AC38: AP | AD38: Everest Medical & Safety Trading | AE38: Everest Medical & Safety Trading | AF38: Mujeeb | AG38: +971 56 683 3107 | AH38: 01- Consumables | AI38: 7 | AJ38: 1 | AK38: LPO-7191 | AL38: 28 | AM38: - | AN38: MS-INV-28421 | AO38: 28 | AP38: 0 | AQ38: 28 | AR38: -
A39: 45671 | B39: 01- Purchase | C39: 04- Dental Materials & Supplies- (DMS) | D39: 05- Endodontic Materials & Posts Supplies | E39: Endodontic Materials | F39: EDTA | G39: NA | H39: EDTA | I39: 2 | J39: Pack of 3 Syringe | K39: 6320002 | L39: 50 | M39: NA | N39: NA | O39: NA | P39: NA | Q39: 45413 | R39: 08- FIN/INV | S39: NA | T39: NA | U39: NA | V39: 32- Main Inventory 1 | W39: NA | X39: 8.4 | Y39: NA | Z39: NA | AA39: NA | AB39: Root Canal Cleanser - Charm EDTA Gel 1.5g | AC39: DENTKIST | AD39: Everest Medical & Safety Trading | AE39: Everest Medical & Safety Trading | AF39: Mujeeb | AG39: +971 56 683 3107 | AH39: 01- Consumables | AI39: 8 | AJ39: 1 | AK39: LPO-7191 | AL39: 100 | AM39: - | AN39: MS-INV-28421 | AO39: 100 | AP39: 0 | AQ39: 100 | AR39: -
A40: 45671 | B40: 01- Purchase | C40: 04- Dental Materials & Supplies- (DMS) | D40: 04- Restorative Fillings, Adhesives & Supplies | E40: Restorative Fillings | F40: Micro Applicator -Regular | G40: NA | H40: Micro Applicator -Regular | I40: 2 | J40: Tube | K40: MAB-00001 | L40: 9 | M40: NA | N40: NA | O40: NA | P40: NA | Q40: NA | R40: 08- FIN/INV | S40: NA | T40: NA | U40: NA | V40: 32- Main Inventory 1 | W40: NA | X40: 7.3 | Y40: NA | Z40: NA | AA40: NA | AB40: Micro Brush Applicator - Regular | AC40: MICRO-B | AD40: Everest Medical & Safety Trading | AE40: Everest Medical & Safety Trading | AF40: Mujeeb | AG40: +971 56 683 3107 | AH40: 01- Consumables | AI40: 7 | AJ40: 1 | AK40: LPO-7191 | AL40: 18 | AM40: - | AN40: MS-INV-28421 | AO40: 18 | AP40: 0 | AQ40: 18 | AR40: -
A41: 45671 | B41: 01- Purchase | C41: 04- Dental Materials & Supplies- (DMS) | D41: 03- Scaling / Gingiva Materials & Supplies | E41: Scaling | F41: Prophylaxis Paste | G41: NA | H41: Prophylaxis Paste | I41: 2 | J41: Box of 200pcs | K41: 58-00224 | L41: 85 | M41: NA | N41: NA | O41: NA | P41: NA | Q41: 46477 | R41: 08- FIN/INV | S41: NA | T41: NA | U41: NA | V41: 32- Main Inventory 1 | W41: NA | X41: 7.2 | Y41: NA | Z41: NA | AA41: NA | AB41: Prophylaxis Paste - Gelato | AC41: QUARTZ | AD41: Everest Medical & Safety Trading | AE41: Everest Medical & Safety Trading | AF41: Mujeeb | AG41: +971 56 683 3107 | AH41: 01- Consumables | AI41: 7 | AJ41: 1 | AK41: LPO-7191 | AL41: 170 | AM41: - | AN41: MS-INV-28421 | AO41: 170 | AP41: 0 | AQ41: 170 | AR41: -
A42: 45671 | B42: 01- Purchase | C42: 04- Dental Materials & Supplies- (DMS) | D42: 04- Restorative Fillings, Adhesives & Supplies | E42: Restorative Fillings | F42: Matrix Band 6-0.2 C-4 | G42: NA | H42: Matrix Band 6-0.2 C-4 | I42: 2 | J42: Box of 50pcs | K42: DIS4785 | L42: 20 | M42: NA | N42: NA | O42: NA | P42: NA | Q42: NA | R42: 08- FIN/INV | S42: NA | T42: NA | U42: NA | V42: 32- Main Inventory 1 | W42: NA | X42: 7.3 | Y42: NA | Z42: NA | AA42: NA | AB42: Matrix Band 6mm-0.2mm - C-4 | AC42: NA | AD42: Everest Medical & Safety Trading | AE42: Everest Medical & Safety Trading | AF42: Mujeeb | AG42: +971 56 683 3107 | AH42: 01- Consumables | AI42: 7 | AJ42: 1 | AK42: LPO-7191 | AL42: 40 | AM42: - | AN42: MS-INV-28421 | AO42: 40 | AP42: 0 | AQ42: 40 | AR42: -
A43: 45671 | B43: 01- Purchase | C43: 03- Prevention & Control of Infection- (PCI) | D43: 04- Wrapping & Protective Materials | E43: Wrapping | F43: Sterilization Pouch 100 | G43: NA | H43: Sterilization Pouch 100 | I43: 2 | J43: Roll | K43: STR-000100 | L43: 42 | M43: NA | N43: NA | O43: NA | P43: NA | Q43: NA | R43: 08- FIN/INV | S43: NA | T43: NA | U43: NA | V43: 30- Main Inventory 2 | W43: NA | X43: 1.4 | Y43: NA | Z43: NA | AA43: NA | AB43: Sterilization Reel - 100x200mt Plain | AC43: MMC | AD43: Everest Medical & Safety Trading | AE43: Everest Medical & Safety Trading | AF43: Mujeeb | AG43: +971 56 683 3107 | AH43: 01- Consumables | AI43: 1 | AJ43: 1 | AK43: LPO-7191 | AL43: 84 | AM43: - | AN43: MS-INV-28421 | AO43: 84 | AP43: 0 | AQ43: 84 | AR43: -
A44: 45671 | B44: 01- Purchase | C44: 02- Drugs, Needles & Triage- (DRG) | D44: 03- Vital Signs/ Emergency Supplies | E44: Surgical Materials | F44: Band Aid Long | G44: NA | H44: Band Aid Long 72x19mm | I44: 2 | J44: Box | K44: NA | L44: 5 | M44: NA | N44: NA | O44: NA | P44: NA | Q44: NA | R44: 08- FIN/INV | S44: NA | T44: NA | U44: NA | V44: 32- Main Inventory 1 | W44: NA | X44: 5.5 | Y44: NA | Z44: NA | AA44: NA | AB44: Band Aid Long 72x19mm | AC44: Medicure | AD44: Everest Medical & Safety Trading | AE44: Everest Medical & Safety Trading | AF44: Mujeeb | AG44: +971 56 683 3107 | AH44: 01- Consumables | AI44: 5 | AJ44: 1 | AK44: LPO-7191 | AL44: 10 | AM44: - | AN44: MS-INV-28421 | AO44: 10 | AP44: 0 | AQ44: 10 | AR44: -
A45: 45671 | B45: 01- Purchase | C45: 03- Prevention & Control of Infection- (PCI) | D45: 02- Disinfectants & Lubricants | E45: Disinfectants | F45: Instrument Solution 5 Ltr. | G45: NA | H45: Instrument Solution 5 Ltr. | I45: 3 | J45: Gallon | K45: 1111-607 | L45: 130 | M45: NA | N45: NA | O45: NA | P45: NA | Q45: 45900 | R45: 08- FIN/INV | S45: NA | T45: NA | U45: NA | V45: 30- Main Inventory 2 | W45: NA | X45: 4.4 | Y45: NA | Z45: NA | AA45: NA | AB45: Instrument Disinfectant - 5 Ltr. | AC45: Caviforte | AD45: Everest Medical & Safety Trading | AE45: Everest Medical & Safety Trading | AF45: Mujeeb | AG45: +971 56 683 3107 | AH45: 01- Consumables | AI45: 4 | AJ45: 1 | AK45: LPO-7191 | AL45: 390 | AM45: - | AN45: MS-INV-28421 | AO45: 390 | AP45: 19.5 | AQ45: 409.5 | AR45: -
A46: 45671 | B46: 01- Purchase | C46: 03- Prevention & Control of Infection- (PCI) | D46: 01- Personal Protective Equipment | E46: Personal Protective Equipment | F46: Shoe Cover | G46: NA | H46: Shoe Cover | I46: 4 | J46: Pack of 100 Pcs | K46: SCNW-00001 | L46: 12 | M46: NA | N46: NA | O46: NA | P46: NA | Q46: NA | R46: 08- FIN/INV | S46: NA | T46: NA | U46: NA | V46: 30- Main Inventory 2 | W46: NA | X46: 3.1 | Y46: NA | Z46: NA | AA46: NA | AB46: Shoe Cover Non-Woven | AC46: Medinorm | AD46: Everest Medical & Safety Trading | AE46: Everest Medical & Safety Trading | AF46: Mujeeb | AG46: +971 56 683 3107 | AH46: 01- Consumables | AI46: 2 | AJ46: 1 | AK46: LPO-7191 | AL46: 48 | AM46: - | AN46: MS-INV-28421 | AO46: 48 | AP46: 0 | AQ46: 48 | AR46: -
A47: 45671 | B47: 01- Purchase | C47: 03- Prevention & Control of Infection- (PCI) | D47: 01- Personal Protective Equipment | E47: Personal Protective Equipment | F47: High Suction Tip- White | G47: NA | H47: High Suction Tip- White | I47: 4 | J47: Pack of 100 Pcs | K47: HST-00001 | L47: 10 | M47: NA | N47: NA | O47: NA | P47: NA | Q47: NA | R47: 08- FIN/INV | S47: NA | T47: NA | U47: NA | V47: 30- Main Inventory 2 | W47: NA | X47: 4.3 | Y47: NA | Z47: NA | AA47: NA | AB47: High Suction Tip- White | AC47: BMS | AD47: Everest Medical & Safety Trading | AE47: Everest Medical & Safety Trading | AF47: Mujeeb | AG47: +971 56 683 3107 | AH47: 01- Consumables | AI47: 5 | AJ47: 1 | AK47: LPO-7191 | AL47: 40 | AM47: - | AN47: MS-INV-28421 | AO47: 40 | AP47: 0 | AQ47: 40 | AR47: -
A48: 45671 | B48: 01- Purchase | C48: 03- Prevention & Control of Infection- (PCI) | D48: 05- Sterilization Monitoring | E48: Sterilization Monitoring | F48: Biological Indicator | G48: NA | H48: Biological Indicator | I48: 4 | J48: Pack of 10 Pcs | K48: 101039001 | L48: 55 | M48: NA | N48: NA | O48: NA | P48: NA | Q48: 45870 | R48: 08- FIN/INV | S48: NA | T48: NA | U48: NA | V48: 30- Main Inventory 2 | W48: NA | X48: 2.4 | Y48: NA | Z48: NA | AA48: NA | AB48: Biological Indicator | AC48: Euromed | AD48: Everest Medical & Safety Trading | AE48: Everest Medical & Safety Trading | AF48: Mujeeb | AG48: +971 56 683 3107 | AH48: 01- Consumables | AI48: 2 | AJ48: 1 | AK48: LPO-7191 | AL48: 220 | AM48: - | AN48: MS-INV-28421 | AO48: 220 | AP48: 0 | AQ48: 220
A49: 45671 | B49: 01- Purchase | C49: 03- Prevention & Control of Infection- (PCI) | D49: 01- Personal Protective Equipment | E49: Personal Protective Equipment | F49: Saliva Ejector | G49: NA | H49: Saliva Ejector | I49: 5 | J49: Pack of 100 Pcs | K49: SE-00001 | L49: 9 | M49: NA | N49: NA | O49: NA | P49: NA | Q49: NA | R49: 08- FIN/INV | S49: NA | T49: NA | U49: NA | V49: 30- Main Inventory 2 | W49: NA | X49: 5.3 | Y49: NA | Z49: NA | AA49: NA | AB49: Saliva Ejector | AC49: EUROMED | AD49: Everest Medical & Safety Trading | AE49: Everest Medical & Safety Trading | AF49: Mujeeb | AG49: +971 56 683 3107 | AH49: 01- Consumables | AI49: 5 | AJ49: 1 | AK49: LPO-7191 | AL49: 45 | AM49: - | AN49: MS-INV-28421 | AO49: 45 | AP49: 0 | AQ49: 45 | AR49: -
A50: 45671 | B50: 01- Purchase | C50: 03- Prevention & Control of Infection- (PCI) | D50: 04- Wrapping & Protective Materials | E50: Wrapping | F50: Sterilization Pouch 75 | G50: NA | H50: Sterilization Pouch 75 | I50: 5 | J50: Roll | K50: STR-00075 | L50: 32 | M50: NA | N50: NA | O50: NA | P50: NA | Q50: NA | R50: 08- FIN/INV | S50: NA | T50: NA | U50: NA | V50: 30- Main Inventory 2 | W50: NA | X50: 1.4 | Y50: NA | Z50: NA | AA50: NA | AB50: Sterilization Reel - 75x200mt Plain | AC50: MMC | AD50: Everest Medical & Safety Trading | AE50: Everest Medical & Safety Trading | AF50: Mujeeb | AG50: +971 56 683 3107 | AH50: 01- Consumables | AI50: 1 | AJ50: 1 | AK50: LPO-7191 | AL50: 160 | AM50: - | AN50: MS-INV-28421 | AO50: 160 | AP50: 0 | AQ50: 160 | AR50: -
A51: 45671 | B51: 01- Purchase | C51: 04- Dental Materials & Supplies- (DMS) | D51: 05- Endodontic Materials & Posts Supplies | E51: Endodontic Materials | F51: Paper Points | G51: NA | H51: Paper Points #35* .04 | I51: 5 | J51: Pkt | K51: APP-003504 | L51: 14 | M51: NA | N51: NA | O51: NA | P51: NA | Q51: 46508 | R51: 08- FIN/INV | S51: NA | T51: NA | U51: NA | V51: 32- Main Inventory 1 | W51: NA | X51: 7.4 | Y51: NA | Z51: NA | AA51: NA | AB51: Absorbent Paper Points - #35* .04 | AC51: Meta Biomed | AD51: Everest Medical & Safety Trading | AE51: Everest Medical & Safety Trading | AF51: Mujeeb | AG51: +971 56 683 3107 | AH51: 01- Consumables | AI51: 7 | AJ51: 1 | AK51: LPO-7191 | AL51: 70 | AM51: - | AN51: MS-INV-28421 | AO51: 70 | AP51: 0 | AQ51: 70 | AR51: -
A52: 45671 | B52: 01- Purchase | C52: 04- Dental Materials & Supplies- (DMS) | D52: 05- Endodontic Materials & Posts Supplies | E52: Endodontic Materials | F52: K Files | G52: NA | H52: K Files 31-10 | I52: 6 | J52: Pkt | K52: KF-003110 | L52: 6 | M52: NA | N52: NA | O52: NA | P52: NA | Q52: NA | R52: 08- FIN/INV | S52: NA | T52: NA | U52: NA | V52: 32- Main Inventory 1 | W52: NA | X52: 8.4 | Y52: NA | Z52: NA | AA52: NA | AB52: K Files - 31mm #10 | AC52: Mani | AD52: Everest Medical & Safety Trading | AE52: Everest Medical & Safety Trading | AF52: Mujeeb | AG52: +971 56 683 3107 | AH52: 02- Reusable | AI52: 8 | AJ52: 1 | AK52: LPO-7191 | AL52: 36 | AM52: - | AN52: MS-INV-28421 | AO52: 36 | AP52: - | AQ52: 36 | AR52: -
A53: 45671 | B53: 01- Purchase | C53: 04- Dental Materials & Supplies- (DMS) | D53: 05- Endodontic Materials & Posts Supplies | E53: Endodontic Materials | F53: Gutta Percha | G53: NA | H53: Gutta Percha #35* .04 | I53: 7 | J53: Pkt | K53: GPP-003504 | L53: 14 | M53: NA | N53: NA | O53: NA | P53: NA | Q53: 45748 | R53: 08- FIN/INV | S53: NA | T53: NA | U53: NA | V53: 32- Main Inventory 1 | W53: NA | X53: 7.4 | Y53: NA | Z53: NA | AA53: NA | AB53: Gutta Percha Points - GP #35* .04 (60s) | AC53: Meta Biomed | AD53: Everest Medical & Safety Trading | AE53: Everest Medical & Safety Trading | AF53: Mujeeb | AG53: +971 56 683 3107 | AH53: 01- Consumables | AI53: 7 | AJ53: 1 | AK53: LPO-7191 | AL53: 98 | AM53: - | AN53: MS-INV-28421 | AO53: 98 | AP53: 0 | AQ53: 98 | AR53: -
A54: 45671 | B54: 01- Purchase | C54: 03- Prevention & Control of Infection- (PCI) | D54: 01- Personal Protective Equipment | E54: Personal Protective Equipment | F54: Disposable Gown - 70 gsm | G54: NA | H54: Disposable Gown - 70 gsm | I54: 7 | J54: Pack of 10pcs | K54: ISG70-00001 | L54: 15 | M54: NA | N54: NA | O54: NA | P54: NA | Q54: NA | R54: 08- FIN/INV | S54: NA | T54: NA | U54: NA | V54: 30- Main Inventory 2 | W54: NA | X54: 6.1 | Y54: NA | Z54: NA | AA54: NA | AB54: Disposable Isolation Gown - 70 GSM Blue | AC54: Novamed | AD54: Everest Medical & Safety Trading | AE54: Everest Medical & Safety Trading | AF54: Mujeeb | AG54: +971 56 683 3107 | AH54: 01- Consumables | AI54: 7 | AJ54: 1 | AK54: LPO-7191 | AL54: 105 | AM54: - | AN54: MS-INV-28421 | AO54: 105 | AP54: 0 | AQ54: 105 | AR54: -
A55: 45671 | B55: 01- Purchase | C55: 03- Prevention & Control of Infection- (PCI) | D55: 01- Personal Protective Equipment | E55: Personal Protective Equipment | F55: Disposable Gown - 50 gsm | G55: NA | H55: Disposable Gown - 50 gsm | I55: 10 | J55: Pack of 10pcs | K55: ISG50-00001 | L55: 13 | M55: NA | N55: NA | O55: NA | P55: NA | Q55: NA | R55: 08- FIN/INV | S55: NA | T55: NA | U55: NA | V55: 30- Main Inventory 2 | W55: NA | X55: 6.2 | Y55: NA | Z55: NA | AA55: NA | AB55: Disposable Isolation Gown - 50 GSM Blue | AC55: Novamed | AD55: Everest Medical & Safety Trading | AE55: Everest Medical & Safety Trading | AF55: Mujeeb | AG55: +971 56 683 3107 | AH55: 01- Consumables | AI55: 6 | AJ55: 1 | AK55: LPO-7191 | AL55: 130 | AM55: - | AN55: MS-INV-28421 | AO55: 130 | AP55: 0 | AQ55: 130 | AR55: -
A56: 45671 | B56: 01- Purchase | C56: 02- Drugs, Needles & Triage- (DRG) | D56: 03- Vital Signs/ Emergency Supplies | E56: Surgical Materials | F56: Surgical Tape | G56: NA | H56: Surgical Tape Transpore 2.5cm x 10m | I56: 12 | J56: Pcs | K56: V4 | L56: 1.6667 | M56: NA | N56: NA | O56: NA | P56: NA | Q56: NA | R56: 08- FIN/INV | S56: NA | T56: NA | U56: NA | V56: 32- Main Inventory 1 | W56: NA | X56: 5.5 | Y56: NA | Z56: NA | AA56: NA | AB56: Surgical Tape Transpore 2.5cm x 10m | AC56: V4 | AD56: Everest Medical & Safety Trading | AE56: Everest Medical & Safety Trading | AF56: Mujeeb | AG56: +971 56 683 3107 | AH56: 01- Consumables | AI56: 5 | AJ56: 1 | AK56: LPO-7191 | AL56: 20.0004 | AM56: - | AN56: MS-INV-28421 | AO56: 20.0004 | AP56: 0 | AQ56: 20.0004 | AR56: -
A57: 45671 | B57: 01- Purchase | C57: 03- Prevention & Control of Infection- (PCI) | D57: 01- Personal Protective Equipment | E57: Personal Protective Equipment | F57: Gloves Powdered - Medium | G57: NA | H57: Gloves Powdered - Medium | I57: 20 | J57: Box | K57: DIS26 | L57: 9 | M57: NA | N57: NA | O57: NA | P57: NA | Q57: NA | R57: 08- FIN/INV | S57: NA | T57: NA | U57: NA | V57: 30- Main Inventory 2 | W57: NA | X57: 1.3 | Y57: NA | Z57: NA | AA57: NA | AB57: Gloves Powdered - Medium | AC57: Gesalife | AD57: Everest Medical & Safety Trading | AE57: Everest Medical & Safety Trading | AF57: Mujeeb | AG57: +971 56 683 3107 | AH57: 01- Consumables | AI57: 1 | AJ57: 1 | AK57: LPO-7191 | AL57: 180 | AM57: - | AN57: MS-INV-28421 | AO57: 180 | AP57: 0 | AQ57: 180 | AR57: -
A58: 45671 | B58: 01- Purchase | C58: 03- Prevention & Control of Infection- (PCI) | D58: 01- Personal Protective Equipment | E58: Personal Protective Equipment | F58: Gloves Powdered - Small | G58: NA | H58: Gloves Powdered - Small | I58: 30 | J58: Box | K58: DIS26 | L58: 9 | M58: NA | N58: NA | O58: NA | P58: NA | Q58: NA | R58: 08- FIN/INV | S58: NA | T58: NA | U58: NA | V58: 30- Main Inventory 2 | W58: NA | X58: 2.3 | Y58: NA | Z58: NA | AA58: NA | AB58: Gloves Powdered - Small | AC58: Gesalife | AD58: Everest Medical & Safety Trading | AE58: Everest Medical & Safety Trading | AF58: Mujeeb | AG58: +971 56 683 3107 | AH58: 01- Consumables | AI58: 2 | AJ58: 1 | AK58: LPO-7191 | AL58: 270 | AM58: - | AN58: MS-INV-28421 | AO58: 270 | AP58: - | AQ58: 270 | AR58: -
A59: 45671 | B59: 01- Purchase | C59: 03- Prevention & Control of Infection- (PCI) | D59: 03- General & Waste Management | E59: General Materials | F59: Z Fold Tissue | G59: NA | H59: Z Fold Tissue | I59: 32 | J59: Bundle | K59: DIS142 | L59: 3.04 | M59: NA | N59: NA | O59: NA | P59: NA | Q59: NA | R59: 08- FIN/INV | S59: NA | T59: NA | U59: NA | V59: 30- Main Inventory 2 | W59: NA | X59: 5.2 | Y59: NA | Z59: NA | AA59: NA | AB59: Hand Towel - Z Fold Tissues - 2 Ply (150*16 Pkt) | AC59: NA | AD59: Everest Medical & Safety Trading | AE59: Everest Medical & Safety Trading | AF59: Mujeeb | AG59: +971 56 683 3107 | AH59: 01- Consumables | AI59: 5 | AJ59: 1 | AK59: LPO-7191 | AL59: 97.28 | AM59: - | AN59: MS-INV-28421 | AO59: 97.28 | AP59: 4.864 | AQ59: 102.144 | AR59: -
A60: 45671 | B60: 01- Purchase | C60: 03- Prevention & Control of Infection- (PCI) | D60: 01- Personal Protective Equipment | E60: Personal Protective Equipment | F60: Dental Chair Cover | G60: NA | H60: Dental Chair Cover | I60: 40 | J60: Pc | K60: DCC-002BLUE | L60: 6 | M60: NA | N60: NA | O60: NA | P60: NA | Q60: NA | R60: 08- FIN/INV | S60: NA | T60: NA | U60: NA | V60: 30- Main Inventory 2 | W60: NA | X60: 4.2 | Y60: NA | Z60: NA | AA60: NA | AB60: Dental Full Chair Cover Non Woven Blue | AC60: NOVAMED | AD60: Everest Medical & Safety Trading | AE60: Everest Medical & Safety Trading | AF60: Mujeeb | AG60: +971 56 683 3107 | AH60: 01- Consumables | AI60: 4 | AJ60: 1 | AK60: LPO-7191 | AL60: 240 | AM60: - | AN60: MS-INV-28421 | AO60: 240 | AP60: 0 | AQ60: 240 | AR60: -
A61: 45671 | B61: 01- Purchase | C61: 03- Prevention & Control of Infection- (PCI) | D61: 05- Sterilization Monitoring | E61: Sterilization Monitoring | F61: Bowie Dick | G61: NA | H61: Bowie Dick | I61: 42 | J61: Pack | K61: BD-200W | L61: 5.25 | M61: NA | N61: NA | O61: NA | P61: NA | Q61: 46235 | R61: 08- FIN/INV | S61: NA | T61: NA | U61: NA | V61: 30- Main Inventory 2 | W61: NA | X61: 2.4 | Y61: NA | Z61: NA | AA61: NA | AB61: Bowiedick Test Pack | AC61: Steristar | AD61: Everest Medical & Safety Trading | AE61: Everest Medical & Safety Trading | AF61: Mujeeb | AG61: +971 56 683 3107 | AH61: 01- Consumables | AI61: 2 | AJ61: 1 | AK61: LPO-7191 | AL61: 220.5 | AM61: - | AN61: MS-INV-28421 | AO61: 220.5 | AP61: 11.025 | AQ61: 231.525 | AR61: -
A62: 45671 | B62: 01- Purchase | C62: 04- Dental Materials & Supplies- (DMS) | D62: 06- Surgical Materials & Supplies | E62: Surgical Materials | F62: Saline | G62: NA | H62: Saline | I62: 45 | J62: Bottle | K62: SSC-000.09 | L62: 2.75 | M62: NA | N62: NA | O62: NA | P62: NA | Q62: 46296 | R62: 08- FIN/INV | S62: NA | T62: NA | U62: NA | V62: 32- Main Inventory 1 | W62: NA | X62: 8.6 | Y62: NA | Z62: NA | AA62: NA | AB62: Saline - Sodium Chloride 0.9% | AC62: KSP PHARMA | AD62: Everest Medical & Safety Trading | AE62: Everest Medical & Safety Trading | AF62: Mujeeb | AG62: +971 56 683 3107 | AH62: 01- Consumables | AI62: 8 | AJ62: 1 | AK62: LPO-7191 | AL62: 123.75 | AM62: - | AN62: MS-INV-28421 | AO62: 123.75 | AP62: 0 | AQ62: 123.75 | AR62: -
A63: 45672 | B63: 01- Purchase | C63: 04- Dental Materials & Supplies- (DMS) | D63: 05- Endodontic Materials & Posts Supplies | E63: Endodontic Materials | F63: Viopex - Temporary Filling | G63: NA | H63: Viopex - Temporary Filling | I63: 2 | J63: Pack | K63: VPX21014 | L63: 60 | M63: NA | N63: NA | O63: NA | P63: NA | Q63: 46021 | R63: 08- FIN/INV | S63: NA | T63: NA | U63: NA | V63: 32- Main Inventory 1 | W63: NA | X63: 7.4 | Y63: NA | Z63: NA | AA63: NA | AB63: Viopex - Temporary Root Canal Filling Material | AC63: SPIDENT | AD63: IRA Medical Supplies | AE63: IRA Medical Supplies | AF63: Mohammed Rashid | AG63: +971 56 272 8220 | AH63: 01- Consumables | AI63: 7 | AJ63: 1 | AK63: LPO-7219 | AL63: 120 | AM63: - | AN63: IRA/INV/25-02765 | AO63: 120 | AP63: 0 | AQ63: 120 | AR63: -
A64: 45672 | B64: 01- Purchase | C64: 04- Dental Materials & Supplies- (DMS) | D64: 07- Impression Materials & Supplies | E64: Impression Materials | F64: Core Build up material/Dentocore | G64: NA | H64: Core Build up material/Dentocore | I64: 2 | J64: Pack | K64: 1319006-A3 | L64: 135 | M64: NA | N64: NA | O64: NA | P64: NA | Q64: 45431 | R64: 08- FIN/INV | S64: NA | T64: NA | U64: NA | V64: 32- Main Inventory 1 | W64: NA | X64: 7.5 | Y64: NA | Z64: NA | AA64: NA | AB64: Automix/Dual Cured Core Build-Up Composite, Shade A3 | AC64: DENTKIST | AD64: IRA Medical Supplies | AE64: IRA Medical Supplies | AF64: Mohammed Rashid | AG64: +971 56 272 8220 | AH64: 01- Consumables | AI64: 7 | AJ64: 1 | AK64: LPO-7219 | AL64: 270 | AM64: - | AN64: IRA/INV/25-02765 | AO64: 270 | AP64: 0 | AQ64: 270 | AR64: -
A65: 45672 | B65: 01- Purchase | C65: 02- Drugs, Needles & Triage- (DRG) | D65: 03- Vital Signs/ Emergency Supplies | E65: Emergency Supplies | F65: Emergency Blanket | G65: NA | H65: Emergency Blanket | I65: 4 | J65: Pcs | K65: NA | L65: 9 | M65: NA | N65: NA | O65: NA | P65: NA | Q65: NA | R65: 08- FIN/INV | S65: NA | T65: NA | U65: NA | V65: 32- Main Inventory 1 | W65: NA | X65: 5.2 | Y65: NA | Z65: NA | AA65: NA | AB65: Emergency Blanket | AC65: NA | AD65: IRA Medical Supplies | AE65: IRA Medical Supplies | AF65: Mohammed Rashid | AG65: +971 56 272 8220 | AH65: 01- Consumables | AI65: 5 | AJ65: 1 | AK65: LPO-7219 | AL65: 36 | AM65: - | AN65: IRA/INV/25-02765 | AO65: 36 | AP65: 1.8 | AQ65: 37.8 | AR65: -
A66: 45672 | B66: 01- Purchase | C66: 04- Dental Materials & Supplies- (DMS) | D66: 07- Impression Materials & Supplies | E66: Impression Materials | F66: Bite Registration | G66: NA | H66: Bite Registration | I66: 4 | J66: Pack of 2tube | K66: 387507 | L66: 110 | M66: NA | N66: NA | O66: NA | P66: NA | Q66: 45716 | R66: 08- FIN/INV | S66: NA | T66: NA | U66: NA | V66: 32- Main Inventory 1 | W66: NA | X66: 7.5 | Y66: NA | Z66: NA | AA66: NA | AB66: Bite Registration Material | AC66: R&S | AD66: IRA Medical Supplies | AE66: IRA Medical Supplies | AF66: Mohammed Rashid | AG66: +971 56 272 8220 | AH66: 01- Consumables | AI66: 7 | AJ66: 1 | AK66: LPO-7219 | AL66: 440 | AM66: - | AN66: IRA/INV/25-02765 | AO66: 440 | AP66: 0 | AQ66: 440 | AR66: -
A67: 45672 | B67: 01- Purchase | C67: 03- Prevention & Control of Infection- (PCI) | D67: 01- Personal Protective Equipment | E67: Personal Protective Equipment | F67: Cam Covers | G67: NA | H67: Cam Covers | I67: 4 | J67: Pack | K67: 1A6410 | L67: 40 | M67: NA | N67: NA | O67: NA | P67: NA | Q67: 46266 | R67: 08- FIN/INV | S67: NA | T67: NA | U67: NA | V67: 30- Main Inventory 2 | W67: NA | X67: 2.4 | Y67: NA | Z67: NA | AA67: NA | AB67: Camera Covers/Intraoral Camera Sheath | AC67: DOCHEM | AD67: IRA Medical Supplies | AE67: IRA Medical Supplies | AF67: Mohammed Rashid | AG67: +971 56 272 8220 | AH67: 01- Consumables | AI67: 2 | AJ67: 1 | AK67: LPO-7219 | AL67: 160 | AM67: - | AN67: IRA/INV/25-02765 | AO67: 160 | AP67: 0 | AQ67: 160 | AR67: -
A68: 45672 | B68: 01- Purchase | C68: 03- Prevention & Control of Infection- (PCI) | D68: 01- Personal Protective Equipment | E68: Personal Protective Equipment | F68: Shoe Cover | G68: NA | H68: Shoe Cover | I68: 4 | J68: Pack of 100 Pcs | K68: SCNW-00001 | L68: 14 | M68: NA | N68: NA | O68: NA | P68: NA | Q68: NA | R68: 08- FIN/INV | S68: NA | T68: NA | U68: NA | V68: 30- Main Inventory 2 | W68: NA | X68: 3.1 | Y68: NA | Z68: NA | AA68: NA | AB68: Shoe Cover Non-Woven | AC68: Medinorm | AD68: IRA Medical Supplies | AE68: IRA Medical Supplies | AF68: Mohammed Rashid | AG68: +971 56 272 8220 | AH68: 01- Consumables | AI68: 2 | AJ68: 1 | AK68: LPO-7219 | AL68: 56 | AM68: - | AN68: IRA/INV/25-02765 | AO68: 56 | AP68: 0 | AQ68: 56 | AR68: -
A69: 45672 | B69: 01- Purchase | C69: 04- Dental Materials & Supplies- (DMS) | D69: 04- Restorative Fillings, Adhesives & Supplies | E69: Restorative Fillings | F69: Micro Applicator -Regular | G69: NA | H69: Micro Applicator -Regular | I69: 4 | J69: Tube | K69: MAB-00001 | L69: 7.5 | M69: NA | N69: NA | O69: NA | P69: NA | Q69: NA | R69: 08- FIN/INV | S69: NA | T69: NA | U69: NA | V69: 32- Main Inventory 1 | W69: NA | X69: 7.3 | Y69: NA | Z69: NA | AA69: NA | AB69: Micro Brush Applicator - Regular | AC69: MICRO-B | AD69: IRA Medical Supplies | AE69: IRA Medical Supplies | AF69: Mohammed Rashid | AG69: +971 56 272 8220 | AH69: 01- Consumables | AI69: 7 | AJ69: 1 | AK69: LPO-7219 | AL69: 30 | AM69: - | AN69: IRA/INV/25-02765 | AO69: 30 | AP69: 0 | AQ69: 30 | AR69: -
A70: 45672 | B70: 01- Purchase | C70: 03- Prevention & Control of Infection- (PCI) | D70: 02- Disinfectants & Lubricants | E70: Disinfectants | F70: Sanitizer Gel | G70: NA | H70: Hand Sanitizer Pouch - 1Ltr | I70: 4 | J70: Pouch | K70: DIS336 | L70: 18 | M70: NA | N70: NA | O70: NA | P70: NA | Q70: 46022 | R70: 08- FIN/INV | S70: NA | T70: NA | U70: NA | V70: 30- Main Inventory 2 | W70: NA | X70: 4.4 | Y70: NA | Z70: NA | AA70: NA | AB70: Hand Sanitizer Gel - 1 Ltr | AC70: NA | AD70: IRA Medical Supplies | AE70: IRA Medical Supplies | AF70: Mohammed Rashid | AG70: +971 56 272 8220 | AH70: 01- Consumables | AI70: 4 | AJ70: 1 | AK70: LPO-7219 | AL70: 72 | AM70: - | AN70: IRA/INV/25-02765 | AO70: 72 | AP70: 3.6 | AQ70: 75.6 | AR70: -
A71: 45672 | B71: 01- Purchase | C71: 03- Prevention & Control of Infection- (PCI) | D71: 01- Personal Protective Equipment | E71: Personal Protective Equipment | F71: Saliva Ejector | G71: NA | H71: Saliva Ejector | I71: 6 | J71: Pack of 100 Pcs | K71: SE-00001 | L71: 8 | M71: NA | N71: NA | O71: NA | P71: NA | Q71: NA | R71: 08- FIN/INV | S71: NA | T71: NA | U71: NA | V71: 30- Main Inventory 2 | W71: NA | X71: 5.3 | Y71: NA | Z71: NA | AA71: NA | AB71: Saliva Ejector | AC71: EUROMED | AD71: IRA Medical Supplies | AE71: IRA Medical Supplies | AF71: Mohammed Rashid | AG71: +971 56 272 8220 | AH71: 01- Consumables | AI71: 5 | AJ71: 1 | AK71: LPO-7219 | AL71: 48 | AM71: - | AN71: IRA/INV/25-02765 | AO71: 48 | AP71: 0 | AQ71: 48 | AR71: -
A72: 45672 | B72: 01- Purchase | C72: 03- Prevention & Control of Infection- (PCI) | D72: 01- Personal Protective Equipment | E72: Personal Protective Equipment | F72: Dental Bibs | G72: NA | H72: Dental Bibs | I72: 12 | J72: Bundle | K72: DB-3-00001 | L72: 7.5 | M72: NA | N72: NA | O72: NA | P72: NA | Q72: NA | R72: 08- FIN/INV | S72: NA | T72: NA | U72: NA | V72: 30- Main Inventory 2 | W72: NA | X72: 4.1 | Y72: NA | Z72: NA | AA72: NA | AB72: Dental Bib (13*18) (4pcs) | AC72: LOMAR | AD72: IRA Medical Supplies | AE72: IRA Medical Supplies | AF72: Mohammed Rashid | AG72: +971 56 272 8220 | AH72: 01- Consumables | AI72: 4 | AJ72: 1 | AK72: LPO-7219 | AL72: 90 | AM72: - | AN72: IRA/INV/25-02765 | AO72: 90 | AP72: 0 | AQ72: 90 | AR72: -
A73: 45672 | B73: 01- Purchase | C73: 03- Prevention & Control of Infection- (PCI) | D73: 01- Personal Protective Equipment | E73: Personal Protective Equipment | F73: Gloves Powdered - Medium | G73: NA | H73: Gloves Powdered - Medium | I73: 20 | J73: Box | K73: DIS24 | L73: 9 | M73: NA | N73: NA | O73: NA | P73: NA | Q73: NA | R73: 08- FIN/INV | S73: NA | T73: NA | U73: NA | V73: 30- Main Inventory 2 | W73: NA | X73: 1.3 | Y73: NA | Z73: NA | AA73: NA | AB73: Gloves Powdered - Medium | AC73: MaxGuard | AD73: IRA Medical Supplies | AE73: IRA Medical Supplies | AF73: Mohammed Rashid | AG73: +971 56 272 8220 | AH73: 01- Consumables | AI73: 1 | AJ73: 1 | AK73: LPO-7219 | AL73: 180 | AM73: - | AN73: IRA/INV/25-02765 | AO73: 180 | AP73: 0 | AQ73: 180 | AR73: -
A74: 45672 | B74: 01- Purchase | C74: 03- Prevention & Control of Infection- (PCI) | D74: 01- Personal Protective Equipment | E74: Personal Protective Equipment | F74: Gloves Powdered - Small | G74: NA | H74: Gloves Powdered - Small | I74: 30 | J74: Box | K74: DIS26 | L74: 9 | M74: NA | N74: NA | O74: NA | P74: NA | Q74: NA | R74: 08- FIN/INV | S74: NA | T74: NA | U74: NA | V74: 30- Main Inventory 2 | W74: NA | X74: 2.3 | Y74: NA | Z74: NA | AA74: NA | AB74: Gloves Powdered - Small | AC74: Gesalife | AD74: IRA Medical Supplies | AE74: IRA Medical Supplies | AF74: Mohammed Rashid | AG74: +971 56 272 8220 | AH74: 01- Consumables | AI74: 2 | AJ74: 1 | AK74: LPO-7219 | AL74: 270 | AM74: - | AN74: IRA/INV/25-02765 | AO74: 270 | AP74: - | AQ74: 270 | AR74: -
A75: 45672 | B75: 01- Purchase | C75: 02- Drugs, Needles & Triage- (DRG) | D75: 04- Needles & Syringes | E75: IV Set | F75: IV Set | G75: NA | H75: IV Set | I75: 50 | J75: Pcs | K75: NA | L75: 0.85 | M75: NA | N75: NA | O75: NA | P75: NA | Q75: NA | R75: 08- FIN/INV | S75: NA | T75: NA | U75: NA | V75: 32- Main Inventory 1 | W75: NA | X75: 5.2 | Y75: NA | Z75: NA | AA75: NA | AB75: I.V Administration Set | AC75: NA | AD75: IRA Medical Supplies | AE75: IRA Medical Supplies | AF75: Mohammed Rashid | AG75: +971 56 272 8220 | AH75: 01- Consumables | AI75: 5 | AJ75: 1 | AK75: LPO-7219 | AL75: 42.5 | AM75: - | AN75: IRA/INV/25-02765 | AO75: 42.5 | AP75: 0 | AQ75: 42.5 | AR75: -
A76: 45673 | B76: 01- Purchase | C76: 06- Laboratory- (LAB) | D76: 06- Dental Stone, Stains & Wax | E76: Stains | F76: Ceramic Intensive Gingiva 2 | G76: NA | H76: Ceramic Intensive Gingiva 2 | I76: 1 | J76: Bottle | K76: CIG02 | L76: 190 | M76: NA | N76: NA | O76: NA | P76: NA | Q76: NA | R76: 08- FIN/INV | S76: NA | T76: NA | U76: NA | V76: 32- Main Inventory 1 | W76: NA | X76: 3.6 | Y76: NA | Z76: NA | AA76: NA | AB76: IPS e.max Ceram Intensive Gingiva 20 g 2 | AC76: IPS EMAX | AD76: Al Sawari Pharma & Medical Equip. Store LLC | AE76: Al Sawari Pharma & Medical Equip. Store LLC | AF76: Amr | AG76: +971 50 809 7422 | AH76: 01- Consumables | AI76: 3 | AJ76: 1 | AK76: LPO-7240 | AL76: 190 | AM76: - | AN76: 59459 | AO76: 190 | AP76: - | AQ76: 190 | AR76: 190
A77: 45673 | B77: 01- Purchase | C77: 06- Laboratory- (LAB) | D77: 06- Dental Stone, Stains & Wax | E77: Stains | F77: Ceramic Intensive Gingiva 1 | G77: NA | H77: Ceramic Intensive Gingiva 1 | I77: 1 | J77: Bottle | K77: CIG01 | L77: 190 | M77: NA | N77: NA | O77: NA | P77: NA | Q77: NA | R77: 08- FIN/INV | S77: NA | T77: NA | U77: NA | V77: 32- Main Inventory 1 | W77: NA | X77: 3.6 | Y77: NA | Z77: NA | AA77: NA | AB77: IPS e.max Ceram Intensive Gingiva 20 g 1 | AC77: IPS EMAX | AD77: Al Sawari Pharma & Medical Equip. Store LLC | AE77: Al Sawari Pharma & Medical Equip. Store LLC | AF77: Amr | AG77: +971 50 809 7422 | AH77: 01- Consumables | AI77: 3 | AJ77: 1 | AK77: LPO-7240 | AL77: 190 | AM77: - | AN77: 59459 | AO77: 190 | AP77: - | AQ77: 190 | AR77: 190
A78: 45673 | B78: 01- Purchase | C78: 06- Laboratory- (LAB) | D78: 06- Dental Stone, Stains & Wax | E78: Stains | F78: Ceramic Intensive Gingiva 3 | G78: NA | H78: Ceramic Intensive Gingiva 3 | I78: 1 | J78: Bottle | K78: CIG03 | L78: 190 | M78: NA | N78: NA | O78: NA | P78: NA | Q78: NA | R78: 08- FIN/INV | S78: NA | T78: NA | U78: NA | V78: 32- Main Inventory 1 | W78: NA | X78: 3.6 | Y78: NA | Z78: NA | AA78: NA | AB78: IPS e.max Ceram Intensive Gingiva 20 g 3 | AC78: IPS EMAX | AD78: Al Sawari Pharma & Medical Equip. Store LLC | AE78: Al Sawari Pharma & Medical Equip. Store LLC | AF78: Amr | AG78: +971 50 809 7422 | AH78: 01- Consumables | AI78: 3 | AJ78: 1 | AK78: LPO-7240 | AL78: 190 | AM78: - | AN78: 59459 | AO78: 190 | AP78: - | AQ78: 190 | AR78: 190
A79: 45673 | B79: 01- Purchase | C79: 08- Facility Management & (FMS) | D79: 08- Stationaries & Printing Supplies | E79: Printing Supplies | F79: VDC FORMS | G79: NA | H79: VDC - Bowie Dick/Helix Log | I79: 5 | J79: Pcs | K79: VDC-BD/HL-01 | L79: 40 | M79: NA | N79: NA | O79: NA | P79: NA | Q79: NA | R79: 08- FIN/INV | S79: NA | T79: NA | U79: NA | V79: 30- Main Inventory 2 | W79: NA | X79: 8.1 | Y79: NA | Z79: NA | AA79: NA | AB79: VDC - Bowie Dick/Helix Log | AC79: NA | AD79: Green Line Printing Works | AE79: Green Line Printing Works | AF79: Najeeb | AG79: +971 50 546 2809 | AH79: 01- Consumables | AI79: 2 | AJ79: 1 | AK79: LPO-7238 | AL79: 200 | AM79: - | AN79: GL-4011 | AO79: 200 | AP79: 10 | AQ79: 210
A80: 45673 | B80: 01- Purchase | C80: 08- Facility Management & (FMS) | D80: 08- Stationaries & Printing Supplies | E80: Printing Supplies | F80: VDC FORMS | G80: NA | H80: VDC - Referral Form | I80: 5 | J80: Pcs | K80: VDC-RF-01 | L80: 40 | M80: NA | N80: NA | O80: NA | P80: NA | Q80: NA | R80: 08- FIN/INV | S80: NA | T80: NA | U80: NA | V80: 30- Main Inventory 2 | W80: NA | X80: 8.1 | Y80: NA | Z80: NA | AA80: NA | AB80: VDC - Referral Form | AC80: NA | AD80: Green Line Printing Works | AE80: Green Line Printing Works | AF80: Najeeb | AG80: +971 50 546 2809 | AH80: 01- Consumables | AI80: 8 | AJ80: 1 | AK80: LPO-7238 | AL80: 200 | AM80: - | AN80: GL-4011 | AO80: 200 | AP80: 10 | AQ80: 210
A81: 45673 | B81: 01- Purchase | C81: 08- Facility Management & (FMS) | D81: 08- Stationaries & Printing Supplies | E81: Printing Supplies | F81: VDC FORMS | G81: NA | H81: VDC - Payment Voucher | I81: 10 | J81: Pcs | K81: VDC-PV-01 | L81: 27.5 | M81: NA | N81: NA | O81: NA | P81: NA | Q81: NA | R81: 08- FIN/INV | S81: NA | T81: NA | U81: NA | V81: 30- Main Inventory 2 | W81: NA | X81: 8.3 | Y81: NA | Z81: NA | AA81: NA | AB81: VDC - Payment Voucher | AC81: NA | AD81: Green Line Printing Works | AE81: Green Line Printing Works | AF81: Najeeb | AG81: +971 50 546 2809 | AH81: 01- Consumables | AI81: 8 | AJ81: 1 | AK81: LPO-7238 | AL81: 275 | AM81: - | AN81: GL-4011 | AO81: 275 | AP81: 13.75 | AQ81: 288.75
A82: 45675 | B82: 01- Purchase | C82: 04- Dental Materials & Supplies- (DMS) | D82: 02- Nitrous & Oxygen Sedation | E82: Nitrous Sedation | F82: Nitrous Oxide Refill | G82: NA | H82: Nitrous Oxide Refill | I82: 1 | J82: Cylinder | K82: MI-DMS-NR-01 | L82: 150 | M82: NA | N82: NA | O82: NA | P82: NA | Q82: NA | R82: 08- FIN/INV | S82: NA | T82: NA | U82: NA | V82: 32- Main Inventory 1 | W82: NA | X82: 2.5 | Y82: NA | Z82: NA | AA82: NA | AB82: Nitrous Oxide Refill | AC82: NA | AD82: Panacea Synthetic Gas Trading LLC | AE82: Panacea Synthetic Gas Trading LLC | AF82: Suresh | AG82: +971 52 850 2873 | AH82: 01- Consumables | AI82: 2 | AJ82: 1 | AK82: LPO-7250 | AL82: 150 | AM82: - | AN82: PSGT-0502025 | AO82: 150 | AP82: 7.5 | AQ82: 157.5 | AR82: -
A83: 45675 | B83: 01- Purchase | C83: 04- Dental Materials & Supplies- (DMS) | D83: 02- Nitrous & Oxygen Sedation | E83: Nitrous Sedation | F83: Oxygen Refill | G83: NA | H83: Oxygen Refill | I83: 3 | J83: Cylinder | K83: MI-DMS-OR-01 | L83: 30 | M83: NA | N83: NA | O83: NA | P83: NA | Q83: NA | R83: 08- FIN/INV | S83: NA | T83: NA | U83: NA | V83: 32- Main Inventory 1 | W83: NA | X83: 2.5 | Y83: NA | Z83: NA | AA83: NA | AB83: Oxygen Refill | AC83: NA | AD83: Panacea Synthetic Gas Trading LLC | AE83: Panacea Synthetic Gas Trading LLC | AF83: Suresh | AG83: +971 52 850 2873 | AH83: 01- Consumables | AI83: 2 | AJ83: 1 | AK83: LPO-7250 | AL83: 90 | AM83: - | AN83: PSGT-0502025 | AO83: 90 | AP83: 4.5 | AQ83: 94.5 | AR83: -
A84: 45675 | B84: 01- Purchase | C84: 05- Implants- (IMPL) | D84: 05- Bone Grafting Materials, Synthetic | E84: Bone Grafting Materials | F84: Easy Graft 0.4ml | G84: NA | H84: Easy Graft 0.4ml | I84: 3 | J84: Syringe | K84: C11-002 | L84: 650 | M84: NA | N84: NA | O84: NA | P84: NA | Q84: 46174 | R84: 08- FIN/INV | S84: NA | T84: NA | U84: NA | V84: 32- Main Inventory 1 | W84: NA | X84: 2.1 | Y84: NA | Z84: NA | AA84: NA | AB84: Easy Graft Classic 0.4ml | AC84: Easy Graft | AD84: Sapling Drug Store | AE84: Sapling Drug Store | AF84: Abdulkalim | AG84: +971 50 851 6101 | AH84: 01- Consumables | AI84: 2 | AJ84: 1 | AK84: LPO-7239 | AL84: 1950 | AM84: - | AN84: 202528 | AO84: 1950 | AP84: 0 | AQ84: 1950 | AR84: -
A85: 45675 | B85: 01- Purchase | C85: 05- Implants- (IMPL) | D85: 05- Bone Grafting Materials, Synthetic | E85: Bone Grafting Materials | F85: Easy Graft 0.25ml | G85: NA | H85: Easy Graft 0.25ml | I85: 6 | J85: Syringe | K85: C11-002 | L85: 550 | M85: NA | N85: NA | O85: NA | P85: NA | Q85: 46478 | R85: 08- FIN/INV | S85: NA | T85: NA | U85: NA | V85: 32- Main Inventory 1 | W85: NA | X85: 2.1 | Y85: NA | Z85: NA | AA85: NA | AB85: Easy Graft Classic 0.25ml | AC85: Easy Graft | AD85: Sapling Drug Store | AE85: Sapling Drug Store | AF85: Abdulkalim | AG85: +971 50 851 6101 | AH85: 01- Consumables | AI85: 2 | AJ85: 1 | AK85: LPO-7239 | AL85: 3300 | AM85: - | AN85: 202528 | AO85: 3300 | AP85: - | AQ85: 3300 | AR85: -
A86: 45677 | B86: 01- Purchase | C86: 04- Dental Materials & Supplies- (DMS) | D86: 04- Restorative Fillings, Adhesives & Supplies | E86: Restorative Fillings | F86: Panavia Translucent | G86: NA | H86: Panavia Translucent | I86: 1 | J86: Pack of 3syringe | K86: D000281387 | L86: 596 | M86: NA | N86: NA | O86: NA | P86: NA | Q86: 46327 | R86: 08- FIN/INV | S86: NA | T86: NA | U86: NA | V86: 32- Main Inventory 1 | W86: NA | X86: 8.3 | Y86: NA | Z86: NA | AA86: NA | AB86: PNV SA Cement Plus Value (Translucent) | AC86: KURARAY | AD86: City Pharmacy Co. WLL | AE86: City Pharmacy Co. WLL | AF86: Mr.Anas | AG86: +971 55 244 0493 | AH86: 01- Consumables | AI86: 8 | AJ86: 1 | AK86: LPO-7253 | AL86: 596 | AM86: - | AN86: 1AINDCP-338183 | AO86: 596 | AP86: 0 | AQ86: 596 | AR86: -
A87: 45677 | B87: 01- Purchase | C87: 03- Prevention & Control of Infection- (PCI) | D87: 01- Personal Protective Equipment | E87: Personal Protective Equipment | F87: Roeko Steri Sleeve | G87: NA | H87: Roeko Steri Sleeve | I87: 1 | J87: Box | K87: 670101 | L87: 190 | M87: NA | N87: NA | O87: NA | P87: NA | Q87: 46508 | R87: 08- FIN/INV | S87: NA | T87: NA | U87: NA | V87: 30- Main Inventory 2 | W87: NA | X87: 2.4 | Y87: NA | Z87: NA | AA87: NA | AB87: Roeko Steri Sleeve | AC87: COLTENE | AD87: City Pharmacy Co. WLL | AE87: City Pharmacy Co. WLL | AF87: Mr.Anas | AG87: +971 55 244 0493 | AH87: 01- Consumables | AI87: 2 | AJ87: 1 | AK87: LPO-7253 | AL87: 190 | AM87: - | AN87: 1AINDCP-338183 | AO87: 190 | AP87: 0 | AQ87: 190 | AR87: -
A88: 45677 | B88: 01- Purchase | C88: 08- Facility Management & (FMS) | D88: 07- Pantry Supplies | E88: Pantry Supplies | F88: Milk Powder | G88: NA | H88: Milk Powder | I88: 2 | J88: Kilogram | K88: IGDT002 | L88: 60 | M88: NA | N88: NA | O88: NA | P88: NA | Q88: 45901 | R88: 08- FIN/INV | S88: NA | T88: NA | U88: NA | V88: 30- Main Inventory 2 | W88: NA | X88: 8.2 | Y88: NA | Z88: NA | AA88: NA | AB88: Dallmayr Topping | AC88: DALLMAYR | AD88: Jackson Trading Co. LLC | AE88: Jackson Trading Co. LLC | AF88: Sales | AG88: +971 56 975 6706 | AH88: 01- Consumables | AI88: 8 | AJ88: 1 | AK88: LPO-7259 | AL88: 120 | AM88: - | AN88: AUH-32442 | AO88: 120 | AP88: 6 | AQ88: 126 | AR88: -
A89: 45677 | B89: 01- Purchase | C89: 08- Facility Management & (FMS) | D89: 07- Pantry Supplies | E89: Pantry Supplies | F89: Coffee Powder | G89: NA | H89: Coffee Powder | I89: 2 | J89: Pack | K89: IGDE044 | L89: 90 | M89: NA | N89: NA | O89: NA | P89: NA | Q89: 45901 | R89: 08- FIN/INV | S89: NA | T89: NA | U89: NA | V89: 30- Main Inventory 2 | W89: NA | X89: 8.2 | Y89: NA | Z89: NA | AA89: NA | AB89: Espresso Barista C&B - 1Kg | AC89: DALLMAYR | AD89: Jackson Trading Co. LLC | AE89: Jackson Trading Co. LLC | AF89: Sales | AG89: +971 56 975 6706 | AH89: 01- Consumables | AI89: 8 | AJ89: 1 | AK89: LPO-7259 | AL89: 180 | AM89: - | AN89: AUH-32442 | AO89: 180 | AP89: 9 | AQ89: 189 | AR89: -
A90: 45677 | B90: 01- Purchase | C90: 03- Prevention & Control of Infection- (PCI) | D90: 02- Disinfectants & Lubricants | E90: Lubricants | F90: Handpiece Oil | G90: NA | H90: Handpiece Oil | I90: 2 | J90: Can | K90: D00Y900630 | L90: 70 | M90: NA | N90: NA | O90: NA | P90: NA | Q90: 46022 | R90: 08- FIN/INV | S90: NA | T90: NA | U90: NA | V90: 30- Main Inventory 2 | W90: NA | X90: 5.5 | Y90: NA | Z90: NA | AA90: NA | AB90: PANA SPRAY PLUS 480ML | AC90: NSK | AD90: City Pharmacy Co. WLL | AE90: City Pharmacy Co. WLL | AF90: Mr.Anas | AG90: +971 55 244 0493 | AH90: 01- Consumables | AI90: 5 | AJ90: 1 | AK90: LPO-7253 | AL90: 140 | AM90: - | AN90: 1AINDCP-338183 | AO90: 140 | AP90: 7 | AQ90: 147 | AR90: -
A91: 45677 | B91: 01- Purchase | C91: 03- Prevention & Control of Infection- (PCI) | D91: 02- Disinfectants & Lubricants | E91: Lubricants | F91: Handpiece Oil | G91: NA | H91: Handpiece Oil | I91: 2 | J91: Bottle | K91: HP-OIL-00001 | L91: 382.5 | M91: NA | N91: NA | O91: NA | P91: NA | Q91: 45931 | R91: 08- FIN/INV | S91: NA | T91: NA | U91: NA | V91: 30- Main Inventory 2 | W91: NA | X91: 5.5 | Y91: NA | Z91: NA | AA91: NA | AB91: NSK Oil 1 Bottle (Maintenance Oil)I Care | AC91: NSK | AD91: City Pharmacy Co. WLL | AE91: City Pharmacy Co. WLL | AF91: Mr.Anas | AG91: +971 55 244 0493 | AH91: 01- Consumables | AI91: 5 | AJ91: 1 | AK91: LPO-7253 | AL91: 765 | AM91: - | AN91: 1AINDCP-338183 | AO91: 765 | AP91: 0 | AQ91: 765 | AR91: -
A92: 45677 | B92: 01- Purchase | C92: 08- Facility Management & (FMS) | D92: 07- Pantry Supplies | E92: Pantry Supplies | F92: Chocolate Powder | G92: NA | H92: Chocolate Powder | I92: 3 | J92: Kilogram | K92: IGDC001 | L92: 50 | M92: NA | N92: NA | O92: NA | P92: NA | Q92: 45901 | R92: 08- FIN/INV | S92: NA | T92: NA | U92: NA | V92: 30- Main Inventory 2 | W92: NA | X92: 8.2 | Y92: NA | Z92: NA | AA92: NA | AB92: Dallmayr Premium Chocolate | AC92: DALLMAYR | AD92: Jackson Trading Co. LLC | AE92: Jackson Trading Co. LLC | AF92: Sales | AG92: +971 56 975 6706 | AH92: 01- Consumables | AI92: 8 | AJ92: 1 | AK92: LPO-7259 | AL92: 150 | AM92: - | AN92: AUH-32442 | AO92: 150 | AP92: 7.5 | AQ92: 157.5 | AR92: -
A93: 45677 | B93: 01- Purchase | C93: 04- Dental Materials & Supplies- (DMS) | D93: 04- Restorative Fillings, Adhesives & Supplies | E93: Restorative Fillings | F93: Panavia White - Single Syringe | G93: NA | H93: Panavia White - Single Syringe | I93: 3 | J93: Syringe | K93: D0004288-WD | L93: 279.5 | M93: NA | N93: NA | O93: NA | P93: NA | Q93: 46539 | R93: 08- FIN/INV | S93: NA | T93: NA | U93: NA | V93: 32- Main Inventory 1 | W93: NA | X93: 8.3 | Y93: NA | Z93: NA | AA93: NA | AB93: PNV SA Cement Plus Value (White) | AC93: KURARAY | AD93: City Pharmacy Co. WLL | AE93: City Pharmacy Co. WLL | AF93: Mr.Anas | AG93: +971 55 244 0493 | AH93: 01- Consumables | AI93: 8 | AJ93: 1 | AK93: LPO-7253 | AL93: 838.5 | AM93: - | AN93: 1AINDCP-338183 | AO93: 838.5 | AP93: 0 | AQ93: 838.5 | AR93: -
A94: 45677 | B94: 01- Purchase | C94: 08- Facility Management & (FMS) | D94: 07- Pantry Supplies | E94: Pantry Supplies | F94: Paper Cups | G94: NA | H94: Paper Cups | I94: 4 | J94: Tube of 50 Cups | K94: IGDP013 | L94: 18 | M94: NA | N94: NA | O94: NA | P94: NA | Q94: NA | R94: 08- FIN/INV | S94: NA | T94: NA | U94: NA | V94: 30- Main Inventory 2 | W94: NA | X94: 8.2 | Y94: NA | Z94: NA | AA94: NA | AB94: Dallmayr Paper Cups | AC94: DALLMAYR | AD94: Jackson Trading Co. LLC | AE94: Jackson Trading Co. LLC | AF94: Sales | AG94: +971 56 975 6706 | AH94: 01- Consumables | AI94: 8 | AJ94: 1 | AK94: LPO-7259 | AL94: 72 | AM94: - | AN94: AUH-32442 | AO94: 72 | AP94: 3.6 | AQ94: 75.6 | AR94: -
A95: 45677 | B95: 01- Purchase | C95: 04- Dental Materials & Supplies- (DMS) | D95: 04- Restorative Fillings, Adhesives & Supplies | E95: Restorative Fillings | F95: PNV Brown Tip | G95: NA | H95: PNV Brown Tip | I95: 4 | J95: Pack of 25 Pcs | K95: PNVTIP-00001 | L95: 110 | M95: NA | N95: NA | O95: NA | P95: NA | Q95: NA | R95: 08- FIN/INV | S95: NA | T95: NA | U95: NA | V95: 32- Main Inventory 1 | W95: NA | X95: 8.3 | Y95: NA | Z95: NA | AA95: NA | AB95: PNV Cement Mixing Tip- Brown | AC95: KURARAY | AD95: City Pharmacy Co. WLL | AE95: City Pharmacy Co. WLL | AF95: Mr.Anas | AG95: +971 55 244 0493 | AH95: 01- Consumables | AI95: 8 | AJ95: 1 | AK95: LPO-7253 | AL95: 440 | AM95: - | AN95: 1AINDCP-338183 | AO95: 440 | AP95: 0 | AQ95: 440 | AR95: -
A96: 45677 | B96: 01- Purchase | C96: 03- Prevention & Control of Infection- (PCI) | D96: 01- Personal Protective Equipment | E96: Personal Protective Equipment | F96: Face Mask - Medplus | G96: NA | H96: Face Mask - Medplus | I96: 5 | J96: Box of 50 Pcs | K96: NA | L96: 25 | M96: NA | N96: NA | O96: NA | P96: NA | Q96: 45992 | R96: 08- FIN/INV | S96: NA | T96: NA | U96: NA | V96: 30- Main Inventory 2 | W96: NA | X96: 1.1 | Y96: NA | Z96: NA | AA96: NA | AB96: Face Mask - Earloop - 3 Ply - Medplus | AC96: MedPlus | AD96: City Pharmacy Co. WLL | AE96: City Pharmacy Co. WLL | AF96: Mr.Anas | AG96: +971 55 244 0493 | AH96: 01- Consumables | AI96: 1 | AJ96: 1 | AK96: LPO-7253 | AL96: 125 | AM96: - | AN96: 1AINDCP-338183 | AO96: 125 | AP96: 6.25 | AQ96: 131.25 | AR96: -
A97: 45677 | B97: 01- Purchase | C97: 04- Dental Materials & Supplies- (DMS) | D97: 01- Burs & Stones Tools | E97: Burs | F97: Depth Cutter Blue | G97: NA | H97: Depth Cutter Blue | I97: 5 | J97: Pkt | K97: D834 2.1 | L97: 70 | M97: NA | N97: NA | O97: NA | P97: NA | Q97: NA | R97: 08- FIN/INV | S97: NA | T97: NA | U97: NA | V97: 32- Main Inventory 1 | W97: NA | X97: 7.4 | Y97: NA | Z97: NA | AA97: NA | AB97: Bur - Diamond Bur #122A - Stoddard | AC97: Stoddard | AD97: Al Hana Medical Equipments | AE97: Al Hana Medical Equipments | AF97: Mahamud | AG97: +971 50 219 8081 | AH97: 02- Reusable | AI97: 7 | AJ97: 1 | AK97: LPO-7278 | AL97: 350 | AM97: - | AN97: 41875 | AO97: 350 | AP97: 17.5 | AQ97: 367.5 | AR97: -
A98: 45677 | B98: 01- Purchase | C98: 04- Dental Materials & Supplies- (DMS) | D98: 01- Burs & Stones Tools | E98: Burs | F98: Needle Straight Red Burs | G98: NA | H98: Needle Straight Red Burs | I98: 5 | J98: Pkt | K98: D859 1.0 | L98: 50 | M98: NA | N98: NA | O98: NA | P98: NA | Q98: NA | R98: 08- FIN/INV | S98: NA | T98: NA | U98: NA | V98: 32- Main Inventory 1 | W98: NA | X98: 7.4 | Y98: NA | Z98: NA | AA98: NA | AB98: Bur - Diamond Bur #74 - Stoddard | AC98: Stoddard | AD98: Al Hana Medical Equipments | AE98: Al Hana Medical Equipments | AF98: Mahamud | AG98: +971 50 219 8081 | AH98: 02- Reusable | AI98: 7 | AJ98: 1 | AK98: LPO-7278 | AL98: 250 | AM98: - | AN98: 41875 | AO98: 250 | AP98: 12.5 | AQ98: 262.5 | AR98: -
A99: 45677 | B99: 01- Purchase | C99: 04- Dental Materials & Supplies- (DMS) | D99: 01- Burs & Stones Tools | E99: Burs | F99: Straight Black Cylinder Round Tip | G99: NA | H99: Straight Black Cylinder Round Tip | I99: 5 | J99: Pkt | K99: D881 SG 1.2 | L99: 60 | M99: NA | N99: NA | O99: NA | P99: NA | Q99: NA | R99: 08- FIN/INV | S99: NA | T99: NA | U99: NA | V99: 32- Main Inventory 1 | W99: NA | X99: 7.4 | Y99: NA | Z99: NA | AA99: NA | AB99: Bur - Diamond Bur #52 - Stoddard | AC99: Stoddard | AD99: Al Hana Medical Equipments | AE99: Al Hana Medical Equipments | AF99: Mahamud | AG99: +971 50 219 8081 | AH99: 02- Reusable | AI99: 7 | AJ99: 1 | AK99: LPO-7278 | AL99: 300 | AM99: - | AN99: 41875 | AO99: 300 | AP99: 15 | AQ99: 315 | AR99: -
A100: 45677 | B100: 01- Purchase | C100: 04- Dental Materials & Supplies- (DMS) | D100: 01- Burs & Stones Tools | E100: Burs | F100: Thick Blue Tapered Diamond Bur | G100: NA | H100: Thick Blue Tapered Diamond Bur | I100: 5 | J100: Pkt | K100: D856 2.3 | L100: 55 | M100: NA | N100: NA | O100: NA | P100: NA | Q100: NA | R100: 08- FIN/INV | S100: NA | T100: NA | U100: NA | V100: 32- Main Inventory 1 | W100: NA | X100: 7.4 | Y100: NA | Z100: NA | AA100: NA | AB100: Bur - Diamond Bur #63A - Stoddard | AC100: Stoddard | AD100: Al Hana Medical Equipments | AE100: Al Hana Medical Equipments | AF100: Mahamud | AG100: +971 50 219 8081 | AH100: 02- Reusable | AI100: 7 | AJ100: 1 | AK100: LPO-7278 | AL100: 275 | AM100: - | AN100: 41875 | AO100: 275 | AP100: 13.75 | AQ100: 288.75 | AR100: -
...

Sheet Salary 12-2024
B1: Salary FMO December 2024 Paid in January
B2: Record Type | C2: Employee Unique ID / 14 DIGITS | D2: Employee Name | E2: Agent ID/ BANK Routing Code | F2: Employee Card No. or IBAN | G2: Pay Start Date | H2: Pay End Date | I2: Days in Periods | J2: Fix Income | K2: Variable Income | L2: Days on Leave | M2: Basic Income | N2: OT | O2: Allowances | P2: Deductions | Q2: Net Salary | R2: Head
B3: SAL | C3: 30411119077489 | D3: CHERIE ANN RUANO | E3: Mashreq Bank PSC | F3: AE730330000019101566507 | G3: 01-12-2024 | H3: 31-121-2024 | I3: 25 | J3: 6000 | K3: =+N3+O3-P3 -> -1000 | L3: 0 | M3: =+J3 -> 6000 | N3: 0 | O3: 0 | P3: 1000 | Q3: =+M3+O3-P3 -> 5000 | R3: indirect | T3: Row Labels | U3: Sum of Net Salary
B4: SAL | C4: 10016078859321 | D4: Manju Devadasan | E4: 600310101 | F4: AE230030011943926920001 | G4: 01-12-2024 | H4: 31-12-2024 | I4: 5 | J4: 7500 | K4: =N4+O4-P4 -> -6000 | L4: 0 | M4: =+J4 -> 7500 | N4: 0 | O4: 0 | P4: 6000 | Q4: =+M4+O4-P4 -> 1500 | R4: Final Settlemt Direct nurse | T4: Doctors Salary | U4: 154008
B5: Final Settlement | C5: 30420059362009 | D5: Ramil Padilla | E5: DIB | F5: AE770240007520145057601 | G5: 01-12-2024 | H5: 31-12-2024 | I5: 4 | J5: 4000 | K5: =N5+O5-P5 -> -3413 | L5: 0 | M5: 4000 | N5: 0 | O5: 0 | P5: =4000-587 -> 3413 | Q5: =+M5+O5-P5 -> 587 | R5: Final Settlemt Direct nurse | T5: External | U5: 9000
B6: Final Settlement | C6: 10016078859321 | D6: Manju Devadasan | E6: 600310101 | F6: AE230030011943926920001 | G6: 01-12-2024 | H6: 31-12-2024 | I6: 8 | J6: 7500 | K6: =N6+O6-P6 -> -5500 | L6: 0 | M6: =+J6 -> 7500 | N6: 0 | O6: 0 | P6: 5500 | Q6: =+M6+O6-P6 -> 2000 | R6: Final Settlemt Direct nurse | T6: Final Settlemt Direct nurse | U6: 4087
B7: SAL | C7: 00105078982517 | D7: MOHAMED ABDEL MONIEM | E7: 600310101 | F7: AE230030013504627820001 | G7: 01-12-2024 | H7: 31-12-2024 | I7: 31 | J7: 3200 | K7: =N7+O7-P7 -> 5800 | L7: 0 | M7: =+J7 -> 3200 | N7: 0 | O7: =2500+1100+2500+1500+1400-3200 -> 5800 | P7: 0 | Q7: =+M7+O7-P7 -> 9000 | R7: External | S7: Saber , Saed , Alamghir , Arjun and Algien External | T7: indirect | U7: 57055
B8: SAL | C8: 00109067045968 | D8: HUSSEIN SALAH AHMED TAHOUN | E8: EMIRATES ISLAMIC BANK PJSC | F8: AE100340003708482640901 | G8: 01-12-2024 | H8: 31-12-2024 | I8: 31 | J8: 120000 | K8: =N8+O8-P8 -> 0 | L8: 0 | M8: 120000 | N8: 0 | O8: 0 | P8: 0 | Q8: =+M8+O8-P8 -> 120000 | R8: Doctors Salary | T8: Nurse Direct | U8: 24400
B9: SAL | C9: 00115028536953 | D9: HEBA HAMDY | E9: ADIB | F9: AE290500000000019267726 | G9: 01-12-2024 | H9: 31-12-2024 | I9: 31 | J9: 20000 | K9: =N9+O9-P9 -> 0 | L9: 0 | M9: =+J9 -> 20000 | N9: 0 | O9: 0 | P9: 0 | Q9: =+M9+O9-P9 -> 20000 | R9: indirect | T9: Grand Total | U9: 248550
B10: SAL | C10: 30424099342516 | D10: Kimberly Ann Natuel | E10: 600310101 | F10: AE100030012150545910001 | G10: 01-12-2024 | H10: 31-12-2024 | I10: 31 | J10: 3000 | K10: =+N10+O10-P10 -> 0 | L10: 0 | M10: 3000 | N10: 0 | O10: 0 | P10: 0 | Q10: =+O10+J10-P10 -> 3000 | R10: indirect
B11: SAL | C11: 30415118637898 | D11: RAZEL DE GUZMAN PEREZ | E11: 302620122 | F11: AE790260001015790005601 | G11: 01-12-2024 | H11: 31-12-2024 | I11: 31 | J11: 7500 | K11: =+N11+O11-P11 -> 0 | L11: 0 | M11: 7500 | N11: 0 | O11: 0 | P11: 0 | Q11: =+O11+J11-P11 -> 7500 | R11: Nurse Direct | T11: Row Labels | U11: Sum of Net Salary
B12: SAL | C12: 30413059492332 | D12: JOERILYN TURALLO JOVE | E12: 803510106 | F12: AE730351426004716443001 | G12: 01-12-2024 | H12: 31-12-2024 | I12: 31 | J12: 6000 | K12: =+N12+O12-P12 -> 0 | L12: 0 | M12: 6000 | N12: 0 | O12: 0 | P12: 0 | Q12: =+O12+J12-P12 -> 6000 | R12: Nurse Direct | T12: Direct | U12: 5500
B13: SAL | C13: 10028069336246 | D13: MARIYAM PULI MOOTIL | E13: ADCB | F13: AE790030013556902910001 | G13: 01-12-2024 | H13: 31-12-2024 | I13: 31 | J13: 4000 | K13: =+N13+O13-P13 -> 400 | L13: 0 | M13: =+J13 -> 4000 | N13: 0 | O13: 400 | P13: 0 | Q13: =+M13+O13-P13 -> 4400 | R13: indirect | T13: Final Settlement Indirect | U13: 3292
B14: SAL | C14: 00404029649957 | D14: MHD ABDULMOHSEN AMEREDDIN ALNABLSI | E14: 405010101 | F14: AE070500000000028637449 | G14: 01-12-2024 | H14: 31-12-2024 | I14: 28 | J14: 7000 | K14: =+N14+O14-P14 -> -500 | L14: 0 | M14: =+J14 -> 7000 | N14: 0 | O14: 0 | P14: 500 | Q14: =+M14+O14-P14 -> 6500 | R14: indirect | T14: indirect | U14: 49073
B15: SAL | C15: 10010089305600 | D15: ANNIE JOHN JOHN JOSEPH | E15: 302620122 | F15: AE850260001015782862801 | G15: 01-12-2024 | H15: 31-12-2024 | I15: 29 | J15: 6000 | K15: =+N15+O15-P15 -> -100 | L15: 0 | M15: =+J15 -> 6000 | N15: 0 | O15: 2400 | P15: 2500 | Q15: =+M15+O15-P15 -> 5900 | R15: Nurse Direct | T15: Grand Total | U15: 57865
B16: SAL | C16: 01023039157178 | D16: SALIM ALI HAMADANI | E16: 804020101 | F16: AE550400008042796185901 | G16: 01-12-2024 | H16: 31-12-2024 | I16: 29 | J16: 17000 | K16: =+N16+O16-P16 -> -992 | L16: 0 | M16: =+J16 -> 17000 | N16: 0 | O16: 0 | P16: 992 | Q16: =+M16+O16-P16 -> 16008 | R16: Doctors Salary
B17: SAL | C17: 30401098916506 | D17: ZENETH SALADO ZAMORA | E17: 600310101 | F17: AE230030011461513910001 | G17: 01-12-2024 | H17: 31-121-2024 | I17: 31 | J17: 5000 | K17: =+N17+O17-P17 -> 0 | L17: 0 | M17: 5000 | N17: 0 | O17: 0 | P17: 0 | Q17: =+O17+J17-P17 -> 5000 | R17: indirect
B18: SAL | C18: 00125019640220 | D18: Ibrahim Abdelkarim | E18: AL HILAL | F18: AE440530000012021710001 | G18: 01-12-2024 | H18: 31-121-2024 | I18: 31 | J18: 6000 | K18: =+N18+O18-P18 -> -1000 | L18: 0 | M18: 6000 | N18: 0 | O18: 0 | P18: 1000 | Q18: =+O18+J18-P18 -> 5000 | R18: Nurse Direct
B19: SAL | C19: 20014037665353 | D19: ASMA BUTT HAROON ZAFAR | E19: 802420101 | F19: AE430240010520243110901 | G19: 01-12-2024 | H19: 31-121-2024 | I19: 31 | J19: 18000 | K19: =+N19+O19-P19 -> 0 | L19: 0 | M19: =+J19 -> 18000 | N19: 0 | O19: 0 | P19: 0 | Q19: =+M19+O19-P19 -> 18000 | R19: Doctors Salary
B20: SAL | C20: 00105078982517 | D20: MOHAMED ABDEL MONIEM | E20: 600310101 | F20: AE230030013504627820001 | G20: 01-12-2024 | H20: 31-121-2024 | I20: 26 | J20: 3200 | K20: =+N20+O20-P20 -> -425 | L20: 0 | M20: 3200 | N20: 0 | O20: 162 | P20: 587 | Q20: =+M20+O20-P20 -> 2775 | R20: indirect
B21: SAL | C21: 30423078946762 | D21: KAE SANDRA ILAGAN GONZALES | E21: 105310101 | F21: AE330530000012756802001 | G21: 01-12-2024 | H21: 31-121-2024 | I21: 31 | J21: 4000 | K21: =+N21+O21-P21 -> 200 | L21: 0 | M21: =+J21 -> 4000 | N21: 0 | O21: 200 | P21: 0 | Q21: =+M21+O21-P21 -> 4200 | R21: indirect
B22: SAL | C22: 30402099983205 | D22: MARIFE SAMSON SOCAO | E22: 600310101 | F22: AE940030012873333910001 | G22: 01-12-2024 | H22: 31-121-2024 | I22: =31-7 -> 24 | J22: 3850 | K22: =+N22+O22-P22 -> -870 | L22: 0 | M22: =+J22 -> 3850 | N22: 0 | O22: 205 | P22: 1075 | Q22: =+M22+O22-P22 -> 2980 | R22: indirect
B23: SAL | C23: 30421029504901 | D23: JOEL MULA ABORITA | E23: 600310101 | F23: AE810030011938003910001 | G23: 01-12-2024 | H23: 31-121-2024 | I23: 31 | J23: 3000 | K23: =+N23+O23-P23 -> 200 | L23: 0 | M23: =+J23 -> 3000 | N23: 0 | O23: 200 | P23: 0 | Q23: =+M23+O23-P23 -> 3200 | R23: indirect
D25: MYSMYLE COMPANY FOR INFORMATION TECHNOLOGY | E25: MOL: 1519899
B26: Record Type | C26: Employee Unique ID / 14 DIGITS | D26: Employee Name | E26: Agent ID/ BANK Routing Code | F26: Employee Card No. or IBAN | G26: Pay Start Date | H26: Pay End Date | I26: Days in Periods | J26: Fix Income | K26: Variable Income | L26: Days on Leave | M26: Basic Income | N26: OT | O26: Allowances | P26: Deductions | Q26: Net Salary | R26: Head
B27: SAL | C27: 00531078232478 | D27: RAMI MOHAMAD ELMAHMOUD | E27: 803510106 | F27: AE640351416005651558001 | G27: 01-12-2024 | H27: 31-12-2024 | I27: 19 | J27: 5000 | K27: =N27+O27-P27 -> -1708 | L27: 0 | M27: =+J27 -> 5000 | N27: 0 | O27: 0 | P27: 1708 | Q27: =+M27+O27-P27 -> 3292 | R27: Final Settlement Indirect
B28: SAL | C28: 40315039258931 | D28: Genet Tesfaye Tumego | E28: ADCB | F28: AE110030013314321820001 | G28: 01-12-2024 | H28: 31-12-2024 | I28: 31 | J28: 1000 | K28: =+O28-P28 -> 0 | L28: 0 | M28: =+J28 -> 1000 | N28: 0 | O28: 0 | P28: 0 | Q28: =+M28+O28-P28 -> 1000 | R28: indirect
B29: SAL | C29: 30413097846043 | D29: MYRNA LANDICHO VILLEGAS | E29: 600310101 | F29: AE250030012535431910001 | G29: 01-12-2024 | H29: 31-12-2024 | I29: 31 | J29: 2700 | K29: =+N29+O29-P29 -> 150 | L29: 0 | M29: =+J29 -> 2700 | N29: 0 | O29: 150 | P29: 0 | Q29: =+M29+O29-P29 -> 2850 | R29: indirect
B30: SAL | C30: 00104028910818 | D30: MOHAMED MOHAMED MOHAMED | E30: 203320101 | F30: AE320330000019100237569 | G30: 01-12-2024 | H30: 31-12-2024 | I30: 30 | J30: 5500 | K30: =+O30-P30 -> -177 | L30: 0 | M30: =+J30 -> 5500 | N30: 0 | O30: 0 | P30: 177 | Q30: =+M30+O30-P30 -> 5323 | R30: indirect
B31: SAL | C31: 30413119268092 | D31: AUBREY ANNE HONRADO ESCANO | E31: AL HILAL DIGITAL | F31: AE750530000015690309001 | G31: 01-12-2024 | H31: 31-12-2024 | I31: 29 | J31: 6000 | K31: =+O31-P31 -> -200 | L31: 0 | M31: =+J31 -> 6000 | N31: 0 | O31: 0 | P31: 200 | Q31: =+M31+O31-P31 -> 5800 | R31: indirect
B32: SAL | C32: 30424128101925 | D32: Jessie Relojero Gromio | E32: ADCB | F32: AE020030012669209920001 | G32: 01-12-2024 | H32: 31-12-2024 | I32: 31 | J32: 3000 | K32: =+O32-P32 -> 0 | L32: 6 | M32: =+J32 -> 3000 | N32: 0 | O32: 0 | P32: 0 | Q32: =+M32+O32-P32 -> 3000 | R32: indirect
B33: SAL | C33: 30409088991714 | D33: Dieryl Patricio Mayor | E33: 600310101 | F33: AE830030011859755910001 | G33: 01-12-2024 | H33: 31-12-2024 | I33: 31 | J33: 4500 | K33: =+O33-P33 -> 0 | L33: 0 | M33: =+J33 -> 4500 | N33: 0 | O33: 0 | P33: 0 | Q33: =+M33+O33-P33 -> 4500 | R33: indirect
B34: SAL | C34: 00404030007288 | D34: OMAR MOHAMAD ALZARKAN | E34: 405010101 | F34: AE320500000000028892691 | G34: 01-12-2024 | H34: 31-12-2024 | I34: 31 | J34: 8000 | K34: =+O34-P34 -> 0 | L34: 0 | M34: =+J34 -> 8000 | N34: 0 | O34: 0 | P34: 0 | Q34: =+M34+O34-P34 -> 8000 | R34: indirect
B35: SAL | C35: 10022079255954 | D35: SHABNA JAMAL JAMALUDEEN PULAKKAVEETTIL KUNJUMOHAMED | E35: 302620122 | F35: AE150260000959069080601 | G35: 01-12-2024 | H35: 31-12-2024 | I35: 31 | J35: 4500 | K35: =+O35-P35 -> 0 | L35: 0 | M35: =+J35 -> 4500 | N35: 0 | O35: 0 | P35: 0 | Q35: =+M35+O35-P35 -> 4500 | R35: indirect
B36: SAL | C36: 00124128828013 | D36: Mohammed Hassan Labib | E36: 302620122 | F36: AE280260000215772050501 | G36: 01-12-2024 | H36: 31-12-2024 | I36: 31 | J36: 5000 | K36: =N36+O36-P36 -> 0 | L36: 0 | M36: =+J36 -> 5000 | N36: 0 | O36: 0 | P36: 0 | Q36: =+M36+O36-P36 -> 5000 | R36: indirect
B37: SAL | C37: 30423098879653 | D37: JENNIFER MANARANG IGLESIA | E37: 600310101 | F37: AE430030012236271910001 | G37: 01-12-2024 | H37: 31-12-2024 | I37: 31 | J37: 5500 | K37: =N37+O37-P37 -> 0 | L37: 0 | M37: =+J37 -> 5500 | N37: 0 | O37: 0 | P37: 0 | Q37: =+M37+O37-P37 -> 5500 | R37: Direct
B38: SAL | C38: 30407037356924 | D38: HELEN GUEVARRA | E38: 105310101 | F38: AE510530000015891288001 | G38: 01-12-2024 | H38: 31-12-2024 | I38: 31 | J38: 3500 | K38: =N38+O38-P38 -> 0 | L38: 0 | M38: =+J38 -> 3500 | N38: 0 | O38: 0 | P38: 0 | Q38: =+M38+O38-P38 -> 3500 | R38: indirect
B39: SAL | C39: 10023099650891 | D39: MOBY ANTONY ANTONY | E39: 600310101 | F39: AE270030011324999910001 | G39: 01-12-2024 | H39: 31-12-2024 | I39: =31-10 -> 21 | J39: 3000 | K39: =N39+O39-P39 -> -900 | L39: 0 | M39: =+J39 -> 3000 | N39: 0 | O39: 0 | P39: 900 | Q39: =+M39+O39-P39 -> 2100 | R39: indirect
B40: SAL | C40: 10006059728355 | D40: AASIYA SIDDIQA PASHA | E40: 600310101 | F40: AE810030011876537920001 | G40: 01-12-2024 | H40: 31-12-2024 | I40: 31 | J40: 3500 | K40: =N40+O40-P40 -> 0 | L40: 0 | M40: =+J40 -> 3500 | N40: 0 | O40: 0 | P40: 0 | Q40: =+M40+O40-P40 -> 3500 | R40: indirect
B52: Salary FMO November 2024 Paid in December
B53: Record Type | C53: Employee Unique ID / 14 DIGITS | D53: Employee Name | E53: Agent ID/ BANK Routing Code | F53: Employee Card No. or IBAN | G53: Pay Start Date | H53: Pay End Date | I53: Days in Periods | J53: Fix Income | K53: Variable Income | L53: Days on Leave | M53: Basic Income | N53: OT | O53: Allowances | P53: Deductions | Q53: Net Salary | R53: Head
B54: SAL | C54: 10008019402648 | D54: Faisal Farooqui | E54: 203320101 | F54: AE130330000019101365827 | G54: 01-10-2024 | H54: 31-10-2024 | I54: 31 | J54: 7000 | K54: =N54+O54-P54 -> -113 | L54: 0 | M54: =+J54 -> 7000 | N54: 0 | O54: 0 | P54: 113 | Q54: =+M54+O54-P54 -> 6887 | R54: nurse | U54: Row Labels | V54: Sum of Net Salary
B55: SAL | C55: 00105078982517 | D55: MOHAMED ABDEL MONIEM | E55: 600310101 | F55: AE230030013504627820001 | G55: 01-11-2024 | H55: 30-11-2024 | I55: 30 | J55: 3200 | K55: =N55+O55-P55 -> 2900 | L55: 0 | M55: =+J55 -> 3200 | N55: 0 | O55: =2400+500 -> 2900 | P55: 0 | Q55: =+M55+O55-P55 -> 6100 | R55: indirect | U55: doc | V55: 179416.36
B56: SAL | C56: 00109067015137 | D56: HUSSEIN SALAH AHMED TAHOUN | E56: EMIRATES ISLAMIC BANK PJSC | F56: AE100340003708482640901 | G56: 01-11-2024 | H56: 30-11-2024 | I56: 30 | J56: 120000 | K56: =N56+O56-P56 -> 0 | L56: 0 | M56: 120000 | N56: 0 | O56: 0 | P56: 0 | Q56: =+M56+O56-P56 -> 120000 | R56: doc | U56: indirect | V56: 65667
B57: SAL | C57: 00115028536953 | D57: HEBA HAMDY | E57: ADIB | F57: AE290500000000019267726 | G57: 01-11-2024 | H57: 30-11-2024 | I57: 30 | J57: 20000 | K57: =N57+O57-P57 -> 0 | L57: 0 | M57: =+J57 -> 20000 | N57: 0 | O57: 0 | P57: 0 | Q57: =+M57+O57-P57 -> 20000 | R57: indirect | U57: Mysmyle indirect | V57: 50152
B58: SAL | C58: 30413059492332 | D58: JOERILYN TURALLO JOVE | E58: 803510106 | F58: AE730351426004716443001 | G58: 01-11-2024 | H58: 30-11-2024 | I58: 30 | J58: 2000 | K58: =N58+O58-P58 -> 0 | L58: 1 | M58: =+J58 -> 2000 | N58: 0 | O58: 0 | P58: 0 | Q58: =+M58+O58-P58 -> 2000 | R58: nurse | U58: nurse | V58: 40770
B59: SAL | D59: Amar Labib | J59: 26424.356 | K59: =N59+O59-P59 -> 0 | L59: 2 | M59: =+J59 -> 26424.356 | N59: 0 | O59: 0 | P59: 0 | Q59: =+M59+O59-P59 -> 26424.356 | R59: doc | U59: Grand Total | V59: 336005.36
B60: SAL | C60: 30424099342516 | D60: Kimberly Ann Natuel | E60: 600310101 | F60: AE100030012150545910001 | G60: 01-11-2024 | H60: 30-11-2024 | I60: 30 | J60: 3000 | K60: 200 | L60: 0 | M60: 3000 | N60: 0 | O60: 200 | P60: 0 | Q60: 3200 | R60: indirect
B61: SAL | C61: 30401098916506 | D61: ZENETH SALADO ZAMORA | E61: 600310101 | F61: AE230030011461513910001 | G61: 01-11-2024 | H61: 30-11-2024 | I61: 30 | J61: 5000 | K61: 0 | L61: 0 | M61: 5000 | N61: 0 | O61: 0 | P61: 0 | Q61: 5000 | R61: indirect
B62: SAL | C62: 30415118637898 | D62: RAZEL DE GUZMAN PEREZ | E62: 302620122 | F62: AE790260001015790005601 | G62: 01-11-2024 | H62: 30-11-2024 | I62: 30 | J62: 7500 | K62: 200 | L62: 0 | M62: 7500 | N62: 0 | O62: 200 | P62: 0 | Q62: 7700 | R62: nurse | T62: Diff in Salary
B63: SAL | C63: 30413059492332 | D63: JOERILYN TURALLO JOVE | E63: 803510106 | F63: AE730351426004716443001 | G63: 01-11-2024 | H63: 30-11-2024 | I63: 30 | J63: 6000 | K63: 200 | L63: 0 | M63: 6000 | N63: 0 | O63: 200 | P63: 0 | Q63: 6200 | R63: nurse | T63: Sajed Tahoun | U63: Salary FMO Aug2024 | V63: Rest Salary FMO July and Aug2024 to Sajed Tahoun | W63: 360
B64: SAL | C64: 00125019640220 | D64: Ibrahim Abdelkarim | E64: AL HILAL | F64: AE440530000012021710001 | G64: 01-11-2024 | H64: 30-11-2024 | I64: 29.75 | J64: 6000 | K64: -50 | L64: 0 | M64: 6000 | N64: 0 | O64: 0 | P64: 50 | Q64: 5950 | R64: nurse | T64: Staff | U64: Salary FMO NOV2024 | V64: Salary FMO NOV2024 to AASiya Siddiqa only 6 Days | W64: 700
B65: SAL | C65: 10028069336246 | D65: MARIYAM PULI MOOTIL | E65: ADCB | F65: AE790030013556902910001 | G65: 01-11-2024 | H65: 30-11-2024 | I65: 30 | J65: 4000 | K65: 400 | L65: 0 | M65: 4000 | N65: 0 | O65: 400 | P65: 0 | Q65: 4400 | R65: indirect | T65: Staff | U65: Salary FMO NOV2024 | V65: Rest Salary Amount FMO NOV2024 to Jessie | W65: 400
B66: SAL | C66: 20014037665353 | D66: ASMA BUTT HAROON ZAFAR | E66: 802420101 | F66: AE430240010520243110901 | G66: 01-11-2024 | H66: 30-11-2024 | I66: 29.25 | J66: 18000 | K66: -450 | L66: 0 | M66: 18000 | N66: 0 | O66: 0 | P66: 450 | Q66: 17550 | R66: doc | T66: Lari Exchange | U66: Salary FMO NOV2024 | V66: Salary FMO NOV2024 to Genet | W66: 1000
B67: SAL | C67: 00105078982517 | D67: MOHAMED ABDEL MONIEM | E67: 600310101 | F67: AE230030013504627820001 | G67: 01-11-2024 | H67: 30-11-2024 | I67: 30 | J67: 3200 | K67: 0 | L67: 0 | M67: 3200 | N67: 0 | O67: 0 | P67: 0 | Q67: 3200 | R67: indirect | T67: Staff | U67: Salary Advance | V67: Salary Advance FMO Dec 2024 to Elbie | W67: 1350
B68: SAL | C68: 30423078946762 | D68: KAE SANDRA ILAGAN GONZALES | E68: 105310101 | F68: AE330530000012756802001 | G68: 01-11-2024 | H68: 30-11-2024 | I68: 30 | J68: 4000 | K68: 217 | L68: 0 | M68: 4000 | N68: 0 | O68: 350 | P68: 133 | Q68: 4217 | R68: indirect | T68: Sajed Tahoun | U68: Salary FMO NOV2024 | V68: Salary FMO NOV2024 to Sajed Tahoun | W68: 1680
B69: SAL | C69: 10010089305600 | D69: ANNIE JOHN JOHN JOSEPH | E69: 302620122 | F69: AE850260001015782862801 | G69: 01-11-2024 | H69: 30-11-2024 | I69: 29.75 | J69: 6000 | K69: -50 | L69: 0 | M69: 6000 | N69: 0 | O69: 200 | P69: 250 | Q69: 5950 | R69: nurse | W69: =SUM(W63:W68) -> 5490
B70: SAL | C70: 30411119077489 | D70: CHERIE ANN RUANO | E70: Mashreq Bank PSC | F70: AE730330000019101566507 | G70: 01-11-2024 | H70: 30-11-2024 | I70: 30 | J70: 6000 | K70: 0 | L70: 0 | M70: 6000 | N70: 0 | O70: 0 | P70: 0 | Q70: 6000 | R70: indirect
B71: SAL | C71: 01023039157178 | D71: SALIM ALI HAMADANI | E71: 804020101 | F71: AE550400008042796185901 | G71: 01-11-2024 | H71: 30-11-2024 | I71: 27 | J71: 17000 | K71: -1558 | L71: 0 | M71: 17000 | N71: 0 | O71: 0 | P71: 1558 | Q71: 15442 | R71: doc
B72: SAL | C72: 30402099983205 | D72: MARIFE SAMSON SOCAO | E72: 600310101 | F72: AE940030012873333910001 | G72: 01-11-2024 | H72: 30-11-2024 | I72: 30 | J72: 3500 | K72: 350 | L72: 0 | M72: 3500 | N72: 0 | O72: 350 | P72: 0 | Q72: 3850 | R72: indirect
B73: SAL | C73: 30421029504901 | D73: JOEL MULA ABORITA | E73: 600310101 | F73: AE810030011938003910001 | G73: 01-11-2024 | H73: 30-11-2024 | I73: 30 | J73: 3000 | K73: 200 | L73: 0 | M73: 3000 | N73: 0 | O73: 200 | P73: 0 | Q73: 3200 | R73: indirect
B74: SAL | C74: 00404029649957 | D74: MHD ABDULMOHSEN AMEREDDIN ALNABLSI | E74: 405010101 | F74: AE070500000000028637449 | G74: 01-11-2024 | H74: 30-11-2024 | I74: 30 | J74: 7000 | K74: -500 | L74: 0 | M74: 7000 | N74: 0 | O74: 0 | P74: 500 | Q74: 6500 | R74: indirect
B75: SAL | C75: 10016078859321 | D75: Manju Devadasan | E75: 600310101 | F75: AE230030011943926920001 | G75: 01-11-2024 | H75: 30-11-2024 | I75: 11 | J75: 7500 | K75: -4750 | L75: 0 | M75: 7500 | N75: 0 | O75: 0 | P75: 4750 | Q75: 2750 | R75: nurse
B76: SAL | C76: 30420059362009 | D76: Ramil Padilla | E76: DIB | F76: AE770240007520145057601 | G76: 01-11-2024 | H76: 30-11-2024 | I76: 25 | J76: 4000 | K76: -667 | L76: 0 | M76: 4000 | N76: 0 | O76: 0 | P76: 667 | Q76: 3333 | R76: nurse
B77: SAL | C77: 30413119268092 | D77: AUBREY ANNE HONRADO ESCANO | E77: 105310101 | F77: AE480530000015690309002 | G77: 01-11-2024 | H77: 30-11-2024 | I77: 30 | J77: 6000 | K77: =+O77-P77 -> 0 | L77: 0 | M77: =+J77 -> 6000 | N77: 0 | O77: 0 | P77: 0 | Q77: =+M77+O77-P77 -> 6000 | R77: Mysmyle indirect
B78: SAL | C78: 30424128101925 | D78: Jessie Relojero Gromio | E78: ADCB | F78: AE020030012669209920001 | G78: 01-11-2024 | H78: 30-11-2024 | I78: 30 | J78: 3000 | K78: =+O78-P78 -> 0 | L78: 6 | M78: =+J78 -> 3000 | N78: 0 | O78: 0 | P78: 0 | Q78: =+M78+O78-P78 -> 3000 | R78: Mysmyle indirect
B79: SAL | C79: 30409088991714 | D79: Dieryl Patricio Mayor | E79: 600310101 | F79: AE830030011859755910001 | G79: 01-11-2024 | H79: 30-11-2024 | I79: 30 | J79: 4500 | K79: =+O79-P79 -> 0 | L79: 0 | M79: =+J79 -> 4500 | N79: 0 | O79: 0 | P79: 0 | Q79: =+M79+O79-P79 -> 4500 | R79: Mysmyle indirect
B80: SAL | C80: 00404030007288 | D80: OMAR MOHAMAD ALZARKAN | E80: 405010101 | F80: AE320500000000028892691 | G80: 01-11-2024 | H80: 30-11-2024 | I80: 30 | J80: 8000 | K80: =+O80-P80 -> 0 | L80: 0 | M80: =+J80 -> 8000 | N80: 0 | O80: 0 | P80: 0 | Q80: =+M80+O80-P80 -> 8000 | R80: Mysmyle indirect
B81: SAL | C81: 00104028910818 | D81: MOHAMED MOHAMED MOHAMED | E81: 203320101 | F81: AE320330000019100237569 | G81: 01-11-2024 | H81: 30-11-2024 | I81: 30 | J81: 5500 | K81: =+O81-P81 -> 0 | L81: 0 | M81: =+J81 -> 5500 | N81: 0 | O81: 0 | P81: 0 | Q81: =+M81+O81-P81 -> 5500 | R81: Mysmyle indirect
B82: SAL | C82: 10022079255954 | D82: SHABNA JAMAL JAMALUDEEN PULAKKAVEETTIL KUNJUMOHAMED | E82: 302620122 | F82: AE150260000959069080601 | G82: 01-11-2024 | H82: 30-11-2024 | I82: 30 | J82: 4500 | K82: =+O82-P82 -> 0 | L82: 0 | M82: =+J82 -> 4500 | N82: 0 | O82: 0 | P82: 0 | Q82: =+M82+O82-P82 -> 4500 | R82: Mysmyle indirect
B83: SAL | C83: 30413097846043 | D83: MYRNA LANDICHO VILLEGAS | E83: 600310101 | F83: AE250030012535431910001 | G83: 01-11-2024 | H83: 30-11-2024 | I83: 30 | J83: 2700 | K83: =+N83+O83-P83 -> 0 | L83: 0 | M83: =+J83 -> 2700 | N83: 0 | O83: 0 | P83: 0 | Q83: =+M83+O83-P83 -> 2700 | R83: Mysmyle indirect
B84: SAL | C84: 00531078232478 | D84: RAMI MOHAMAD ELMAHMOUD | E84: 803510106 | F84: AE640351416005651558001 | G84: 01-11-2024 | H84: 30-11-2024 | I84: 30 | J84: 5000 | K84: =N84+O84-P84 -> 33 | L84: 0 | M84: =+J84 -> 5000 | N84: 0 | O84: 200 | P84: 167 | Q84: =+M84+O84-P84 -> 5033 | R84: Mysmyle indirect
B85: SAL | C85: 00124128828013 | D85: Mohammed Hassan Labib | E85: 426710101 | F85: 5501100005273967 | G85: 01-11-2024 | H85: 30-11-2024 | I85: 30 | J85: 5000 | K85: =N85+O85-P85 -> 0 | L85: 0 | M85: =+J85 -> 5000 | N85: 0 | O85: 0 | P85: 0 | Q85: =+M85+O85-P85 -> 5000 | R85: Mysmyle indirect
B86: SAL | C86: 30407037356924 | D86: HELEN GUEVARRA | E86: Al Hilal | F86: AE510530000015891288001 | G86: 01-11-2024 | H86: 30-11-2024 | I86: 16 | J86: 3500 | K86: =+O86-P86 -> -1581 | L86: 0 | M86: =+J86 -> 3500 | N86: 0 | O86: 0 | P86: 1581 | Q86: =+M86+O86-P86 -> 1919 | R86: Mysmyle indirect
B87: SAL | C87: 40315039258931 | D87: Genet Tesfaye Tumego | E87: ADCB | F87: AE110030013314321820001 | G87: 01-11-2024 | H87: 30-11-2024 | I87: 30 | J87: 1000 | K87: =+O87-P87 -> 0 | L87: 0 | M87: =+J87 -> 1000 | N87: 0 | O87: 0 | P87: 0 | Q87: =+M87+O87-P87 -> 1000 | R87: Mysmyle indirect
B88: SAL | C88: 30413119268092 | D88: AUBREY ANNE HONRADO ESCANO | E88: 105310101 | F88: AE480530000015690309002 | G88: 01-11-2024 | H88: 15-11-2024 | I88: 15 | J88: 3000 | K88: =N88+O88-P88 -> 0 | L88: 0 | M88: =+J88 -> 3000 | N88: 0 | O88: 0 | P88: 0 | Q88: =+M88+O88-P88 -> 3000 | R88: Mysmyle indirect
A99: Salary FMO October 2024 Paid in November
A100: NAME OF THE COMPANY: | C100: VISION DENTAL CLINIC | D100: MOL: 827857
A101: Record Type | B101: Employee Unique ID / 14 DIGITS | C101: Employee Name | D101: Agent ID/ BANK Routing Code | E101: Employee Card No. or IBAN | F101: Pay Start Date | G101: Pay End Date | H101: Days in Periods | I101: Fix Income | J101: Variable Income | K101: Days on Leave | L101: Basic Income | M101: OT | N101: Allowances | O101: Deductions | P101: Net Salary | Q101: Head | S101: Row Labels | T101: Sum of Net Salary
A102: SAL | B102: 30424099342516 | C102: Kimberly Ann Natuel | D102: 600310101 | E102: AE100030012150545910001 | F102: 01-10-2024 | G102: 31-10-2024 | H102: 31 | I102: 3000 | J102: =M102+N102-O102 -> 0 | K102: 0 | L102: =+I102 -> 3000 | M102: 0 | N102: 0 | O102: 0 | P102: =+L102+N102-O102 -> 3000 | Q102: indirect | S102: doctor | T102: 168558
A103: SAL | B103: 30401098916506 | C103: ZENETH SALADO ZAMORA | D103: 600310101 | E103: AE230030011461513910001 | F103: 01-10-2024 | G103: 31-10-2024 | H103: 31 | I103: 5000 | J103: =M103+N103-O103 -> 0 | K103: 0 | L103: =+I103 -> 5000 | M103: 0 | N103: 0 | O103: 0 | P103: =+L103+N103-O103 -> 5000 | Q103: indirect | S103: Final Settlement | T103: 4232
A104: SAL | B104: 30415118637898 | C104: RAZEL DE GUZMAN PEREZ | D104: 302620122 | E104: AE790260001015790005601 | F104: 01-10-2024 | G104: 31-10-2024 | H104: 31 | I104: 7500 | J104: =M104+N104-O104 -> 0 | K104: 0 | L104: =+I104 -> 7500 | M104: 0 | N104: 0 | O104: 0 | P104: =+L104+N104-O104 -> 7500 | Q104: nurse | S104: indirect | T104: 73087
A105: SAL | B105: 30413059492332 | C105: JOERILYN TURALLO JOVE | D105: 803510106 | E105: AE730351426004716443001 | F105: 01-10-2024 | G105: 31-10-2024 | H105: 31 | I105: 6000 | J105: =M105+N105-O105 -> 0 | K105: 0 | L105: =+I105 -> 6000 | M105: 0 | N105: 0 | O105: 0 | P105: =+L105+N105-O105 -> 6000 | Q105: nurse | S105: nurse | T105: 43337
A106: SAL | B106: 00125019640220 | C106: Ibrahim Abdelkarim | D106: AL HILAL | E106: AE440530000012021710001 | F106: 01-10-2024 | G106: 31-10-2024 | H106: 31 | I106: 6000 | J106: =M106+N106-O106 -> 0 | K106: 0 | L106: =+I106 -> 6000 | M106: 0 | N106: 0 | O106: 0 | P106: =+L106+N106-O106 -> 6000 | Q106: nurse | S106: Grand Total | T106: 289214
A107: SAL | B107: 00109067045968 | C107: HUSSEIN SALAH AHMED TAHOUN | D107: EMIRATES ISLAMIC BANK PJSC | E107: AE100340003708482640901 | F107: 01-10-2024 | G107: 31-10-2024 | H107: 31 | I107: 120000 | J107: =M107+N107-O107 -> 0 | K107: 0 | L107: 120000 | M107: 0 | N107: 0 | O107: 0 | P107: =+L107+N107-O107 -> 120000 | Q107: doctor
A108: SAL | B108: 00115028536953 | C108: HEBA HAMDY | D108: ADIB | E108: AE290500000000019267726 | F108: 01-10-2024 | G108: 31-10-2024 | H108: 31 | I108: 20000 | J108: =M108+N108-O108 -> 0 | K108: 0 | L108: =+I108 -> 20000 | M108: 0 | N108: 0 | O108: 0 | P108: =+L108+N108-O108 -> 20000 | Q108: indirect
A109: SAL | B109: 00105078982517 | C109: MOHAMED ABDEL MONIEM | D109: 600310101 | E109: AE230030013504627820001 | F109: 01-10-2024 | G109: 31-10-2024 | H109: 31 | I109: 3200 | J109: =M109+N109-O109 -> 4000 | K109: 0 | L109: =+I109 -> 3200 | M109: 0 | N109: =2400+1100+500 -> 4000 | O109: 0 | P109: =+L109+N109-O109 -> 7200 | Q109: indirect
A110: SAL | B110: 02126037202064 | C110: Muna Mohamed Ali | D110: 803510106 | E110: AE620351416003132013010 | F110: 01-10-2024 | G110: 31-10-2024 | H110: 31 | I110: 5000 | J110: =M110+N110-O110 -> -400 | K110: 0 | L110: =+I110 -> 5000 | M110: 0 | N110: 0 | O110: 400 | P110: =+L110+N110-O110 -> 4600 | Q110: indirect
A111: SAL | B111: 10026109684847 | C111: SOWMYA DHARMARAM | D111: 600310101 | E111: AE240030012691440910001 | F111: 01-10-2024 | G111: 26-10-2024 | H111: 26 | I111: 3774 | J111: =M111+N111-O111 -> -274 | K111: 0 | L111: =+I111 -> 3774 | M111: 0 | N111: 0 | O111: =3774-3500 -> 274 | P111: =+L111+N111-O111 -> 3500 | Q111: Final Settlement
A112: SAL | B112: 10028069336246 | C112: MARIYAM PULI MOOTIL | D112: ADCB | E112: AE790030013556902910001 | F112: 01-10-2024 | G112: 31-10-2024 | H112: 31 | I112: 4000 | J112: =M112+N112-O112 -> 650 | K112: 0 | L112: =+I112 -> 4000 | M112: 0 | N112: =400+250 -> 650 | O112: 0 | P112: =+L112+N112-O112 -> 4650 | Q112: indirect
A113: SAL | B113: 20014037665353 | C113: ASMA BUTT HAROON ZAFAR | D113: 802420101 | E113: AE430240010520243110901 | F113: 01-10-2024 | G113: 31-10-2024 | H113: 31 | I113: 18000 | J113: =M113+N113-O113 -> -750 | K113: 0 | L113: =+I113 -> 18000 | M113: 0 | N113: 150 | O113: 900 | P113: =+L113+N113-O113 -> 17250 | Q113: doctor
A114: SAL | B114: 00105078982517 | C114: MOHAMED ABDEL MONIEM | D114: 600310101 | E114: AE230030013504627820001 | F114: 01-10-2024 | G114: 31-10-2024 | H114: 31 | I114: 3200 | J114: =M114+N114-O114 -> 0 | K114: 0 | L114: =+I114 -> 3200 | M114: 0 | N114: 0 | O114: 0 | P114: =+L114+N114-O114 -> 3200 | Q114: indirect
A115: SAL | B115: 30423078946762 | C115: KAE SANDRA ILAGAN GONZALES | D115: 105310101 | E115: AE330530000012756802001 | F115: 01-10-2024 | G115: 31-10-2024 | H115: 31 | I115: 4000 | J115: =M115+N115-O115 -> 150 | K115: 0 | L115: =+I115 -> 4000 | M115: 0 | N115: 150 | O115: 0 | P115: =+L115+N115-O115 -> 4150 | Q115: indirect
A116: SAL | B116: 30411119077489 | C116: CHERIE ANN RUANO | D116: 600310101 | E116: AE910030011944495920001 | F116: 01-10-2024 | G116: 31-10-2024 | H116: 31 | I116: 6000 | J116: =M116+N116-O116 -> -500 | K116: 0 | L116: =+I116 -> 6000 | M116: 0 | N116: 100 | O116: 600 | P116: =+L116+N116-O116 -> 5500 | Q116: indirect
A117: SAL | B117: 10010089305600 | C117: ANNIE JOHN JOHN JOSEPH | D117: 302620122 | E117: AE850260001015782862801 | F117: 01-10-2024 | G117: 31-10-2024 | H117: 31 | I117: 6000 | J117: =M117+N117-O117 -> -150 | K117: 0 | L117: =+I117 -> 6000 | M117: 0 | N117: 100 | O117: 250 | P117: =+L117+N117-O117 -> 5850 | Q117: nurse
A118: SAL | B118: 10008019402648 | C118: Faisal Farooqui | D118: 203320101 | E118: AE130330000019101365827 | F118: 01-10-2024 | G118: 31-10-2024 | H118: 31 | I118: 7000 | J118: =M118+N118-O118 -> -113 | K118: 0 | L118: =+I118 -> 7000 | M118: 0 | N118: 0 | O118: 113 | P118: =+L118+N118-O118 -> 6887 | Q118: nurse
A119: SAL | B119: 10016078859321 | C119: Manju Devadasan | D119: 600310101 | E119: AE230030011943926920001 | F119: 01-10-2024 | G119: 31-10-2024 | H119: 31 | I119: 7500 | J119: =M119+N119-O119 -> 0 | K119: 0 | L119: =+I119 -> 7500 | M119: 0 | N119: 0 | O119: 0 | P119: =+L119+N119-O119 -> 7500 | Q119: nurse
A120: SAL | B120: 00404029649957 | C120: MHD ABDULMOHSEN AMEREDDIN ALNABLSI | D120: 405010101 | E120: AE070500000000028637449 | F120: 01-10-2024 | G120: 31-10-2024 | H120: 31 | I120: 7000 | J120: =M120+N120-O120 -> -3790 | K120: 0 | L120: =+I120 -> 7000 | M120: 0 | N120: 0 | O120: =3015+875-100 -> 3790 | P120: =+L120+N120-O120 -> 3210 | Q120: indirect
A121: SAL | B121: 01023039157178 | C121: SALIM ALI HAMADANI | D121: 804020101 | E121: AE550400008042796185901 | F121: 01-10-2024 | G121: 31-10-2024 | H121: 31 | I121: 17000 | J121: =M121+N121-O121 -> -1692 | K121: 0 | L121: =+I121 -> 17000 | M121: 0 | N121: 150 | O121: 1842 | P121: =+L121+N121-O121 -> 15308 | Q121: doctor
A122: SAL | B122: 30402099983205 | C122: MARIFE SAMSON SOCAO | D122: 600310101 | E122: AE940030012873333910001 | F122: 01-10-2024 | G122: 31-10-2024 | H122: 31 | I122: 3500 | J122: =M122+N122-O122 -> -650 | K122: 0 | L122: =+I122 -> 3500 | M122: 0 | N122: 350 | O122: 1000 | P122: =+L122+N122-O122 -> 2850 | Q122: indirect
...

Sheet Bank Recon
G1: Total Search Results: 945
A2: Value Date | B2: Narrative | C2: Transaction Reference | D2: Debit | E2: Credit | F2: Running Balance
A3: 31-01-2025 | B3: T435955143:-ADCB MCR ADNIC CLAIMS ACCOUNT PO BOX 839 TO REF1202776 MEDICAL EF | C3: 404C250131B1B731 | D3: 0 | E3: 1038.8 | F3: 8317.02
A4: 31-01-2025 | B4: 0162501310931183 Merchant Payment 1002038 | C4: 0162501310931183 | D4: 0 | E4: 3913.19 | F4: 7278.22 | G4: =+H4-78473.25 -> -1578.03 | H4: =+E4+E13+E25+E41+E43+E54+E56+E66+E74+E80 -> 76895.22
A5: 30-01-2025 | B5: VAT on Charges Amount | C5: 5453001254812440 | D5: 0.75 | E5: 0 | F5: 3365.03
A6: 30-01-2025 | B6: IB-DFT-5453001254812440 Ref-PV City Pharmacy Co Wll - Charges | C6: 5453001254812440 | D6: 15 | E6: 0 | F6: 3365.78
A7: 30-01-2025 | B7: IB-DFT-5453001254812440 Ref-PV City Pharmacy Co Wll | C7: 5453001254812440 | D7: 4794.5 | E7: 0 | F7: 3380.78
A8: 30-01-2025 | B8: VAT on Charges Amount | C8: 5453001254642069 | D8: 0.75 | E8: 0 | F8: 8175.28
A9: 30-01-2025 | B9: IB-DFT-5453001254642069 Ref-PV THREE Q DENTAL - Charges | C9: 5453001254642069 | D9: 15 | E9: 0 | F9: 8176.03
A10: 30-01-2025 | B10: IB-DFT-5453001254642069 Ref-PV THREE Q DENTAL | C10: 5453001254642069 | D10: 2000 | E10: 0 | F10: 8191.03
A11: 30-01-2025 | B11: IB-INTT-5452901254432288 Ref-PV Transfer within bank AE370500000000028174704 | C11: 5452901254432288 | D11: 1500 | E11: 0 | F11: 10191.03
A12: 30-01-2025 | B12: Inward posting of cheque : 500416 | C12: 549IS250130002812 | D12: 5834.5 | E12: 0 | F12: 11691.03
A13: 30-01-2025 | B13: 0162501300916391 Merchant Payment 1002038 | C13: 0162501300916391 | D13: 0 | E13: 4711.38 | F13: 17525.53
A14: 29-01-2025 | B14: VAT on Charges Amount | C14: 5452801254015587 | D14: 0.75 | E14: 0 | F14: 12814.15
A15: 29-01-2025 | B15: IB-DFT-5452801254015587 Ref-PV AstraCare Medical Supplies Trading - Charges | C15: 5452801254015587 | D15: 15 | E15: 0 | F15: 12814.9
A16: 29-01-2025 | B16: IB-DFT-5452801254015587 Ref-PV AstraCare Medical Supplies Trading | C16: 5452801254015587 | D16: 840 | E16: 0 | F16: 12829.9
... A21: 29-01-2025 | B21: IB-DFT-5452901254400742 Ref-PV HANAN ALI ABDULLA MOH ALHINDI - Charges | C21: 5452901254400742 | D21: 15 | E21: 0 | F21: 15186.4
A22: 29-01-2025 | B22: IB-DFT-5452901254400742 Ref-PV HANAN ALI ABDULLA MOH ALHINDI | C22: 5452901254400742 | D22: 4944 | E22: 0 | F22: 15201.4 | G22: =+D22-4869.94 -> 74.06
A23: 29-01-2025 | B23: T434766404:-ADCB MCR NATIONAL HEALTH INS CO.-DAMAN PJSC REFENH--27012025-78506 | C23: 404C250129AC5FC3 | D23: 0 | E23: 240 | F23: 20145.4
A24: 29-01-2025 | B24: T434767010:-ADCB MCR NATIONAL HEALTH INS CO.-DAMAN PJSC REFENH--28012025-78549 | C24: 404C250129AC5ACA | D24: 0 | E24: 408 | F24: 19905.4
A25: 29-01-2025 | B25: 0162501290901422 Merchant Payment 1002038 | C25: 0162501290901422 | D25: 0 | E25: 6948.96 | F25: 19497.4
A26: 28-01-2025 | B26: IB-INTT-5452801253951219 Ref-PV Transfer within bank AE370500000000028174704 | C26: 5452801253951219 | D26: 2000 | E26: 0 | F26: 12548.44
A27: 28-01-2025 | B27: VAT on Charges Amount | C27: 5452801253771069 | D27: 0.75 | E27: 0 | F27: 14548.44
A28: 28-01-2025 | B28: IB-DFT-5452801253771069 Ref-PV CALIBRATE PRO MANAGEMENT - Charges | C28: 5452801253771069 | D28: 15 | E28: 0 | F28: 14549.19
A29: 28-01-2025 | B29: IB-DFT-5452801253771069 Ref-PV CALIBRATE PRO MANAGEMENT | C29: 5452801253771069 | D29: 4532.85 | E29: 0 | F29: 14564.19
A30: 28-01-2025 | B30: VAT on Charges Amount | C30: 5452801253783917 | D30: 0.75 | E30: 0 | F30: 19097.04
A31: 28-01-2025 | B31: IB-DFT-5452801253783917 Ref-PV Bio Link Medical Surgical Equipment - Charges | C31: 5452801253783917 | D31: 15 | E31: 0 | F31: 19097.79
A32: 28-01-2025 | B32: IB-DFT-5452801253783917 Ref-PV Bio Link Medical Surgical Equipment | C32: 5452801253783917 | D32: 2420 | E32: 0 | F32: 19112.79
A33: 28-01-2025 | B33: IB-INTT-5452801253781726 Ref-PV Transfer within bank AE850500000000028623338 | C33: 5452801253781726 | D33: 5000 | E33: 0 | F33: 21532.79
A34: 28-01-2025 | B34: VAT on Charges Amount | C34: 5452801253777235 | D34: 0.75 | E34: 0 | F34: 26532.79
... A74: 22-01-2025 | B74: 0162501220806033 Merchant Payment 1002038 | C74: 0162501220806033 | D74: 0 | E74: 3082.18 | F74: 27390.89
A75: 22-01-2025 | B75: IB-INTT-5452201251847705 Ref-PV 6188 Transfer within bank AE67050000000001041792 | C75: 5452201251847705 | D75: 5013.65 | E75: 0 | F75: 24308.71 | G75: =+D75-5000 -> 13.65
A76: 22-01-2025 | B76: T431374857:-ADCB MCR NATIONAL HEALTH INS CO.-DAMAN PJSC REFTPA--17012025-78318 | C76: 404G2501228E5C5F | D76: 0 | E76: 15865.5 | F76: 29322.36
A77: 22-01-2025 | B77: T431375540:-ADCB MCR NATIONAL HEALTH INS CO.-DAMAN PJSC REFENH--20012025-78335 | C77: 404C2501228E5ABD | D77: 0 | E77: 815.4 | F77: 13456.86
A78: 21-01-2025 | B78: IB-INTT-5452101251695670 Ref-PV 6187 Transfer within bank AE37050000000002817470 | C78: 5452101251695670 | D78: 2000 | E78: 0 | F78: 12641.46
A79: 21-01-2025 | B79: IB-INTT-5452101251619512 Ref-PV 6186 Transfer within bank AE67050000000001041792 | C79: 5452101251619512 | D79: 3025.45 | E79: 0 | F79: 14641.46
A80: 21-01-2025 | B80: 0162501210792762 Merchant Payment 1002038 | C80: 0162501210792762 | D80: 0 | E80: 2530.76 | F80: 17666.91
A81: 20-01-2025 | B81: Payment - Installment CFF 70087892 | C81: - - | D81: 31335.21 | E81: 0 | F81: 15136.15
A82: 20-01-2025 | B82: VAT on Charges Amount | C82: 5452001251241718 | D82: 0.75 | E82: 0 | F82: 46471.36
A83: 20-01-2025 | B83: IB-DFT-5452001251241718 Ref-PV 6185 ADVANCED INNOVATION MANAGEMENT - Charges | C83: 5452001251241718 | D83: 15 | E83: 0 | F83: 46472.11
A84: 20-01-2025 | B84: IB-DFT-5452001251241718 Ref-PV 6185 ADVANCED INNOVATION MANAGEMENT | C84: 5452001251241718 | D84: 4200 | E84: 0 | F84: 46487.11
A85: 20-01-2025 | B85: IB-INTT-5451901259766846 Ref-PV Transfer within bank 28602022 | C85: 5451901259766846 | D85: 1635 | E85: 0 | F85: 50687.11
A86: 20-01-2025 | B86: IB-INTT-5451801259656484 Ref-PV Transfer within bank AE370500000000028174704 | C86: 5451801259656484 | D86: 3000 | E86: 0 | F86: 52322.11
A87: 20-01-2025 | B87: VAT on Charges Amount | C87: 5451801259545795 | D87: 0.75 | E87: 0 | F87: 55322.11
... A92: 20-01-2025 | B92: IB-DFT-5452001259985887 Ref-PV 6184 MHMOD ASAAD BADRAN | C92: 5452001259985887 | D92: 1500 | E92: 0 | F92: 55923.61
A93: 20-01-2025 | B93: IB-INTT-5452001251229494 Ref-PV 6178 Transfer within bank AE67050000000001041792 | C93: 5452001251229494 | D93: 7013 | E93: 0 | F93: 57423.61 | G93: =+D93-7000 -> 13
A94: 20-01-2025 | B94: 430799852:- TTS MICHAEL WILLIAM BABULA | C94: 603a850dca67be0401 | D94: 0 | E94: 315 | F94: 64436.61
A95: 20-01-2025 | B95: 0162501200777802 Merchant Payment 1002038 | C95: 0162501200777802 | D95: 0 | E95: 6801.45 | F95: 64121.61 | G95: =+H95-51960.91 -> -1040.93 | H95: =+E95+E97+E101+E124+E126+E139+E150+E151 -> 50919.98
A96: 20-01-2025 | B96: CCDM 3508 Deposit 19012025 21:14 | C96: 611011921270134#1 | D96: 0 | E96: 11000 | F96: 57320.16
A97: 20-01-2025 | B97: 0162501190763167 Merchant Payment 1002038 | C97: 0162501190763167 | D97: 0 | E97: 15078.42 | F97: 46320.16
A98: 20-01-2025 | B98: CCDM 3509 Deposit 19012025 11:19 | C98: 611011911317747#1 | D98: 0 | E98: 500 | F98: 31241.74
A99: 20-01-2025 | B99: CCDM 3509 Deposit 19012025 11:17 | C99: 611011911315725#1 | D99: 0 | E99: 25000 | F99: 30741.74
A100: 17-01-2025 | B100: T429881095:-ADCB MCR NATIONAL HEALTH INS CO.-DAMAN PJSC REFENH--15012025-78235 | C100: 404C25011788A237 | D100: 0 | E100: 204 | F100: 5741.74
A101: 17-01-2025 | B101: 0162501170738038 Merchant Payment 1002038 | C101: 0162501170738038 | D101: 0 | E101: 3476.81 | F101: 5537.74
A102: 17-01-2025 | B102: T429826886:-ADCB MCR ADNIC CLAIMS ACCOUNT PO BOX 839 TO REF1193511 MEDICAL EF | C102: 404G250117883B96 | D102: 0 | E102: 1411.9 | F102: 2060.93
A103: 17-01-2025 | B103: VAT on Charges Amount | C103: 5451601259050468 | D103: 0.75 | E103: 0 | F103: 649.03
A104: 17-01-2025 | B104: IB-DFT-5451601259050468 Ref-PV HADI KHALEL - Charges | C104: 5451601259050468 | D104: 15 | E104: 0 | F104: 649.78
A105: 17-01-2025 | B105: IB-DFT-5451601259050468 Ref-PV HADI KHALEL | C105: 5451601259050468 | D105: 1355 | E105: 0 | F105: 664.78
A106: 17-01-2025 | B106: VAT on Charges Amount | C106: 5451601259105249 | D106: 0.75 | E106: 0 | F106: 2019.78
A107: 17-01-2025 | B107: IB-DFT-5451601259105249 Ref-PV MPHASIS INFORMATION - Charges | C107: 5451601259105249 | D107: 15 | E107: 0 | F107: 2020.53
... A153: 10-01-2025 | B153: Inward posting of cheque : 500415 | C153: 549IS250110004167 | D153: 5500 | E153: 0 | F153: 7882.03
A154: 10-01-2025 | B154: 0162501100643186 Merchant Payment 1002038 | C154: 0162501100643186 | D154: 0 | E154: 2124.44 | F154: 13382.03 | G154: =+H154-68202.78 -> -1184.8 | H154: =+E154+E158+E177+E181+E191+E192+E193+E195+E197 -> 67017.98
A155: 09-01-2025 | B155: IB-INTT-5450901256914982 Ref-PV Transfer within bank AE670500000000010417926 | C155: 5450901256914982 | D155: 41189.55 | E155: 0 | F155: 11257.59 | G155: =+D155-41156 -> 33.55
A156: 09-01-2025 | B156: IB-INTT-5450901256793558 Ref-PV 6040 Transfer within bank AE37050000000002817470 | C156: 5450901256793558 | D156: 20000 | E156: 0 | F156: 52447.14
A157: 09-01-2025 | B157: 169499987:- GDI HUSSIEN SALAH AHMED TAHOUN | C157: 60303e1098fbd384c5 | D157: 0 | E157: 30000 | F157: 72447.14
A158: 09-01-2025 | B158: 0162501090628230 Merchant Payment 1002038 | C158: 0162501090628230 | D158: 0 | E158: 3001.34 | F158: 42447.14
A159: 09-01-2025 | B159: T426726739:-ADCB MCR NATIONAL HEALTH INS CO.-DAMAN PJSC REFTPA--08012025-78062 | C159: 404G2501097D23F1 | D159: 0 | E159: 4980.5 | F159: 39445.8
A160: 08-01-2025 | B160: IB-UBP- ETISALAT - 0551366843 | C160: 5450801256435600 | D160: 780.76 | E160: 0 | F160: 34465.3
A161: 08-01-2025 | B161: IB-UBP- ETISALAT - 025571885 | C161: 5450801256433890 | D161: 1569.75 | E161: 0 | F161: 35246.06
A162: 08-01-2025 | B162: IB-UBP- ETISALAT - 026224700 | C162: 5450801256433041 | D162: 115.5 | E162: 0 | F162: 36815.81
A163: 08-01-2025 | B163: IB-UBP- ETISALAT - 023122777 | C163: 5450801256432832 | D163: 1500.26 | E163: 0 | F163: 36931.31
A164: 08-01-2025 | B164: IB-UBP- ETISALAT - 025529567 | C164: 5450801256432531 | D164: 1548.75 | E164: 0 | F164: 38431.57
A165: 08-01-2025 | B165: IB-UBP- ETISALAT - 1222276837 | C165: 5450801256431935 | D165: 367.5 | E165: 0 | F165: 39980.32
A166: 08-01-2025 | B166: IB-UBP- ETISALAT - 026313110 | C166: 5450801256431450 | D166: 99.75 | E166: 0 | F166: 40347.82
A167: 08-01-2025 | B167: IB-UBP- ETISALAT - 0525749749 | C167: 5450801256436208 | D167: 838.1 | E167: 0 | F167: 40447.57
... A197: 01-01-2025 | B197: 0162501010517650 Merchant Payment 1002038 | C197: 0162501010517650 | D197: 0 | E197: 9037.49 | F197: 348.57
A202: Value Date | B202: Narrative | C202: Transaction Reference | D202: Debit | E202: Credit | F202: Running Balance
A203: 31-01-2025 | B203: 0162501310931183 Merchant Payment 1002038 | C203: 0162501310931183 | D203: 0 | E203: 3913.19 | F203: 7278.22
A204: 30-01-2025 | B204: 0162501300916391 Merchant Payment 1002038 | C204: 0162501300916391 | D204: 0 | E204: 4711.38 | F204: 17525.53
A205: 29-01-2025 | B205: 0162501290901422 Merchant Payment 1002038 | C205: 0162501290901422 | D205: 0 | E205: 6948.96 | F205: 19497.4
A206: 28-01-2025 | B206: 0162501280888223 Merchant Payment 1002038 | C206: 0162501280888223 | D206: 0 | E206: 4362.54 | F206: 30271.79
A207: 27-01-2025 | B207: 0162501270875176 Merchant Payment 1002038 | C207: 0162501270875176 | D207: 0 | E207: 3327.86 | F207: 30909.25
A208: 27-01-2025 | B208: 0162501260858669 Merchant Payment 1002038 | C208: 0162501260858669 | D208: 0 | E208: 19740.23 | F208: 36487.84
A209: 24-01-2025 | B209: 0162501240833413 Merchant Payment 1002038 | C209: 0162501240833413 | D209: 0 | E209: 3603.1 | F209: 16699.61
A210: 23-01-2025 | B210: 0162501230817368 Merchant Payment 1002038 | C210: 0162501230817368 | D210: 0 | E210: 24675.02 | F210: 43092.01
A211: 22-01-2025 | B211: 0162501220806033 Merchant Payment 1002038 | C211: 0162501220806033 | D211: 0 | E211: 3082.18 | F211: 27390.89
A212: 21-01-2025 | B212: 0162501210792762 Merchant Payment 1002038 | C212: 0162501210792762 | D212: 0 | E212: 2530.76 | F212: 17666.91
A213: 20-01-2025 | B213: 0162501200777802 Merchant Payment 1002038 | C213: 0162501200777802 | D213: 0 | E213: 6801.45 | F213: 64121.61
A214: 20-01-2025 | B214: 0162501190763167 Merchant Payment 1002038 | C214: 0162501190763167 | D214: 0 | E214: 15078.42 | F214: 46320.16
... A229: 01-01-2025 | B229: 0162501010517650 Merchant Payment 1002038 | C229: 0162501010517650 | D229: 0 | E229: 9037.49 | F229: 348.57
D231: Total | E231: =SUBTOTAL(9,E203:E230) -> 194833.18
D232: Charges | E232: 4103.76
D233: Grand Total | E233: =+E231+E232 -> 198936.94

Sheet Salary
A1: January paid in Feb
A2: Name Of Employee | B2: Net Salary | C2: Head | E2: Row Labels | F2: Sum of Net Salary
A3: Mohammed Hassan Labib | B3: 5000 | C3: indirect | E3: external | F3: 8000
A4: Mona Linda Econg | B4: 2744.9597 | C4: indirect | E4: indirect | F4: 117272.56
A5: Aubrey Anne Honrado Escano | B5: 5422.7823 | C5: indirect | E5: Mysmyle indirect | F5: 8907.2581
A6: Shabna Jamal | B6: 4500 | C6: indirect | E6: nurse | F6: 34140.323
A7: Jennifer Iglesia | B7: 5500 | C7: nurse | E7: Doctor | F7: 174061.73
A8: Omar Alzarkan | B8: 8000 | C8: indirect | E8: Grand Total | F8: 342381.87
A9: Myrna Villegas | B9: 2850 | C9: indirect
A10: Helen Dacayo | B10: 3443.5484 | C10: indirect
A11: Marife Samson | B11: 3341.2298 | C11: indirect
A12: Aasiya Siddiqa | B12: 3500 | C12: indirect
A13: Moby Antony | B13: 3000 | C13: Mysmyle indirect
A14: Dieryl Mayor | B14: 5907.2581 | C14: Mysmyle indirect
A15: Genet Tumago | B15: 1000 | C15: indirect
A16: Elbie Cristobal | B16: 2250 | C16: nurse
A17: Hadi Haj | B17: 4838.7097 | C17: indirect
A18: Mahmod Badran | B18: 2419.3548 | C18: indirect
A19: Dr. Hussien Tahoun | B19: 120000 | C19: Doctor
A20: Heba Hamdy | B20: 20000 | C20: indirect
... A45: Dr. Amr Labib | B45: 0 | C45: Doctor
A49: Salary FMO December 2024 Paid in January
A50: Record Type | B50: Employee Unique ID / 14 DIGITS | C50: Employee Name | D50: Agent ID/ BANK Routing Code | E50: Employee Card No. or IBAN | F50: Pay Start Date | G50: Pay End Date | H50: Days in Periods | I50: Fix Income | J50: Variable Income | K50: Days on Leave | L50: Basic Income | M50: OT | N50: Allowances | O50: Deductions | P50: Net Salary | Q50: Head | S50: Row Labels | T50: Sum of Net Salary
A51: SAL | B51: 30411119077489 | C51: CHERIE ANN RUANO | D51: Mashreq Bank PSC | E51: AE730330000019101566507 | F51: 01-12-2024 | G51: 31-121-2024 | H51: 25 | I51: 6000 | J51: =+M51+N51-O51 -> -1000 | K51: 0 | L51: =+I51 -> 6000 | M51: 0 | N51: 0 | O51: 1000 | P51: =+L51+N51-O51 -> 5000 | Q51: indirect | S51: Doctors Salary | T51: 157808
A52: SAL | B52: 10016078859321 | C52: Manju Devadasan | D52: 600310101 | E52: AE230030011943926920001 | F52: 01-12-2024 | G52: 31-12-2024 | H52: 5 | I52: 7500 | J52: =M52+N52-O52 -> -6000 | K52: 0 | L52: =+I52 -> 7500 | M52: 0 | N52: 0 | O52: 6000 | P52: =+L52+N52-O52 -> 1500 | Q52: Final Settlemt Direct nurse | S52: External | T52: 10830
A53: Final Settlement | B53: 30420059362009 | C53: Ramil Padilla | D53: DIB | E53: AE770240007520145057601 | F53: 01-12-2024 | G53: 31-12-2024 | H53: 4 | I53: 4000 | J53: =M53+N53-O53 -> -3413 | K53: 0 | L53: 4000 | M53: 0 | N53: 0 | O53: =4000-587 -> 3413 | P53: =+L53+N53-O53 -> 587 | Q53: Final Settlemt Direct nurse | S53: Final Settlemt Direct nurse | T53: 4087
A54: Final Settlement | B54: 10016078859321 | C54: Manju Devadasan | D54: 600310101 | E54: AE230030011943926920001 | F54: 01-12-2024 | G54: 31-12-2024 | H54: 8 | I54: 7500 | J54: =M54+N54-O54 -> -5500 | K54: 0 | L54: =+I54 -> 7500 | M54: 0 | N54: 0 | O54: 5500 | P54: =+L54+N54-O54 -> 2000 | Q54: Final Settlemt Direct nurse | S54: indirect | T54: 58805
A55: SAL | B55: 00105078982517 | C55: MOHAMED ABDEL MONIEM | D55: 600310101 | E55: AE230030013504627820001 | F55: 01-12-2024 | G55: 31-12-2024 | H55: 31 | I55: 3200 | J55: =M55+N55-O55 -> 5800 | K55: 0 | L55: =+I55 -> 3200 | M55: 0 | N55: =2500+1100+2500+1500+1400-3200 -> 5800 | O55: 0 | P55: =+L55+N55-O55 -> 9000 | Q55: External | S55: Nurse Direct | T55: 31400
A56: SAL | B56: 00109067045968 | C56: HUSSEIN SALAH AHMED TAHOUN | D56: EMIRATES ISLAMIC BANK PJSC | E56: AE100340003708482640901 | F56: 01-12-2024 | G56: 31-12-2024 | H56: 31 | I56: 120000 | J56: =M56+N56-O56 -> 0 | K56: 0 | L56: 120000 | M56: 0 | N56: 0 | O56: 0 | P56: =+L56+N56-O56 -> 120000 | Q56: Doctors Salary | S56: Grand Total | T56: 262930
A57: SAL | B57: 00115028536953 | C57: HEBA HAMDY | D57: ADIB | E57: AE290500000000019267726 | F57: 01-12-2024 | G57: 31-12-2024 | H57: 31 | I57: 20000 | J57: =M57+N57-O57 -> 0 | K57: 0 | L57: =+I57 -> 20000 | M57: 0 | N57: 0 | O57: 0 | P57: =+L57+N57-O57 -> 20000 | Q57: indirect
A58: SAL | B58: 30424099342516 | C58: Kimberly Ann Natuel | D58: 600310101 | E58: AE100030012150545910001 | F58: 01-12-2024 | G58: 31-12-2024 | H58: 31 | I58: 3000 | J58: =+M58+N58-O58 -> 0 | K58: 0 | L58: 3000 | M58: 0 | N58: 0 | O58: 0 | P58: =+N58+I58-O58 -> 3000 | Q58: indirect | S58: Row Labels | T58: Sum of Net Salary
A59: SAL | B59: 30415118637898 | C59: RAZEL DE GUZMAN PEREZ | D59: 302620122 | E59: AE790260001015790005601 | F59: 01-12-2024 | G59: 31-12-2024 | H59: 31 | I59: 7500 | J59: =+M59+N59-O59 -> 0 | K59: 0 | L59: 7500 | M59: 0 | N59: 0 | O59: 0 | P59: =+N59+I59-O59 -> 7500 | Q59: Nurse Direct | S59: Final Settlement Indirect | T59: 3292
A60: SAL | B60: 30413059492332 | C60: JOERILYN TURALLO JOVE | D60: 803510106 | E60: AE730351426004716443001 | F60: 01-12-2024 | G60: 31-12-2024 | H60: 31 | I60: 6000 | J60: =+M60+N60-O60 -> 0 | K60: 0 | L60: 6000 | M60: 0 | N60: 0 | O60: 0 | P60: =+N60+I60-O60 -> 6000 | Q60: Nurse Direct | S60: indirect | T60: 51928
A61: SAL | B61: 10028069336246 | C61: MARIYAM PULI MOOTIL | D61: ADCB | E61: AE790030013556902910001 | F61: 01-12-2024 | G61: 31-12-2024 | H61: 31 | I61: 4000 | J61: =+M61+N61-O61 -> 400 | K61: 0 | L61: =+I61 -> 4000 | M61: 0 | N61: 400 | O61: 0 | P61: =+L61+N61-O61 -> 4400 | Q61: indirect | S61: Nurse Direct | T61: 7750
A62: SAL | B62: 00404029649957 | C62: MHD ABDULMOHSEN AMEREDDIN ALNABLSI | D62: 405010101 | E62: AE070500000000028637449 | F62: 01-12-2024 | G62: 31-12-2024 | H62: 28 | I62: 7000 | J62: =+M62+N62-O62 -> -500 | K62: 0 | L62: =+I62 -> 7000 | M62: 0 | N62: 0 | O62: 500 | P62: =+L62+N62-O62 -> 6500 | Q62: indirect | S62: Grand Total | T62: 62970
A63: SAL | B63: 10010089305600 | C63: ANNIE JOHN JOHN JOSEPH | D63: 302620122 | E63: AE850260001015782862801 | F63: 01-12-2024 | G63: 31-12-2024 | H63: 29 | I63: 6000 | J63: =+M63+N63-O63 -> -100 | K63: 0 | L63: =+I63 -> 6000 | M63: 0 | N63: 2400 | O63: 2500 | P63: =+L63+N63-O63 -> 5900 | Q63: Nurse Direct
A64: SAL | B64: 01023039157178 | C64: SALIM ALI HAMADANI | D64: 804020101 | E64: AE550400008042796185901 | F64: 01-12-2024 | G64: 31-12-2024 | H64: 29 | I64: 17000 | J64: =+M64+N64-O64 -> -992 | K64: 0 | L64: =+I64 -> 17000 | M64: 0 | N64: 0 | O64: 992 | P64: =+L64+N64-O64 -> 16008 | Q64: Doctors Salary
A65: SAL | B65: 30401098916506 | C65: ZENETH SALADO ZAMORA | D65: 600310101 | E65: AE230030011461513910001 | F65: 01-12-2024 | G65: 31-121-2024 | H65: 31 | I65: 5000 | J65: =+M65+N65-O65 -> 0 | K65: 0 | L65: 5000 | M65: 0 | N65: 0 | O65: 0 | P65: =+N65+I65-O65 -> 5000 | Q65: indirect
A66: SAL | B66: 00125019640220 | C66: Ibrahim Abdelkarim | D66: AL HILAL | E66: AE440530000012021710001 | F66: 01-12-2024 | G66: 31-121-2024 | H66: 31 | I66: 6000 | J66: =+M66+N66-O66 -> -1000 | K66: 0 | L66: 6000 | M66: 0 | N66: 0 | O66: 1000 | P66: =+N66+I66-O66 -> 5000 | Q66: Nurse Direct
A67: SAL | B67: 20014037665353 | C67: ASMA BUTT HAROON ZAFAR | D67: 802420101 | E67: AE430240010520243110901 | F67: 01-12-2024 | G67: 31-121-2024 | H67: 31 | I67: 18000 | J67: =+M67+N67-O67 -> 0 | K67: 0 | L67: =+I67 -> 18000 | M67: 0 | N67: 0 | O67: 0 | P67: =+L67+N67-O67 -> 18000 | Q67: Doctors Salary
A68: SAL | B68: 00105078982517 | C68: MOHAMED ABDEL MONIEM | D68: 600310101 | E68: AE230030013504627820001 | F68: 01-12-2024 | G68: 31-121-2024 | H68: 26 | I68: 3200 | J68: =+M68+N68-O68 -> -425 | K68: 0 | L68: 3200 | M68: 0 | N68: 162 | O68: 587 | P68: =+L68+N68-O68 -> 2775 | Q68: indirect
A69: SAL | B69: 30423078946762 | C69: KAE SANDRA ILAGAN GONZALES | D69: 105310101 | E69: AE330530000012756802001 | F69: 01-12-2024 | G69: 31-121-2024 | H69: 31 | I69: 4000 | J69: =+M69+N69-O69 -> 200 | K69: 0 | L69: =+I69 -> 4000 | M69: 0 | N69: 200 | O69: 0 | P69: =+L69+N69-O69 -> 4200 | Q69: indirect
A70: SAL | B70: 30402099983205 | C70: MARIFE SAMSON SOCAO | D70: 600310101 | E70: AE940030012873333910001 | F70: 01-12-2024 | G70: 31-121-2024 | H70: =31-7 -> 24 | I70: 3850 | J70: =+M70+N70-O70 -> -870 | K70: 0 | L70: =+I70 -> 3850 | M70: 0 | N70: 205 | O70: 1075 | P70: =+L70+N70-O70 -> 2980 | Q70: indirect
A71: SAL | B71: 30421029504901 | C71: JOEL MULA ABORITA | D71: 600310101 | E71: AE810030011938003910001 | F71: 01-12-2024 | G71: 31-121-2024 | H71: 31 | I71: 3000 | J71: =+M71+N71-O71 -> 200 | K71: 0 | L71: =+I71 -> 3000 | M71: 0 | N71: 200 | O71: 0 | P71: =+L71+N71-O71 -> 3200 | Q71: indirect
A72: SAL | C72: Dr/ Ibrahim | F72: 01-12-2024 | G72: 31-121-2024 | P72: =1500+2300 -> 3800 | Q72: Doctors Salary
A73: SAL | C73: Ahmed thanweer | F73: 01-12-2024 | G73: 31-121-2024 | P73: 1750 | Q73: indirect
A74: SAL | C74: Faisal Farooqui | F74: 01-11-2024 | G74: 30-11-2024 | P74: 7000 | Q74: Nurse Direct
A75: SAL | C75: Sajed Tahoun | F75: 01-12-2024 | G75: 31-121-2024 | H75: 31 | P75: 1830 | Q75: External
C76: MYSMYLE COMPANY FOR INFORMATION TECHNOLOGY | D76: MOL: 1519899
A77: Record Type | B77: Employee Unique ID / 14 DIGITS | C77: Employee Name | D77: Agent ID/ BANK Routing Code | E77: Employee Card No. or IBAN | F77: Pay Start Date | G77: Pay End Date | H77: Days in Periods | I77: Fix Income | J77: Variable Income | K77: Days on Leave | L77: Basic Income | M77: OT | N77: Allowances | O77: Deductions | P77: Net Salary | Q77: Head
A78: SAL | B78: 00531078232478 | C78: RAMI MOHAMAD ELMAHMOUD | D78: 803510106 | E78: AE640351416005651558001 | F78: 01-12-2024 | G78: 31-12-2024 | H78: 19 | I78: 5000 | J78: =M78+N78-O78 -> -1708 | K78: 0 | L78: =+I78 -> 5000 | M78: 0 | N78: 0 | O78: 1708 | P78: =+L78+N78-O78 -> 3292 | Q78: Final Settlement Indirect
A79: SAL | B79: 40315039258931 | C79: Genet Tesfaye Tumego | D79: ADCB | E79: AE110030013314321820001 | F79: 01-12-2024 | G79: 31-12-2024 | H79: 31 | I79: 1000 | J79: =+N79-O79 -> 0 | K79: 0 | L79: =+I79 -> 1000 | M79: 0 | N79: 0 | O79: 0 | P79: =+L79+N79-O79 -> 1000 | Q79: indirect
A80: SAL | B80: 30413097846043 | C80: MYRNA LANDICHO VILLEGAS | D80: 600310101 | E80: AE250030012535431910001 | F80: 01-12-2024 | G80: 31-12-2024 | H80: 31 | I80: 2700 | J80: =+M80+N80-O80 -> 150 | K80: 0 | L80: =+I80 -> 2700 | M80: 0 | N80: 150 | O80: 0 | P80: =+L80+N80-O80 -> 2850 | Q80: indirect
A81: SAL | B81: 00104028910818 | C81: MOHAMED MOHAMED MOHAMED | D81: 203320101 | E81: AE320330000019100237569 | F81: 01-12-2024 | G81: 31-12-2024 | H81: 30 | I81: 5500 | J81: =+N81-O81 -> -177 | K81: 0 | L81: =+I81 -> 5500 | M81: 0 | N81: 0 | O81: 177 | P81: =+L81+N81-O81 -> 5323 | Q81: indirect
A82: SAL | B82: 30413119268092 | C82: AUBREY ANNE HONRADO ESCANO | D82: AL HILAL DIGITAL | E82: AE750530000015690309001 | F82: 01-12-2024 | G82: 31-12-2024 | H82: 29 | I82: 6000 | J82: =+N82-O82 -> -200 | K82: 0 | L82: =+I82 -> 6000 | M82: 0 | N82: 0 | O82: 200 | P82: =+L82+N82-O82 -> 5800 | Q82: indirect
A83: SAL | B83: 30424128101925 | C83: Jessie Relojero Gromio | D83: ADCB | E83: AE020030012669209920001 | F83: 01-12-2024 | G83: 31-12-2024 | H83: 31 | I83: 3000 | J83: =+N83-O83 -> 0 | K83: 6 | L83: =+I83 -> 3000 | M83: 0 | N83: 0 | O83: 0 | P83: =+L83+N83-O83 -> 3000 | Q83: indirect
A84: SAL | B84: 30409088991714 | C84: Dieryl Patricio Mayor | D84: 600310101 | E84: AE830030011859755910001 | F84: 01-12-2024 | G84: 31-12-2024 | H84: 31 | I84: 4500 | J84: =+N84-O84 -> 0 | K84: 0 | L84: =+I84 -> 4500 | M84: 0 | N84: 0 | O84: 0 | P84: =+L84+N84-O84 -> 4500 | Q84: indirect
A85: SAL | B85: 00404030007288 | C85: OMAR MOHAMAD ALZARKAN | D85: 405010101 | E85: AE320500000000028892691 | F85: 01-12-2024 | G85: 31-12-2024 | H85: 31 | I85: 8000 | J85: =+N85-O85 -> 0 | K85: 0 | L85: =+I85 -> 8000 | M85: 0 | N85: 0 | O85: 0 | P85: =+L85+N85-O85 -> 8000 | Q85: indirect
A86: SAL | B86: 10022079255954 | C86: SHABNA JAMAL JAMALUDEEN PULAKKAVEETTIL KUNJUMOHAMED | D86: 302620122 | E86: AE150260000959069080601 | F86: 01-12-2024 | G86: 31-12-2024 | H86: 31 | I86: 4500 | J86: =+N86-O86 -> 0 | K86: 0 | L86: =+I86 -> 4500 | M86: 0 | N86: 0 | O86: 0 | P86: =+L86+N86-O86 -> 4500 | Q86: indirect
A87: SAL | B87: 00124128828013 | C87: Mohammed Hassan Labib | D87: 302620122 | E87: AE280260000215772050501 | F87: 01-12-2024 | G87: 31-12-2024 | H87: 31 | I87: 5000 | J87: =M87+N87-O87 -> 0 | K87: 0 | L87: =+I87 -> 5000 | M87: 0 | N87: 0 | O87: 0 | P87: =+L87+N87-O87 -> 5000 | Q87: indirect
A88: SAL | B88: 30423098879653 | C88: JENNIFER MANARANG IGLESIA | D88: 600310101 | E88: AE430030012236271910001 | F88: 01-12-2024 | G88: 31-12-2024 | H88: 31 | I88: 5500 | J88: =M88+N88-O88 -> 0 | K88: 0 | L88: =+I88 -> 5500 | M88: 0 | N88: 0 | O88: 0 | P88: =+L88+N88-O88 -> 5500 | Q88: Nurse Direct
A89: SAL | B89: 30407037356924 | C89: HELEN GUEVARRA | D89: 105310101 | E89: AE510530000015891288001 | F89: 01-12-2024 | G89: 31-12-2024 | H89: 31 | I89: 3500 | J89: =M89+N89-O89 -> 0 | K89: 0 | L89: =+I89 -> 3500 | M89: 0 | N89: 0 | O89: 0 | P89: =+L89+N89-O89 -> 3500 | Q89: indirect
A90: SAL | B90: 10023099650891 | C90: MOBY ANTONY ANTONY | D90: 600310101 | E90: AE270030011324999910001 | F90: 01-12-2024 | G90: 31-12-2024 | H90: =31-10 -> 21 | I90: 3000 | J90: =M90+N90-O90 -> -900 | K90: 0 | L90: =+I90 -> 3000 | M90: 0 | N90: 0 | O90: 900 | P90: =+L90+N90-O90 -> 2100 | Q90: indirect
A91: SAL | B91: 10006059728355 | C91: AASIYA SIDDIQA PASHA | D91: 600310101 | E91: AE810030011876537920001 | F91: 01-12-2024 | G91: 31-12-2024 | H91: 31 | I91: 3500 | J91: =M91+N91-O91 -> 0 | K91: 0 | L91: =+I91 -> 3500 | M91: 0 | N91: 0 | O91: 0 | P91: =+L91+N91-O91 -> 3500 | Q91: indirect
A92: SAL | C92: Elbie Cristobal | F92: 01-12-2024 | G92: 31-12-2024 | P92: 2250 | Q92: Nurse Direct
A93: SAL | C93: Hadi Khalil | F93: 01-12-2024 | G93: 31-12-2024 | P93: 1355 | Q93: indirect
A94: SAL | C94: Mahmoud Badran | F94: 01-12-2024 | G94: 31-12-2024 | P94: 1500 | Q94: indirect

Sheet Income Raw Data
A1: Cashier List2025-01-01 - 2025-01-31
A2: Date | B2: Bill Date | C2: Unit | D2: Host / Agent | E2: Doctor | F2: Chart | G2: Patient Name | H2: Payer | I2: INV / FP / Bill No. | J2: Payment Status | K2: Payment Type | L2: Gross Amount | M2: Additional Discount | N2: Gross INS Share | O2: Net INS Share | P2: Net INS Share VAT | Q2: Net INS Share VATable Amount | R2: Gross PT Share | S2: Net PT Share | T2: Net PT Share VAT | U2: Net PT Share VATable Amount | V2: SUM [INS Share + PT Share] | W2: SUM VAT | X2: SUM VATable Amount | Y2: Old INV Payment | Z2: Current Payment | AA2: Advance Payment | AB2: Total Oustanding Balance | AC2: Next Appointment Type | AD2: Visit Status | AE2: Clinic Notes | AF2: INS/SLF Notes
A3: 45676 | B3: --- | C3: 12th Floor | D3: Shaimaa | E3: Dr. Ammar | F3: 35486 | G3: Erika Lessmann | H3: 06- SelfPay Direct | I3: --- | J3: --- | K3: 00- Pending Invoice Generation | L3: 0 | M3: 0 | N3: 0 | O3: 0 | P3: 0 | Q3: 0 | R3: 0 | S3: 0 | T3: 0 | U3: 0 | V3: 0 | W3: 0 | X3: 0 | Y3: 0 | Z3: 0 | AA3: 0 | AB3: 0 | AC3: 01.4- New Diagnosis after 6 months | AD3: 03- Waiting > 10 minutes | AE3: Clinic Notes: restoration #11 Next Clinic Notes: continue treatment with VIP when due for impression | AF3: Choose A1 B1 C1 F1 R1
A4: 45682 | B4: --- | C4: 12th Floor | D4: Hassan | E4: Dr. Hussien | F4: 38491 | G4: Ilian Nikolov Nikolov | H4: 06- SelfPay Direct | I4: --- | J4: --- | K4: 00- Pending Invoice Generation | L4: 0 | M4: 0 | N4: 0 | O4: 0 | P4: 0 | Q4: 0 | R4: 0 | S4: 0 | T4: 0 | U4: 0 | V4: 0 | W4: 0 | X4: 0 | Y4: 0 | Z4: 0 | AA4: 0 | AB4: 0 | AC4: 05.M- Surgical Miscellaneous (post surgery care, | AD4: 04- Discharged | AE4: Clinic Notes: Surgical extraction #13,16,17 and implants #13,15 with GTR/GRAFT/STENT/GUIDE Under Nitrous Oxide , OPG 1) Wound irrigation #13,15,16 ,17 after 3 days with IV infusion of ceftriaxone , paracetamol and dexamethasone - VIP Clinic 2 - 3 units 2) Wound irrigation #13,15,16 ,17 after 5 days- VIP Clinic 2 - 1 unit 3) Suture removal # 13,15,16,17 after 12 days - VIP Clinic 1 - 1 unit Next Clinic Notes: 1) Wound irrigation #13,15,16 ,17 after 3 days with IV infusion of ceftriaxone , paracetamol and dexamethasone - VIP Clinic 2 - 3 units 2) Wound irrigation #13,15,16 ,17 after 5 days- VIP Clinic 2 - 1 unit 3) Suture removal # 13,15,16,17 after 12 days - VIP Clinic 1 - 1 unit | AF4: Choose A1 B1 C1 F1 R1
A5: 45687 | B5: --- | C5: 12th Floor | D5: --- | E5: Dr. Hussien | F5: 41061 | G5: Mohammed Hamad Sultan Alkhouri Alnaqbi | H5: 06- SelfPay Direct | I5: --- | J5: --- | K5: 00- Pending Invoice Generation | L5: 0 | M5: 0 | N5: 0 | O5: 0 | P5: 0 | Q5: 0 | R5: 0 | S5: 0 | T5: 0 | U5: 0 | V5: 0 | W5: 0 | X5: 0 | Y5: 0 | Z5: 0 | AA5: 0 | AB5: 0 | AC5: 05.M- Surgical Miscellaneous (post surgery care, | AD5: 02- Checked-out | AE5: Clinic Notes: Examination , CBCT , surgical extraction #30 , cyst removal #30 , bone augmentation under nitrous oxide Next Clinic Notes: 1) Patient can come for post surgical care either after 4,5 days or on the 12th day for suture removal # 30 ( depending on the availability, as the patient is coming from RAK ) - 1 unit 2) Implant planning # 30 after 3 months ( must have scaling visit with GP same day visit with VIP Clinic ) - VIP Clinic - 2 units | AF5: Choose A1 B1 C1 F1 R1
A6: 45679 | B6: 45679 | C6: 12th Floor | D6: Hassan | E6: Dr. Hussien | F6: 38338 | G6: Seham Ahmad Suleiman Deekh | H6: NA | I6: INV118429 | J6: Debit / credit Card | K6: 04- Partially Paid / Old Collection | L6: 0 | M6: 0 | N6: 0 | O6: 0 | P6: 0 | Q6: 0 | R6: 0 | S6: 0 | T6: 0 | U6: 0 | V6: 0 | W6: 0 | X6: 0 | Y6: 6226.11 | Z6: 0 | AA6: 0 | AB6: 0 | AC6: --- | AD6: --- | AE6: Clinic Notes: --- Next Clinic Notes: --- | AF6: Choose A1 B1 C1 F1 R1
A7: 45685 | B7: 45685 | C7: 12th Floor | D7: Kae | E7: Dr. Hussien | F7: 37776 | G7: Richelle Bacus Mangundaya | H7: NA | I7: INV117124 | J7: Debit / credit Card | K7: 04- Partially Paid / Old Collection | L7: 0 | M7: 0 | N7: 0 | O7: 0 | P7: 0 | Q7: 0 | R7: 0 | S7: 0 | T7: 0 | U7: 0 | V7: 0 | W7: 0 | X7: 0 | Y7: 3503.07 | Z7: 0 | AA7: 0 | AB7: 0 | AC7: --- | AD7: --- | AE7: Clinic Notes: --- Next Clinic Notes: --- | AF7: Choose A1 B1 C1 F1 R1
A8: 45688 | B8: 45688 | C8: 13th Floor | D8: Kae | E8: Dr. Amr | F8: 35763 | G8: Mostafa Mohamed Abdulhamid Shabaan | H8: NA | I8: INV77723 | J8: Debit / credit Card | K8: 04- Partially Paid / Old Collection | L8: 0 | M8: 0 | N8: 0 | O8: 0 | P8: 0 | Q8: 0 | R8: 0 | S8: 0 | T8: 0 | U8: 0 | V8: 0 | W8: 0 | X8: 0 | Y8: 618 | Z8: 0 | AA8: 0 | AB8: 0 | AC8: --- | AD8: --- | AE8: Clinic Notes: --- Next Clinic Notes: --- | AF8: Choose A1 B1 C1 F1 R1
A9: 45662 | B9: --- | C9: NA | D9: Hassan | E9: --- | F9: 35486 | G9: Erika Lessmann | H9: NA | I9: 44216 | J9: Debit / credit Card | K9: NA | L9: 0 | M9: 0 | N9: 0 | O9: 0 | P9: 0 | Q9: 0 | R9: 0 | S9: 0 | T9: 0 | U9: 0 | V9: 0 | W9: 0 | X9: 0 | Y9: 0 | Z9: 0 | AA9: 4422.16 | AB9: 0 | AC9: --- | AD9: --- | AE9: Clinic Notes: --- Next Clinic Notes: --- | AF9: Choose A1 B1 C1 F1 R1
A10: 45671 | B10: --- | C10: NA | D10: Hassan | E10: --- | F10: 40475 | G10: Jhulee Anne Raymundo Arias | H10: NA | I10: 44971 | J10: Debit / credit Card | K10: NA | L10: 0 | M10: 0 | N10: 0 | O10: 0 | P10: 0 | Q10: 0 | R10: 0 | S10: 0 | T10: 0 | U10: 0 | V10: 0 | W10: 0 | X10: 0 | Y10: 0 | Z10: 0 | AA10: 1349.57 | AB10: 0 | AC10: --- | AD10: --- | AE10: Clinic Notes: --- Next Clinic Notes: --- | AF10: Choose A1 B1 C1 F1 R1
A11: 45676 | B11: --- | C11: NA | D11: Hassan | E11: --- | F11: 39157 | G11: Nuha Mohamed Amri | H11: NA | I11: 45353 | J11: Debit / credit Card | K11: NA | L11: 0 | M11: 0 | N11: 0 | O11: 0 | P11: 0 | Q11: 0 | R11: 0 | S11: 0 | T11: 0 | U11: 0 | V11: 0 | W11: 0 | X11: 0 | Y11: 0 | Z11: 0 | AA11: 470 | AB11: 230.12 | AC11: --- | AD11: --- | AE11: Clinic Notes: --- Next Clinic Notes: --- | AF11: Choose A1 B1 C1 F1 R1
A12: 45676 | B12: --- | C12: NA | D12: Hassan | E12: --- | F12: 41005 | G12: Hanan M Shaker Shneineh | H12: NA | I12: 45382 | J12: Cash | K12: NA | L12: 0 | M12: 0 | N12: 0 | O12: 0 | P12: 0 | Q12: 0 | R12: 0 | S12: 0 | T12: 0 | U12: 0 | V12: 0 | W12: 0 | X12: 0 | Y12: 0 | Z12: 0 | AA12: 200 | AB12: 0 | AC12: --- | AD12: --- | AE12: Clinic Notes: --- Next Clinic Notes: --- | AF12: Choose A1 B1 C1 F1 R1
A13: 45679 | B13: --- | C13: NA | D13: Hassan | E13: --- | F13: 39157 | G13: Nuha Mohamed Amri | H13: NA | I13: 45742 | J13: Debit / credit Card | K13: NA | L13: 0 | M13: 0 | N13: 0 | O13: 0 | P13: 0 | Q13: 0 | R13: 0 | S13: 0 | T13: 0 | U13: 0 | V13: 0 | W13: 0 | X13: 0 | Y13: 0 | Z13: 0 | AA13: 68.42 | AB13: 230.12 | AC13: --- | AD13: --- | AE13: Clinic Notes: --- Next Clinic Notes: --- | AF13: Choose A1 B1 C1 F1 R1
A14: 45679 | B14: --- | C14: NA | D14: Dieryl | E14: --- | F14: 9000009 | G14: HELLO WORLD | H14: NA | I14: 45755 | J14: Cash | K14: NA | L14: 0 | M14: 0 | N14: 0 | O14: 0 | P14: 0 | Q14: 0 | R14: 0 | S14: 0 | T14: 0 | U14: 0 | V14: 0 | W14: 0 | X14: 0 | Y14: 0 | Z14: 0 | AA14: 100 | AB14: 273 | AC14: --- | AD14: --- | AE14: Clinic Notes: --- Next Clinic Notes: --- | AF14: Choose A1 B1 C1 F1 R1
A15: 45679 | B15: --- | C15: NA | D15: Hassan | E15: --- | F15: 38338 | G15: Seham Ahmad Suleiman Deekh | H15: NA | I15: 45869 | J15: Debit / credit Card | K15: NA | L15: 0 | M15: 0 | N15: 0 | O15: 0 | P15: 0 | Q15: 0 | R15: 0 | S15: 0 | T15: 0 | U15: 0 | V15: 0 | W15: 0 | X15: 0 | Y15: 0 | Z15: 0 | AA15: 2243.52 | AB15: 0 | AC15: --- | AD15: --- | AE15: Clinic Notes: --- Next Clinic Notes: --- | AF15: Choose A1 B1 C1 F1 R1
A16: 45658 | B16: 45658 | C16: 12th Floor | D16: Hassan | E16: Dr. Hussien | F16: 34366 | G16: RAYA ALI HMOUD | H16: 01- Thiqa / E001 | I16: 43946 | J16: Cash | K16: 02- Claims Sent Not Remitted | L16: 350 | M16: 0 | N16: 350 | O16: 350 | P16: 0 | Q16: 0 | R16: 0 | S16: 0 | T16: 0 | U16: 0 | V16: 350 | W16: 0 | X16: 0 | Y16: 0 | Z16: 0 | AA16: 0 | AB16: 0 | AC16: 01.2- Consultation (Existing patient) | AD16: 04- Discharged | AE16: Clinic Notes: Examination, OPG, direct repair Next Clinic Notes: - Referred to Dr Salim for Scaling and replacement of restoration/Query RCT #18 - New diagnosis after 6 months - VIP - 2 units(must have scaling with GP) | AF16: Choose A1 B1 C1 F1 R1
A17: 45658 | B17: 45658 | C17: 13th Floor | D17: Rami | E17: Dr. Salim | F17: 38069 | G17: Maram Rawhi Raouf Alsadi | H17: 02- Daman / A001 | I17: 43949 | J17: Debit / credit Card | K17: 02- Claims Sent Not Remitted | L17: 150 | M17: 0 | N17: 120 | O17: 120 | P17: 0 | Q17: 0 | R17: 30 | S17: 30 | T17: 0 | U17: 0 | V17: 150 | W17: 0 | X17: 0 | Y17: 0 | Z17: 30 | AA17: 0 | AB17: 0 | AC17: 03.0- Direct Restorative/ Simple | AD17: 04- Discharged | AE17: Clinic Notes: consultation and scaling Next Clinic Notes: direct restoration #17 (3 unit)(limited mouth opening) | AF17: Choose A1 B1 C1 F1 R1
A18: 45658 | B18: 45658 | C18: 13th Floor | D18: Rami | E18: Dr. Salim | F18: 38069 | G18: Maram Rawhi Raouf Alsadi | H18: 06- SelfPay Direct | I18: 43951 | J18: Debit / credit Card | K18: 02- Claims Sent Not Remitted | L18: 195.52 | M18: 0 | N18: 0 | O18: 0 | P18: 0 | Q18: 0 | R18: 195.52 | S18: 195.52 | T18: 0 | U18: 0 | V18: 195.52 | W18: 0 | X18: 0 | Y18: 0 | Z18: 195.52 | AA18: 0 | AB18: 0 | AC18: 03.0- Direct Restorative/ Simple | AD18: 04- Discharged | AE18: Clinic Notes: consultation and scaling Next Clinic Notes: direct restoration #17 (3 unit)(limited mouth opening) | AF18: Choose A1 B1 C1 F1 R1
A19: 45658 | B19: 45658 | C19: 13th Floor | D19: Rami | E19: Dr. Salim | F19: 40891 | G19: Diala Ziad Mohamed Abu Amsha | H19: 06- SelfPay Direct | I19: 43960 | J19: Cash | K19: 02- Claims Sent Not Remitted | L19: 0 | M19: 0 | N19: 0 | O19: 0 | P19: 0 | Q19: 0 | R19: 0 | S19: 0 | T19: 0 | U19: 0 | V19: 0 | W19: 0 | X19: 0 | Y19: 0 | Z19: 0 | AA19: 0 | AB19: 0 | AC19: 04.1- RCT / Anterior tooth + Endo crown Prep. | AD19: 04- Discharged | AE19: Clinic Notes: temporary restoration #9 Next Clinic Notes: RCT #7,8,9,10 ( 6 unit) | AF19: Choose A1 B1 C1 F1 R1
A20: 45658 | B20: 45662 | C20: 13th Floor | D20: Joel | E20: Dr. Ibrahim | F20: 40921 | G20: Ahmed Ali Ahmed Ali Elnaggar | H20: 06- SelfPay Direct | I20: 43961 | J20: Debit / credit Card | K20: 02- Claims Sent Not Remitted | L20: 195.52 | M20: 0 | N20: 0 | O20: 0 | P20: 0 | Q20: 0 | R20: 195.52 | S20: 195.52 | T20: 0 | U20: 0 | V20: 195.52 | W20: 0 | X20: 0 | Y20: 0 | Z20: 195.52 | AA20: 0 | AB20: 0 | AC20: 03.1- Restorative / Compound | AD20: 04- Discharged | AE20: Clinic Notes: Scaling and polishing Next Clinic Notes: Restoration #17 | AF20: Choose A1 B1 C1 F1 R1
A21: 45658 | B21: 45658 | C21: 12th Floor | D21: Hassan | E21: Dr. Hussien | F21: 39290 | G21: Obaid Mohammed Abdulla Hamad Almansoori | H21: 01- Thiqa / E001 | I21: 43963 | J21: Cash | K21: 02- Claims Sent Not Remitted | L21: 35 | M21: 0 | N21: 35 | O21: 35 | P21: 0 | Q21: 0 | R21: 0 | S21: 0 | T21: 0 | U21: 0 | V21: 35 | W21: 0 | X21: 0 | Y21: 0 | Z21: 0 | AA21: 0 | AB21: 0 | AC21: 09.9- Implant Crown Delivery - Complex (6 -10) | AD21: 04- Discharged | AE21: Clinic Notes: lower arch impression Next Clinic Notes: Lower implant bridge delivery - after 2 weeks - 4 units | AF21: Choose A1 B1 C1 F1 R1
A22: 45658 | B22: 45658 | C22: 13th Floor | D22: Rami | E22: Dr. Salim | F22: 36452 | G22: Alp Idil Jones | H22: 03- ADNIC / A002 | I22: 43966 | J22: Debit / credit Card | K22: 02- Claims Sent Not Remitted | L22: 871.5 | M22: 0 | N22: 697.2 | O22: 697.2 | P22: 0 | Q22: 0 | R22: 174.3 | S22: 174.3 | T22: 0 | U22: 0 | V22: 871.5 | W22: 0 | X22: 0 | Y22: 0 | Z22: 174.3 | AA22: 0 | AB22: 0 | AC22: 06.3- Inlay / Crown Delivery - Simple (1-2) | AD22: 04- Discharged | AE22: Clinic Notes: crown removal and post and core and restoration #29 Next Clinic Notes: crown delivery #29(3 unit) | AF22: Choose A1 B1 C1 F1 R1
A23: 45658 | B23: --- | C23: 13th Floor | D23: Rami | E23: Dr. Salim | F23: 36452 | G23: Alp Idil Jones | H23: 06- SelfPay Direct | I23: 43970 | J23: --- | K23: 02- Claims Sent Not Remitted | L23: 311.85 | M23: 311.85 | N23: 0 | O23: 0 | P23: 0 | Q23: 0 | R23: 311.85 | S23: 0 | T23: 0 | U23: 0 | V23: 0 | W23: 0 | X23: 0 | Y23: 0 | Z23: 0 | AA23: 0 | AB23: 0 | AC23: 06.3- Inlay / Crown Delivery - Simple (1-2) | AD23: 04- Discharged | AE23: Clinic Notes: crown removal and post and core and restoration #29 Next Clinic Notes: crown delivery #29(3 unit) | AF23: Choose A1 B1 C1 F1 R1
A24: 45658 | B24: 45658 | C24: 13th Floor | D24: Rami | E24: Dr. Salim | F24: 40447 | G24: Syed Danial Hussain Syed Ishaq Hussain | H24: 06- SelfPay Direct | I24: 43979 | J24: Cash | K24: 02- Claims Sent Not Remitted | L24: 51.98 | M24: 51.98 | N24: 0 | O24: 0 | P24: 0 | Q24: 0 | R24: 51.98 | S24: 0 | T24: 0 | U24: 0 | V24: 0 | W24: 0 | X24: 0 | Y24: 0 | Z24: 0 | AA24: 0 | AB24: 30 | AC24: 01.2- Consultation (Existing patient) | AD24: 04- Discharged | AE24: Clinic Notes: follow up photograph Next Clinic Notes: follow up after 4-5 days (1 unit) | AF24: Choose A1 B1 C1 F1 R1
A25: 45658 | B25: 45658 | C25: 13th Floor | D25: Rami | E25: Dr. Salim | F25: 34527 | G25: DR. NAWAL AL KHALIDI | H25: 06- SelfPay Direct | I25: 43983 | J25: Cash | K25: 02- Claims Sent Not Remitted | L25: 0 | M25: 0 | N25: 0 | O25: 0 | P25: 0 | Q25: 0 | R25: 0 | S25: 0 | T25: 0 | U25: 0 | V25: 0 | W25: 0 | X25: 0 | Y25: 0 | Z25: 0 | AA25: 0 | AB25: 0 | AC25: 01.4- New Diagnosis after 6 months | AD25: 04- Discharged | AE25: Clinic Notes: re cementation #3 Next Clinic Notes: new diagnosis | AF25: Choose A1 B1 C1 F1 R1
A26: 45658 | B26: 45658 | C26: 13th Floor | D26: Rami | E26: Dr. Ibrahim | F26: 37518 | G26: Mohammed Abdulla Fairooz Mohammed Alblooshi | H26: 01- Thiqa / E001 | I26: 43985 | J26: Cash | K26: 02- Claims Sent Not Remitted | L26: 175 | M26: 0 | N26: 175 | O26: 175 | P26: 0 | Q26: 0 | R26: 0 | S26: 0 | T26: 0 | U26: 0 | V26: 175 | W26: 0 | X26: 0 | Y26: 0 | Z26: 0 | AA26: 0 | AB26: 0 | AC26: 01.4- New Diagnosis after 6 months | AD26: 04- Discharged | AE26: Clinic Notes: Exam, OPG scaling and polishing Next Clinic Notes: Scaling after 6 months | AF26: Choose A1 B1 C1 F1 R1
A27: 45658 | B27: 45658 | C27: 13th Floor | D27: Rami | E27: Dr. Ibrahim | F27: 37518 | G27: Mohammed Abdulla Fairooz Mohammed Alblooshi | H27: 06- SelfPay Direct | I27: 43987 | J27: Cash | K27: 02- Claims Sent Not Remitted | L27: 416 | M27: 416 | N27: 0 | O27: 0 | P27: 0 | Q27: 0 | R27: 416 | S27: 0 | T27: 0 | U27: 0 | V27: 0 | W27: 0 | X27: 0 | Y27: 0 | Z27: 0 | AA27: 0 | AB27: 0 | AC27: 01.4- New Diagnosis after 6 months | AD27: 04- Discharged | AE27: Clinic Notes: Exam, OPG scaling and polishing Next Clinic Notes: Scaling after 6 months | AF27: Choose A1 B1 C1 F1 R1
A28: 45658 | B28: 45658 | C28: 13th Floor | D28: Rami | E28: Dr. Salim | F28: 40821 | G28: Mohamed Mezaache | H28: 06- SelfPay Direct | I28: 43990 | J28: Debit / credit Card | K28: 02- Claims Sent Not Remitted | L28: 922.66 | M28: 393.85 | N28: 0 | O28: 0 | P28: 0 | Q28: 0 | R28: 922.66 | S28: 528.81 | T28: 0 | U28: 0 | V28: 528.81 | W28: 0 | X28: 0 | Y28: 0 | Z28: 528.81 | AA28: 0 | AB28: 0 | AC28: 06.3- Inlay / Crown Delivery - Simple (1-2) | AD28: 04- Discharged | AE28: Clinic Notes: RCT #19 restoration #20 Next Clinic Notes: Crown delivery #19 (3 unit) | AF28: Choose A1 B1 C1 F1 R1
A29: 45658 | B29: 45658 | C29: 13th Floor | D29: Rami | E29: Dr. Salim | F29: 40252 | G29: Wesley Mcgraw | H29: 07- SelfPay FP | I29: 43994 / FP1668 | J29: From Advanced Payment | K29: 04- Partially Paid / Old Collection | L29: 1385 | M29: 440 | N29: 0 | O29: 0 | P29: 0 | Q29: 0 | R29: 1385 | S29: 945 | T29: 0 | U29: 0 | V29: 945 | W29: 0 | X29: 0 | Y29: 0 | Z29: 472.5 | AA29: 0 | AB29: 0 | AC29: X.0- Internal referral | AD29: 04- Discharged | AE29: Clinic Notes: crown delivery #2 Next Clinic Notes: send back for implant #3,4 | AF29: Choose A1 B1 C1 F1 R1
A30: 45658 | B30: 45658 | C30: 13th Floor | D30: Rami | E30: Dr. Salim | F30: 40252 | G30: Wesley Mcgraw | H30: 07- SelfPay FP | I30: 43994 / FP1668 | J30: Debit / credit Card | K30: 03- Fully Paid / Remitted | L30: 0 | M30: 0 | N30: 0 | O30: 0 | P30: 0 | Q30: 0 | R30: 1385 | S30: 0 | T30: 0 | U30: 0 | V30: 0 | W30: 0 | X30: 0 | Y30: 0 | Z30: 472.5 | AA30: 0 | AB30: 0 | AC30: X.0- Internal referral | AD30: 04- Discharged | AE30: Clinic Notes: crown delivery #2 Next Clinic Notes: send back for implant #3,4 | AF30: Choose A1 B1 C1 F1 R1
A31: 45658 | B31: 45658 | C31: 13th Floor | D31: Rami | E31: Dr. Ibrahim | F31: 40934 | G31: Sarah Ahmed Ali Ahmed Alyammahi | H31: 06- SelfPay Direct | I31: 43996 | J31: Cash | K31: 02- Claims Sent Not Remitted | L31: 311.85 | M31: 311.85 | N31: 0 | O31: 0 | P31: 0 | Q31: 0 | R31: 311.85 | S31: 0 | T31: 0 | U31: 0 | V31: 0 | W31: 0 | X31: 0 | Y31: 0 | Z31: 0 | AA31: 0 | AB31: 0 | AC31: 06.3- Inlay / Crown Delivery - Simple (1-2) | AD31: 04- Discharged | AE31: Clinic Notes: Prep and impression #14 Next Clinic Notes: Crown delivery #14 Refer to Dr Hussien For implant #3 | AF31: Choose A1 B1 C1 F1 R1
